Workbook

Sheet Summary_Dashboard
F2: PAYROLL DASHBOARD | لوحة الرواتب
F4: ="Elite Development · "&IF($K$5="All Months","All months",TEXT($K$5,"mmmm yyyy"))&" · "&$B$8&" riders" -> Elite Development · All months · 15 riders
I5: Month filter | الشهر ▸ | K5: All Months | M5: ◂ All Months or one month | Q5: Filter start | R5: =IF($K$5="All Months",1,$K$5) -> 1
Q6: Filter end (excl.) | R6: =IF($K$5="All Months",2958465,EDATE($K$5,1)) -> 2958465
B7: TOTAL RIDERS | عدد المندوبين | E7: TOTAL GROSS SALARY | إجمالي الراتب | H7: TOTAL DEDUCTIONS | الخصومات | K7: TOTAL FINAL SALARY | صافي الرواتب
B8: =COUNTIFS(Salary_Calculation[Salary Month],">="&Dash_Start,Salary_Calculation[Salary Month],"<"&Dash_End) -> 15 | E8: =SUMIFS(Salary_Calculation[Gross Salary Before Deductions],Salary_Calculation[Salary Month],">="&Dash_Start,Salary_Calculation[Salary Month],"<"&Dash_End) -> 17676.222 | H8: =SUMIFS(Salary_Calculation[Total Deductions],Salary_Calculation[Salary Month],">="&Dash_Start,Salary_Calculation[Salary Month],"<"&Dash_End) -> 4478.75 | K8: =SUMIFS(Salary_Calculation[Final Salary],Salary_Calculation[Salary Month],">="&Dash_Start,Salary_Calculation[Salary Month],"<"&Dash_End) -> 14208.35 | Q8: Chart data
B9: ="review required: "&COUNTIFS(Salary_Calculation[Payment Status],"Review Required",Salary_Calculation[Salary Month],">="&Dash_Start,Salary_Calculation[Salary Month],"<"&Dash_End) -> review required: 0 | E9: =IFERROR("avg SAR "&TEXT(E8/$B$8,"#,##0")&" per rider","") -> avg SAR 1,178 per rider | H9: =IFERROR(TEXT(H8/E8,"0.0%")&" of gross salary","") -> 25.3% of gross salary | K9: =IFERROR("avg SAR "&TEXT(K8/$B$8,"#,##0")&" per rider","") -> avg SAR 947 per rider | Q9: Gross | R9: =E8 -> 17676.222
Q10: Deductions | R10: =H8 -> 4478.75
B11: AMOUNT DUE FROM RIDERS | مستحق على المندوبين | E11: COMPLETED ORDERS | الطلبات المكتملة | H11: MISSING ORDERS | الطلبات الناقصة | K11: EXTRA ORDERS | الطلبات الإضافية | Q11: Final salary | R11: =K8 -> 14208.35
B12: =SUMIFS(Salary_Calculation[Total Amount Due from Rider],Salary_Calculation[Salary Month],">="&Dash_Start,Salary_Calculation[Salary Month],"<"&Dash_End) -> 1026.86 | E12: =SUMIFS(Salary_Calculation[Completed Orders],Salary_Calculation[Salary Month],">="&Dash_Start,Salary_Calculation[Salary Month],"<"&Dash_End) -> 4734 | H12: =SUMIFS(Salary_Calculation[Missing Orders],Salary_Calculation[Salary Month],">="&Dash_Start,Salary_Calculation[Salary Month],"<"&Dash_End) -> 586 | K12: =SUMIFS(Salary_Calculation[Extra Orders],Salary_Calculation[Salary Month],">="&Dash_Start,Salary_Calculation[Salary Month],"<"&Dash_End) -> 130 | Q12: Due from riders | R12: =B12 -> 1026.86
B13: =COUNTIFS(Salary_Calculation[Total Amount Due from Rider],">0",Salary_Calculation[Salary Month],">="&Dash_Start,Salary_Calculation[Salary Month],"<"&Dash_End)&" rider(s) owe the company" -> 4 rider(s) owe the company | E13: =IFERROR("avg "&TEXT(E12/$B$8,"#,##0")&" per rider","") -> avg 316 per rider | H13: =COUNTIFS(Salary_Calculation[Missing Orders],">0",Salary_Calculation[Salary Month],">="&Dash_Start,Salary_Calculation[Salary Month],"<"&Dash_End)&" rider(s) below target" -> 12 rider(s) below target | K13: =COUNTIFS(Salary_Calculation[Extra Orders],">0",Salary_Calculation[Salary Month],">="&Dash_Start,Salary_Calculation[Salary Month],"<"&Dash_End)&" rider(s) earned a bonus" -> 3 rider(s) earned a bonus
B15: =IF(COUNTIFS(Salary_Calculation[Payment Status],"Review Required",Salary_Calculation[Salary Month],">="&Dash_Start,Salary_Calculation[Salary Month],"<"&Dash_End)=0,"✔ All records valid – no exceptions","⚠ "&COUNTIFS(Salary_Calculation[Payment Status],"Review Required",Salary_Calculation[Salary Month],">="&Dash_Start,Salary_Calculation[Salary Month],"<"&Dash_End)&" record(s) require review – see the Exception Report below") -> ✔ All records valid – no exceptions
B17: PAYROLL COMPOSITION | تكوين الرواتب | H17: PAYMENT STATUS | حالات الدفع
B33: STATUS BREAKDOWN | توزيع الحالات | H33: TOP 10 BY FINAL SALARY | أعلى ١٠ رواتب
B34: Status | E34: Riders | F34: Share | H34: # | I34: Rider ID | J34: Rider Name | L34: Final Salary | M34: Orders | Q34: Top-10 row index
B35: Paid in Full | E35: =COUNTIFS(Salary_Calculation[Payment Status],$B35,Salary_Calculation[Salary Month],">="&Dash_Start,Salary_Calculation[Salary Month],"<"&Dash_End) -> 0 | F35: =IF($B$8=0,0,E35/$B$8) -> 0 | H35: =IF($R35="","",1) -> 1 | I35: =IF($R35="","",INDEX(Payslip_Lookup[Rider ID],$R35)) -> 4648308 | J35: =IF($R35="","",INDEX(Payslip_Lookup[Rider Name],$R35)) -> Rider 4648308 | L35: =IF($R35="","",INDEX(Payslip_Lookup[Final Salary],$R35)) -> 2721.55 | M35: =IF($R35="","",INDEX(Payslip_Lookup[Completed Orders],$R35)) -> 551 | R35: =IFERROR(MATCH(LARGE(Payslip_Data!$AM$2:$AM$501,1),Payslip_Data!$AM$2:$AM$501,0),"") -> 11
B36: Paid After Deductions | E36: =COUNTIFS(Salary_Calculation[Payment Status],$B36,Salary_Calculation[Salary Month],">="&Dash_Start,Salary_Calculation[Salary Month],"<"&Dash_End) -> 11 | F36: =IF($B$8=0,0,E36/$B$8) -> 0.73333333 | H36: =IF($R36="","",2) -> 2 | I36: =IF($R36="","",INDEX(Payslip_Lookup[Rider ID],$R36)) -> 4747290 | J36: =IF($R36="","",INDEX(Payslip_Lookup[Rider Name],$R36)) -> Rider 4747290 | L36: =IF($R36="","",INDEX(Payslip_Lookup[Final Salary],$R36)) -> 2240.64 | M36: =IF($R36="","",INDEX(Payslip_Lookup[Completed Orders],$R36)) -> 498 | R36: =IFERROR(MATCH(LARGE(Payslip_Data!$AM$2:$AM$501,2),Payslip_Data!$AM$2:$AM$501,0),"") -> 7
B37: No Salary – Amount Due from Rider | E37: =COUNTIFS(Salary_Calculation[Payment Status],$B37,Salary_Calculation[Salary Month],">="&Dash_Start,Salary_Calculation[Salary Month],"<"&Dash_End) -> 4 | F37: =IF($B$8=0,0,E37/$B$8) -> 0.26666667 | H37: =IF($R37="","",3) -> 3 | I37: =IF($R37="","",INDEX(Payslip_Lookup[Rider ID],$R37)) -> 4611383 | J37: =IF($R37="","",INDEX(Payslip_Lookup[Rider Name],$R37)) -> Rider 4611383 | L37: =IF($R37="","",INDEX(Payslip_Lookup[Final Salary],$R37)) -> 1848.27 | M37: =IF($R37="","",INDEX(Payslip_Lookup[Completed Orders],$R37)) -> 476 | R37: =IFERROR(MATCH(LARGE(Payslip_Data!$AM$2:$AM$501,3),Payslip_Data!$AM$2:$AM$501,0),"") -> 15
B38: No Orders | E38: =COUNTIFS(Salary_Calculation[Payment Status],$B38,Salary_Calculation[Salary Month],">="&Dash_Start,Salary_Calculation[Salary Month],"<"&Dash_End) -> 0 | F38: =IF($B$8=0,0,E38/$B$8) -> 0 | H38: =IF($R38="","",4) -> 4 | I38: =IF($R38="","",INDEX(Payslip_Lookup[Rider ID],$R38)) -> 4643856 | J38: =IF($R38="","",INDEX(Payslip_Lookup[Rider Name],$R38)) -> Rider 4643856 | L38: =IF($R38="","",INDEX(Payslip_Lookup[Final Salary],$R38)) -> 1675.29 | M38: =IF($R38="","",INDEX(Payslip_Lookup[Completed Orders],$R38)) -> 449 | R38: =IFERROR(MATCH(LARGE(Payslip_Data!$AM$2:$AM$501,4),Payslip_Data!$AM$2:$AM$501,0),"") -> 13
B39: Review Required | E39: =COUNTIFS(Salary_Calculation[Payment Status],$B39,Salary_Calculation[Salary Month],">="&Dash_Start,Salary_Calculation[Salary Month],"<"&Dash_End) -> 0 | F39: =IF($B$8=0,0,E39/$B$8) -> 0 | H39: =IF($R39="","",5) -> 5 | I39: =IF($R39="","",INDEX(Payslip_Lookup[Rider ID],$R39)) -> 4642935 | J39: =IF($R39="","",INDEX(Payslip_Lookup[Rider Name],$R39)) -> Rider 4642935 | L39: =IF($R39="","",INDEX(Payslip_Lookup[Final Salary],$R39)) -> 1602.49 | M39: =IF($R39="","",INDEX(Payslip_Lookup[Completed Orders],$R39)) -> 442 | R39: =IFERROR(MATCH(LARGE(Payslip_Data!$AM$2:$AM$501,5),Payslip_Data!$AM$2:$AM$501,0),"") -> 14
H40: =IF($R40="","",6) -> 6 | I40: =IF($R40="","",INDEX(Payslip_Lookup[Rider ID],$R40)) -> 4652654 | J40: =IF($R40="","",INDEX(Payslip_Lookup[Rider Name],$R40)) -> Rider 4652654 | L40: =IF($R40="","",INDEX(Payslip_Lookup[Final Salary],$R40)) -> 1454.79 | M40: =IF($R40="","",INDEX(Payslip_Lookup[Completed Orders],$R40)) -> 433 | R40: =IFERROR(MATCH(LARGE(Payslip_Data!$AM$2:$AM$501,6),Payslip_Data!$AM$2:$AM$501,0),"") -> 8
H41: =IF($R41="","",7) -> 7 | I41: =IF($R41="","",INDEX(Payslip_Lookup[Rider ID],$R41)) -> 4648709 | J41: =IF($R41="","",INDEX(Payslip_Lookup[Rider Name],$R41)) -> Rider 4648709 | L41: =IF($R41="","",INDEX(Payslip_Lookup[Final Salary],$R41)) -> 877.6 | M41: =IF($R41="","",INDEX(Payslip_Lookup[Completed Orders],$R41)) -> 391 | R41: =IFERROR(MATCH(LARGE(Payslip_Data!$AM$2:$AM$501,7),Payslip_Data!$AM$2:$AM$501,0),"") -> 10
H42: =IF($R42="","",8) -> 8 | I42: =IF($R42="","",INDEX(Payslip_Lookup[Rider ID],$R42)) -> 4644774 | J42: =IF($R42="","",INDEX(Payslip_Lookup[Rider Name],$R42)) -> Rider 4644774 | L42: =IF($R42="","",INDEX(Payslip_Lookup[Final Salary],$R42)) -> 617.8 | M42: =IF($R42="","",INDEX(Payslip_Lookup[Completed Orders],$R42)) -> 367 | R42: =IFERROR(MATCH(LARGE(Payslip_Data!$AM$2:$AM$501,8),Payslip_Data!$AM$2:$AM$501,0),"") -> 12
H43: =IF($R43="","",9) -> 9 | I43: =IF($R43="","",INDEX(Payslip_Lookup[Rider ID],$R43)) -> 4652587 | J43: =IF($R43="","",INDEX(Payslip_Lookup[Rider Name],$R43)) -> Rider 4652587 | L43: =IF($R43="","",INDEX(Payslip_Lookup[Final Salary],$R43)) -> 555.86 | M43: =IF($R43="","",INDEX(Payslip_Lookup[Completed Orders],$R43)) -> 382 | R43: =IFERROR(MATCH(LARGE(Payslip_Data!$AM$2:$AM$501,9),Payslip_Data!$AM$2:$AM$501,0),"") -> 9
H44: =IF($R44="","",10) -> 10 | I44: =IF($R44="","",INDEX(Payslip_Lookup[Rider ID],$R44)) -> 4844480 | J44: =IF($R44="","",INDEX(Payslip_Lookup[Rider Name],$R44)) -> Rider 4844480 | L44: =IF($R44="","",INDEX(Payslip_Lookup[Final Salary],$R44)) -> 363.5 | M44: =IF($R44="","",INDEX(Payslip_Lookup[Completed Orders],$R44)) -> 150 | R44: =IFERROR(MATCH(LARGE(Payslip_Data!$AM$2:$AM$501,10),Payslip_Data!$AM$2:$AM$501,0),"") -> 4
B47: EXCEPTION REPORT | تقرير الاستثناءات – invalid or incomplete records (all months)
B48: =COUNTIF(Payslip_Lookup[Payment Status],"Review Required")&" record(s) need review"&IF(COUNTIF(Payslip_Lookup[Payment Status],"Review Required")>25," (first 25 shown – filter Salary_Calculation on Payment Status for all)","") -> 0 record(s) need review
B49: # | C49: Rider ID | D49: Month | E49: Rider Name | G49: Reason | السبب
B50: =IF(1<=COUNTIF(Payslip_Lookup[Payment Status],"Review Required"),1,"") | C50: =IF($B50="","",INDEX(Payslip_Lookup[Rider ID],MATCH($B50,Payslip_Lookup[Exception Seq],0))) | D50: =IF($B50="","",INDEX(Payslip_Lookup[Salary Month],MATCH($B50,Payslip_Lookup[Exception Seq],0))) | E50: =IF($B50="","",INDEX(Payslip_Lookup[Rider Name],MATCH($B50,Payslip_Lookup[Exception Seq],0))) | G50: =IF($B50="","",INDEX(Payslip_Lookup[Exception Reason],MATCH($B50,Payslip_Lookup[Exception Seq],0)))
B51: =IF(2<=COUNTIF(Payslip_Lookup[Payment Status],"Review Required"),2,"") | C51: =IF($B51="","",INDEX(Payslip_Lookup[Rider ID],MATCH($B51,Payslip_Lookup[Exception Seq],0))) | D51: =IF($B51="","",INDEX(Payslip_Lookup[Salary Month],MATCH($B51,Payslip_Lookup[Exception Seq],0))) | E51: =IF($B51="","",INDEX(Payslip_Lookup[Rider Name],MATCH($B51,Payslip_Lookup[Exception Seq],0))) | G51: =IF($B51="","",INDEX(Payslip_Lookup[Exception Reason],MATCH($B51,Payslip_Lookup[Exception Seq],0)))
B52: =IF(3<=COUNTIF(Payslip_Lookup[Payment Status],"Review Required"),3,"") | C52: =IF($B52="","",INDEX(Payslip_Lookup[Rider ID],MATCH($B52,Payslip_Lookup[Exception Seq],0))) | D52: =IF($B52="","",INDEX(Payslip_Lookup[Salary Month],MATCH($B52,Payslip_Lookup[Exception Seq],0))) | E52: =IF($B52="","",INDEX(Payslip_Lookup[Rider Name],MATCH($B52,Payslip_Lookup[Exception Seq],0))) | G52: =IF($B52="","",INDEX(Payslip_Lookup[Exception Reason],MATCH($B52,Payslip_Lookup[Exception Seq],0)))
B53: =IF(4<=COUNTIF(Payslip_Lookup[Payment Status],"Review Required"),4,"") | C53: =IF($B53="","",INDEX(Payslip_Lookup[Rider ID],MATCH($B53,Payslip_Lookup[Exception Seq],0))) | D53: =IF($B53="","",INDEX(Payslip_Lookup[Salary Month],MATCH($B53,Payslip_Lookup[Exception Seq],0))) | E53: =IF($B53="","",INDEX(Payslip_Lookup[Rider Name],MATCH($B53,Payslip_Lookup[Exception Seq],0))) | G53: =IF($B53="","",INDEX(Payslip_Lookup[Exception Reason],MATCH($B53,Payslip_Lookup[Exception Seq],0)))
B54: =IF(5<=COUNTIF(Payslip_Lookup[Payment Status],"Review Required"),5,"") | C54: =IF($B54="","",INDEX(Payslip_Lookup[Rider ID],MATCH($B54,Payslip_Lookup[Exception Seq],0))) | D54: =IF($B54="","",INDEX(Payslip_Lookup[Salary Month],MATCH($B54,Payslip_Lookup[Exception Seq],0))) | E54: =IF($B54="","",INDEX(Payslip_Lookup[Rider Name],MATCH($B54,Payslip_Lookup[Exception Seq],0))) | G54: =IF($B54="","",INDEX(Payslip_Lookup[Exception Reason],MATCH($B54,Payslip_Lookup[Exception Seq],0)))
B55: =IF(6<=COUNTIF(Payslip_Lookup[Payment Status],"Review Required"),6,"") | C55: =IF($B55="","",INDEX(Payslip_Lookup[Rider ID],MATCH($B55,Payslip_Lookup[Exception Seq],0))) | D55: =IF($B55="","",INDEX(Payslip_Lookup[Salary Month],MATCH($B55,Payslip_Lookup[Exception Seq],0))) | E55: =IF($B55="","",INDEX(Payslip_Lookup[Rider Name],MATCH($B55,Payslip_Lookup[Exception Seq],0))) | G55: =IF($B55="","",INDEX(Payslip_Lookup[Exception Reason],MATCH($B55,Payslip_Lookup[Exception Seq],0)))
B56: =IF(7<=COUNTIF(Payslip_Lookup[Payment Status],"Review Required"),7,"") | C56: =IF($B56="","",INDEX(Payslip_Lookup[Rider ID],MATCH($B56,Payslip_Lookup[Exception Seq],0))) | D56: =IF($B56="","",INDEX(Payslip_Lookup[Salary Month],MATCH($B56,Payslip_Lookup[Exception Seq],0))) | E56: =IF($B56="","",INDEX(Payslip_Lookup[Rider Name],MATCH($B56,Payslip_Lookup[Exception Seq],0))) | G56: =IF($B56="","",INDEX(Payslip_Lookup[Exception Reason],MATCH($B56,Payslip_Lookup[Exception Seq],0)))
B57: =IF(8<=COUNTIF(Payslip_Lookup[Payment Status],"Review Required"),8,"") | C57: =IF($B57="","",INDEX(Payslip_Lookup[Rider ID],MATCH($B57,Payslip_Lookup[Exception Seq],0))) | D57: =IF($B57="","",INDEX(Payslip_Lookup[Salary Month],MATCH($B57,Payslip_Lookup[Exception Seq],0))) | E57: =IF($B57="","",INDEX(Payslip_Lookup[Rider Name],MATCH($B57,Payslip_Lookup[Exception Seq],0))) | G57: =IF($B57="","",INDEX(Payslip_Lookup[Exception Reason],MATCH($B57,Payslip_Lookup[Exception Seq],0)))
B58: =IF(9<=COUNTIF(Payslip_Lookup[Payment Status],"Review Required"),9,"") | C58: =IF($B58="","",INDEX(Payslip_Lookup[Rider ID],MATCH($B58,Payslip_Lookup[Exception Seq],0))) | D58: =IF($B58="","",INDEX(Payslip_Lookup[Salary Month],MATCH($B58,Payslip_Lookup[Exception Seq],0))) | E58: =IF($B58="","",INDEX(Payslip_Lookup[Rider Name],MATCH($B58,Payslip_Lookup[Exception Seq],0))) | G58: =IF($B58="","",INDEX(Payslip_Lookup[Exception Reason],MATCH($B58,Payslip_Lookup[Exception Seq],0)))
B59: =IF(10<=COUNTIF(Payslip_Lookup[Payment Status],"Review Required"),10,"") | C59: =IF($B59="","",INDEX(Payslip_Lookup[Rider ID],MATCH($B59,Payslip_Lookup[Exception Seq],0))) | D59: =IF($B59="","",INDEX(Payslip_Lookup[Salary Month],MATCH($B59,Payslip_Lookup[Exception Seq],0))) | E59: =IF($B59="","",INDEX(Payslip_Lookup[Rider Name],MATCH($B59,Payslip_Lookup[Exception Seq],0))) | G59: =IF($B59="","",INDEX(Payslip_Lookup[Exception Reason],MATCH($B59,Payslip_Lookup[Exception Seq],0)))
B60: =IF(11<=COUNTIF(Payslip_Lookup[Payment Status],"Review Required"),11,"") | C60: =IF($B60="","",INDEX(Payslip_Lookup[Rider ID],MATCH($B60,Payslip_Lookup[Exception Seq],0))) | D60: =IF($B60="","",INDEX(Payslip_Lookup[Salary Month],MATCH($B60,Payslip_Lookup[Exception Seq],0))) | E60: =IF($B60="","",INDEX(Payslip_Lookup[Rider Name],MATCH($B60,Payslip_Lookup[Exception Seq],0))) | G60: =IF($B60="","",INDEX(Payslip_Lookup[Exception Reason],MATCH($B60,Payslip_Lookup[Exception Seq],0)))
B61: =IF(12<=COUNTIF(Payslip_Lookup[Payment Status],"Review Required"),12,"") | C61: =IF($B61="","",INDEX(Payslip_Lookup[Rider ID],MATCH($B61,Payslip_Lookup[Exception Seq],0))) | D61: =IF($B61="","",INDEX(Payslip_Lookup[Salary Month],MATCH($B61,Payslip_Lookup[Exception Seq],0))) | E61: =IF($B61="","",INDEX(Payslip_Lookup[Rider Name],MATCH($B61,Payslip_Lookup[Exception Seq],0))) | G61: =IF($B61="","",INDEX(Payslip_Lookup[Exception Reason],MATCH($B61,Payslip_Lookup[Exception Seq],0)))
B62: =IF(13<=COUNTIF(Payslip_Lookup[Payment Status],"Review Required"),13,"") | C62: =IF($B62="","",INDEX(Payslip_Lookup[Rider ID],MATCH($B62,Payslip_Lookup[Exception Seq],0))) | D62: =IF($B62="","",INDEX(Payslip_Lookup[Salary Month],MATCH($B62,Payslip_Lookup[Exception Seq],0))) | E62: =IF($B62="","",INDEX(Payslip_Lookup[Rider Name],MATCH($B62,Payslip_Lookup[Exception Seq],0))) | G62: =IF($B62="","",INDEX(Payslip_Lookup[Exception Reason],MATCH($B62,Payslip_Lookup[Exception Seq],0)))
B63: =IF(14<=COUNTIF(Payslip_Lookup[Payment Status],"Review Required"),14,"") | C63: =IF($B63="","",INDEX(Payslip_Lookup[Rider ID],MATCH($B63,Payslip_Lookup[Exception Seq],0))) | D63: =IF($B63="","",INDEX(Payslip_Lookup[Salary Month],MATCH($B63,Payslip_Lookup[Exception Seq],0))) | E63: =IF($B63="","",INDEX(Payslip_Lookup[Rider Name],MATCH($B63,Payslip_Lookup[Exception Seq],0))) | G63: =IF($B63="","",INDEX(Payslip_Lookup[Exception Reason],MATCH($B63,Payslip_Lookup[Exception Seq],0)))
B64: =IF(15<=COUNTIF(Payslip_Lookup[Payment Status],"Review Required"),15,"") | C64: =IF($B64="","",INDEX(Payslip_Lookup[Rider ID],MATCH($B64,Payslip_Lookup[Exception Seq],0))) | D64: =IF($B64="","",INDEX(Payslip_Lookup[Salary Month],MATCH($B64,Payslip_Lookup[Exception Seq],0))) | E64: =IF($B64="","",INDEX(Payslip_Lookup[Rider Name],MATCH($B64,Payslip_Lookup[Exception Seq],0))) | G64: =IF($B64="","",INDEX(Payslip_Lookup[Exception Reason],MATCH($B64,Payslip_Lookup[Exception Seq],0)))
B65: =IF(16<=COUNTIF(Payslip_Lookup[Payment Status],"Review Required"),16,"") | C65: =IF($B65="","",INDEX(Payslip_Lookup[Rider ID],MATCH($B65,Payslip_Lookup[Exception Seq],0))) | D65: =IF($B65="","",INDEX(Payslip_Lookup[Salary Month],MATCH($B65,Payslip_Lookup[Exception Seq],0))) | E65: =IF($B65="","",INDEX(Payslip_Lookup[Rider Name],MATCH($B65,Payslip_Lookup[Exception Seq],0))) | G65: =IF($B65="","",INDEX(Payslip_Lookup[Exception Reason],MATCH($B65,Payslip_Lookup[Exception Seq],0)))
B66: =IF(17<=COUNTIF(Payslip_Lookup[Payment Status],"Review Required"),17,"") | C66: =IF($B66="","",INDEX(Payslip_Lookup[Rider ID],MATCH($B66,Payslip_Lookup[Exception Seq],0))) | D66: =IF($B66="","",INDEX(Payslip_Lookup[Salary Month],MATCH($B66,Payslip_Lookup[Exception Seq],0))) | E66: =IF($B66="","",INDEX(Payslip_Lookup[Rider Name],MATCH($B66,Payslip_Lookup[Exception Seq],0))) | G66: =IF($B66="","",INDEX(Payslip_Lookup[Exception Reason],MATCH($B66,Payslip_Lookup[Exception Seq],0)))
B67: =IF(18<=COUNTIF(Payslip_Lookup[Payment Status],"Review Required"),18,"") | C67: =IF($B67="","",INDEX(Payslip_Lookup[Rider ID],MATCH($B67,Payslip_Lookup[Exception Seq],0))) | D67: =IF($B67="","",INDEX(Payslip_Lookup[Salary Month],MATCH($B67,Payslip_Lookup[Exception Seq],0))) | E67: =IF($B67="","",INDEX(Payslip_Lookup[Rider Name],MATCH($B67,Payslip_Lookup[Exception Seq],0))) | G67: =IF($B67="","",INDEX(Payslip_Lookup[Exception Reason],MATCH($B67,Payslip_Lookup[Exception Seq],0)))
B68: =IF(19<=COUNTIF(Payslip_Lookup[Payment Status],"Review Required"),19,"") | C68: =IF($B68="","",INDEX(Payslip_Lookup[Rider ID],MATCH($B68,Payslip_Lookup[Exception Seq],0))) | D68: =IF($B68="","",INDEX(Payslip_Lookup[Salary Month],MATCH($B68,Payslip_Lookup[Exception Seq],0))) | E68: =IF($B68="","",INDEX(Payslip_Lookup[Rider Name],MATCH($B68,Payslip_Lookup[Exception Seq],0))) | G68: =IF($B68="","",INDEX(Payslip_Lookup[Exception Reason],MATCH($B68,Payslip_Lookup[Exception Seq],0)))
B69: =IF(20<=COUNTIF(Payslip_Lookup[Payment Status],"Review Required"),20,"") | C69: =IF($B69="","",INDEX(Payslip_Lookup[Rider ID],MATCH($B69,Payslip_Lookup[Exception Seq],0))) | D69: =IF($B69="","",INDEX(Payslip_Lookup[Salary Month],MATCH($B69,Payslip_Lookup[Exception Seq],0))) | E69: =IF($B69="","",INDEX(Payslip_Lookup[Rider Name],MATCH($B69,Payslip_Lookup[Exception Seq],0))) | G69: =IF($B69="","",INDEX(Payslip_Lookup[Exception Reason],MATCH($B69,Payslip_Lookup[Exception Seq],0)))
B70: =IF(21<=COUNTIF(Payslip_Lookup[Payment Status],"Review Required"),21,"") | C70: =IF($B70="","",INDEX(Payslip_Lookup[Rider ID],MATCH($B70,Payslip_Lookup[Exception Seq],0))) | D70: =IF($B70="","",INDEX(Payslip_Lookup[Salary Month],MATCH($B70,Payslip_Lookup[Exception Seq],0))) | E70: =IF($B70="","",INDEX(Payslip_Lookup[Rider Name],MATCH($B70,Payslip_Lookup[Exception Seq],0))) | G70: =IF($B70="","",INDEX(Payslip_Lookup[Exception Reason],MATCH($B70,Payslip_Lookup[Exception Seq],0)))
B71: =IF(22<=COUNTIF(Payslip_Lookup[Payment Status],"Review Required"),22,"") | C71: =IF($B71="","",INDEX(Payslip_Lookup[Rider ID],MATCH($B71,Payslip_Lookup[Exception Seq],0))) | D71: =IF($B71="","",INDEX(Payslip_Lookup[Salary Month],MATCH($B71,Payslip_Lookup[Exception Seq],0))) | E71: =IF($B71="","",INDEX(Payslip_Lookup[Rider Name],MATCH($B71,Payslip_Lookup[Exception Seq],0))) | G71: =IF($B71="","",INDEX(Payslip_Lookup[Exception Reason],MATCH($B71,Payslip_Lookup[Exception Seq],0)))
B72: =IF(23<=COUNTIF(Payslip_Lookup[Payment Status],"Review Required"),23,"") | C72: =IF($B72="","",INDEX(Payslip_Lookup[Rider ID],MATCH($B72,Payslip_Lookup[Exception Seq],0))) | D72: =IF($B72="","",INDEX(Payslip_Lookup[Salary Month],MATCH($B72,Payslip_Lookup[Exception Seq],0))) | E72: =IF($B72="","",INDEX(Payslip_Lookup[Rider Name],MATCH($B72,Payslip_Lookup[Exception Seq],0))) | G72: =IF($B72="","",INDEX(Payslip_Lookup[Exception Reason],MATCH($B72,Payslip_Lookup[Exception Seq],0)))
B73: =IF(24<=COUNTIF(Payslip_Lookup[Payment Status],"Review Required"),24,"") | C73: =IF($B73="","",INDEX(Payslip_Lookup[Rider ID],MATCH($B73,Payslip_Lookup[Exception Seq],0))) | D73: =IF($B73="","",INDEX(Payslip_Lookup[Salary Month],MATCH($B73,Payslip_Lookup[Exception Seq],0))) | E73: =IF($B73="","",INDEX(Payslip_Lookup[Rider Name],MATCH($B73,Payslip_Lookup[Exception Seq],0))) | G73: =IF($B73="","",INDEX(Payslip_Lookup[Exception Reason],MATCH($B73,Payslip_Lookup[Exception Seq],0)))
B74: =IF(25<=COUNTIF(Payslip_Lookup[Payment Status],"Review Required"),25,"") | C74: =IF($B74="","",INDEX(Payslip_Lookup[Rider ID],MATCH($B74,Payslip_Lookup[Exception Seq],0))) | D74: =IF($B74="","",INDEX(Payslip_Lookup[Salary Month],MATCH($B74,Payslip_Lookup[Exception Seq],0))) | E74: =IF($B74="","",INDEX(Payslip_Lookup[Rider Name],MATCH($B74,Payslip_Lookup[Exception Seq],0))) | G74: =IF($B74="","",INDEX(Payslip_Lookup[Exception Reason],MATCH($B74,Payslip_Lookup[Exception Seq],0)))
B78: SPECIFICATION EXAMPLE CHECKS | فحص الأمثلة – formulas re-compute the three worked examples from the rules
B79: Example | D79: Calendar Days | E79: Working Days | F79: Completed Orders | G79: Base Rate Used | H79: Rider Target | I79: Earned Salary | J79: Missing-Order Deduction | K79: Extra-Order Bonus | L79: Gross Before Deductions | M79: Other Deductions | N79: Final Salary | O79: Amount Due from Rider
B80: Example 1 – exact rate 2000/450 | D80: 30 | E80: 15 | F80: 200 | G80: =Default_Basic/Std_Orders -> 4.4444444 | H80: =Std_Orders/Std_Days*E80 -> 225 | I80: =MIN(F80,H80)*G80 -> 888.88889 | J80: =MAX(H80-F80,0)*Missing_Rate -> 175 | K80: =MAX(F80-H80,0)*Extra_Rate -> 0 | L80: =MAX(I80-J80+K80,0) -> 713.88889 | M80: 0 | N80: =MAX(L80-M80,0) -> 713.88889 | O80: =MAX(J80-I80,0)+MAX(M80-L80,0) -> 0
B81: Example 2 – Rider 4849914 (fixed 4.44) | D81: 31 | E81: 8 | F81: 72 | G81: =Fixed_Rate -> 4.44 | H81: =Std_Orders/Std_Days*E81 -> 120 | I81: =MIN(F81,H81)*G81 -> 319.68 | J81: =MAX(H81-F81,0)*Missing_Rate -> 336 | K81: =MAX(F81-H81,0)*Extra_Rate -> 0 | L81: =MAX(I81-J81+K81,0) -> 0 | M81: 0 | N81: =MAX(L81-M81,0) -> 0 | O81: =MAX(J81-I81,0)+MAX(M81-L81,0) -> 16.32
B82: Example 3 – Rider 4648308 (fixed 4.44) | D82: 31 | E82: 31 | F82: 551 | G82: =Fixed_Rate -> 4.44 | H82: =Std_Orders/Std_Days*E82 -> 465 | I82: =MIN(F82,H82)*G82 -> 2064.6 | J82: =MAX(H82-F82,0)*Missing_Rate -> 0 | K82: =MAX(F82-H82,0)*Extra_Rate -> 860 | L82: =MAX(I82-J82+K82,0) -> 2924.6 | M82: =112+93.12 -> 205.12 | N82: =MAX(L82-M82,0) -> 2719.48 | O82: =MAX(J82-I82,0)+MAX(M82-L82,0) -> 0
B83: Blue = typed from the specification. Example 3 other deductions = 112 + 93.12 (stacking + rider balance). Example 1 rate = Default Basic Payment / Standard Orders.
B85: Check | G85: Calculated | H85: Expected (spec) | I85: Difference | J85: Result
B86: Ex.1 Rider target (225) | G86: =H80 -> 225 | H86: 225 | I86: =IF(AND(ISNUMBER(G86),ISNUMBER(H86)),ROUND(G86-H86,2),"") -> 0 | J86: =IF(I86="","n/a",IF(ABS(I86)<0.005,"OK","MISMATCH – review")) -> OK
B87: Ex.1 Earned salary (888.89) | G87: =I80 -> 888.88889 | H87: 888.89 | I87: =IF(AND(ISNUMBER(G87),ISNUMBER(H87)),ROUND(G87-H87,2),"") -> 0 | J87: =IF(I87="","n/a",IF(ABS(I87)<0.005,"OK","MISMATCH – review")) -> OK
B88: Ex.1 Missing-order deduction (175) | G88: =J80 -> 175 | H88: 175 | I88: =IF(AND(ISNUMBER(G88),ISNUMBER(H88)),ROUND(G88-H88,2),"") -> 0 | J88: =IF(I88="","n/a",IF(ABS(I88)<0.005,"OK","MISMATCH – review")) -> OK
B89: Ex.1 Salary before other deductions (713.89) | G89: =I80-J80 -> 713.88889 | H89: 713.89 | I89: =IF(AND(ISNUMBER(G89),ISNUMBER(H89)),ROUND(G89-H89,2),"") -> 0 | J89: =IF(I89="","n/a",IF(ABS(I89)<0.005,"OK","MISMATCH – review")) -> OK
B90: Ex.2 Rider target (120) | G90: =H81 -> 120 | H90: 120 | I90: =IF(AND(ISNUMBER(G90),ISNUMBER(H90)),ROUND(G90-H90,2),"") -> 0 | J90: =IF(I90="","n/a",IF(ABS(I90)<0.005,"OK","MISMATCH – review")) -> OK
B91: Ex.2 Earned salary at 4.44 (319.68) | G91: =I81 -> 319.68 | H91: 319.68 | I91: =IF(AND(ISNUMBER(G91),ISNUMBER(H91)),ROUND(G91-H91,2),"") -> 0 | J91: =IF(I91="","n/a",IF(ABS(I91)<0.005,"OK","MISMATCH – review")) -> OK
B92: Ex.2 Missing-order deduction (336) | G92: =J81 -> 336 | H92: 336 | I92: =IF(AND(ISNUMBER(G92),ISNUMBER(H92)),ROUND(G92-H92,2),"") -> 0 | J92: =IF(I92="","n/a",IF(ABS(I92)<0.005,"OK","MISMATCH – review")) -> OK
B93: Ex.2 Salary before other deductions (-16.32) | G93: =I81-J81 -> -16.32 | H93: -16.32 | I93: =IF(AND(ISNUMBER(G93),ISNUMBER(H93)),ROUND(G93-H93,2),"") -> 0 | J93: =IF(I93="","n/a",IF(ABS(I93)<0.005,"OK","MISMATCH – review")) -> OK
B94: Ex.2 Company payment (0) | G94: =N81 -> 0 | H94: 0 | I94: =IF(AND(ISNUMBER(G94),ISNUMBER(H94)),ROUND(G94-H94,2),"") -> 0 | J94: =IF(I94="","n/a",IF(ABS(I94)<0.005,"OK","MISMATCH – review")) -> OK
B95: Ex.2 Amount due from rider (16.32) | G95: =O81 -> 16.32 | H95: 16.32 | I95: =IF(AND(ISNUMBER(G95),ISNUMBER(H95)),ROUND(G95-H95,2),"") -> 0 | J95: =IF(I95="","n/a",IF(ABS(I95)<0.005,"OK","MISMATCH – review")) -> OK
B96: Ex.3 Basic salary for target (2,064.60) | G96: =MIN(F82,H82)*G82 -> 2064.6 | H96: 2064.6 | I96: =IF(AND(ISNUMBER(G96),ISNUMBER(H96)),ROUND(G96-H96,2),"") -> 0 | J96: =IF(I96="","n/a",IF(ABS(I96)<0.005,"OK","MISMATCH – review")) -> OK
B97: Ex.3 Extra-order bonus (860) | G97: =K82 -> 860 | H97: 860 | I97: =IF(AND(ISNUMBER(G97),ISNUMBER(H97)),ROUND(G97-H97,2),"") -> 0 | J97: =IF(I97="","n/a",IF(ABS(I97)<0.005,"OK","MISMATCH – review")) -> OK
B98: Ex.3 Gross salary (2,924.60) | G98: =L82 -> 2924.6 | H98: 2924.6 | I98: =IF(AND(ISNUMBER(G98),ISNUMBER(H98)),ROUND(G98-H98,2),"") -> 0 | J98: =IF(I98="","n/a",IF(ABS(I98)<0.005,"OK","MISMATCH – review")) -> OK
B99: Ex.3 Final salary (2,719.48) | G99: =N82 -> 2719.48 | H99: 2719.48 | I99: =IF(AND(ISNUMBER(G99),ISNUMBER(H99)),ROUND(G99-H99,2),"") -> 0 | J99: =IF(I99="","n/a",IF(ABS(I99)<0.005,"OK","MISMATCH – review")) -> OK
B100: Ex.3 Final salary vs 2,718.88 quoted in the spec note | G100: =N82 -> 2719.48 | H100: 2718.88 | I100: =IF(AND(ISNUMBER(G100),ISNUMBER(H100)),ROUND(G100-H100,2),"") -> 0.6 | J100: =IF(I100="","n/a",IF(ABS(I100)<0.005,"OK","MISMATCH – review")) -> MISMATCH – review
B101: Live: Rider 4849914 total amount due incl. other deductions (Fixed rate only) | G101: =IF(Rate_Method="Fixed rate",SUMIFS(Salary_Calculation[Total Amount Due from Rider],Salary_Calculation[Rider ID],4849914),"n/a – set Fixed rate") -> n/a – set Fixed rate | H101: =O81+268.09+32 -> 316.41 | I101: =IF(AND(ISNUMBER(G101),ISNUMBER(H101)),ROUND(G101-H101,2),"") | J101: =IF(I101="","n/a",IF(ABS(I101)<0.005,"OK","MISMATCH – review")) -> n/a
B102: Live: Rider 4648308 final salary (Fixed rate only) | G102: =IF(Rate_Method="Fixed rate",SUMIFS(Salary_Calculation[Final Salary],Salary_Calculation[Rider ID],4648308),"n/a – set Fixed rate") -> n/a – set Fixed rate | H102: 2719.48 | I102: =IF(AND(ISNUMBER(G102),ISNUMBER(H102)),ROUND(G102-H102,2),"") | J102: =IF(I102="","n/a",IF(ABS(I102)<0.005,"OK","MISMATCH – review")) -> n/a
B103: The 2,718.88 figure differs from the calculated 2,719.48 by 0.60 and is deliberately flagged for review (see spec note on Example 3).

Sheet Payslip_Print
B1: SELECT PAYSLIP | اختيار القسيمة
B2: Month / الشهر ▸ | C2: =Salary_Month -> 46235 | E2: Rider ID / المندوب ▸ | F2: =Payslip_Data!AL2 -> 4849914 | H2: Print: File ▸ Print ▸ PDF
B3: Record # (auto) | C3: =IFERROR(MATCH($F$2&"|"&$C$2,Payslip_Lookup[Key],0),"") -> 1 | E3: =IF($C$3="","⚠ No record for this month + rider. Choose the month first, then the rider.","✔ Record found – payslip ready to print.") -> ✔ Record found – payslip ready to print.
E6: PAYSLIP | قسيمة راتب
E7: =IF($C$3="","",TEXT(INDEX(Payslip_Lookup[Salary Month],$C$3),"dd mmm yyyy")&" – "&TEXT(EOMONTH(INDEX(Payslip_Lookup[Salary Month],$C$3),0),"dd mmm yyyy")) -> 01 Aug 2026 – 31 Aug 2026
E8: =IF($C$3="","","Payslip No. PS-"&TEXT(INDEX(Payslip_Lookup[Salary Month],$C$3),"yyyymm")&"-"&INDEX(Payslip_Lookup[Rider ID],$C$3)) -> Payslip No. PS-202608-4849914
E9: ="Issued by "&Company_Name&" · Payroll Department" -> Issued by Elite Development · Payroll Department
B11: RIDER | المندوب | F11: PAYMENT STATUS | حالة الدفع
B12: =IF($C$3="","",INDEX(Payslip_Lookup[Rider Name],$C$3)) -> Rider 4849914 | F12: =IF($C$3="","",INDEX(Payslip_Lookup[Payment Status],$C$3)) -> No Salary – Amount Due from Rider
B13: =IF($C$3="","","Rider ID "&INDEX(Payslip_Lookup[Rider ID],$C$3)) -> Rider ID 4849914
B14: =IF($C$3="","","Salary month: "&TEXT(INDEX(Payslip_Lookup[Salary Month],$C$3),"mmmm yyyy")) -> Salary month: August 2026 | F14: =IF($C$3="","","Base rate SAR "&TEXT(INDEX(Payslip_Lookup[Base Order Rate],$C$3),"0.00")&" / order · "&Rate_Method) -> Base rate SAR 4.44 / order · Exact rate
B16: WORKING DAYS | أيام العمل | D16: TARGET ORDERS | الهدف | F16: COMPLETED | المكتملة | H16: ACHIEVEMENT | الإنجاز
B17: =IF($C$3="","",INDEX(Payslip_Lookup[Working Days],$C$3)) -> 8 | D17: =IF($C$3="","",INDEX(Payslip_Lookup[Rider Target Orders],$C$3)) -> 120 | F17: =IF($C$3="","",INDEX(Payslip_Lookup[Completed Orders],$C$3)) -> 72 | H17: =IF(OR($C$3="",N(INDEX(Payslip_Lookup[Rider Target Orders],$C$3))=0),"",INDEX(Payslip_Lookup[Completed Orders],$C$3)/INDEX(Payslip_Lookup[Rider Target Orders],$C$3)) -> 0.6
B18: =IF($C$3="","","of "&INDEX(Payslip_Lookup[Calendar Days],$C$3)&" calendar days") -> of 31 calendar days | D18: =IF($C$3="","","monthly target "&TEXT(INDEX(Payslip_Lookup[Monthly Target Orders],$C$3),"0.##")) -> monthly target 465 | F18: =IF($C$3="","",IF(INDEX(Payslip_Lookup[Extra Orders],$C$3)>0,"▲ "&TEXT(INDEX(Payslip_Lookup[Extra Orders],$C$3),"0.##")&" extra orders",IF(INDEX(Payslip_Lookup[Missing Orders],$C$3)>0,"▼ "&TEXT(INDEX(Payslip_Lookup[Missing Orders],$C$3),"0.##")&" missing orders","target met"))) -> ▼ 48 missing orders | H18: =IF($C$3="","","completed ÷ target") -> completed ÷ target
B20: EARNINGS | المستحقات | F20: DEDUCTIONS | الخصومات
B21: Basic Payment (contract) | الدفعة الأساسية | E21: =IF($C$3="","",INDEX(Payslip_Lookup[Basic Payment],$C$3)) -> 2000 | F21: Missing Orders | الطلبات الناقصة | I21: =IF($C$3="","",INDEX(Payslip_Lookup[Missing Orders],$C$3)) -> 48
B22: Orders counted at base rate | الطلبات بالسعر الأساسي | E22: =IF($C$3="","",INDEX(Payslip_Lookup[Orders Counted at Base Rate],$C$3)) -> 72 | F22: Missing-Order Deduction | خصم الطلبات الناقصة | I22: =IF($C$3="","",INDEX(Payslip_Lookup[Missing-Order Deduction],$C$3)) -> 336
B23: Earned Salary | الراتب المكتسب | E23: =IF($C$3="","",INDEX(Payslip_Lookup[Earned Salary],$C$3)) -> 320 | F23: missed_days_penalty | غرامة الأيام الفائتة | I23: =IF($C$3="","",INDEX(Payslip_Lookup[missed_days_penalty],$C$3)) -> 0
B24: Extra Orders | الطلبات الإضافية | E24: =IF($C$3="","",INDEX(Payslip_Lookup[Extra Orders],$C$3)) -> 0 | F24: Rider Balance | محفظة المندوب | I24: =IF($C$3="","",INDEX(Payslip_Lookup[Rider Balance],$C$3)) -> 268.09
B25: Extra-Order Bonus | مكافأة الطلبات الإضافية | E25: =IF($C$3="","",INDEX(Payslip_Lookup[Extra-Order Bonus],$C$3)) -> 0 | F25: stacking_deduction | خصم الطلبات المتعددة | I25: =IF($C$3="","",INDEX(Payslip_Lookup[stacking_deduction],$C$3)) -> 32
B26: Basic Salary at Target | الراتب الأساسي للهدف | E26: =IF($C$3="","",INDEX(Payslip_Lookup[Basic Salary for Target],$C$3)) -> 533.33333 | F26: Other Deductions | خصومات أخرى | I26: =IF($C$3="","",INDEX(Payslip_Lookup[Other Deductions],$C$3)) -> 0
B27: GROSS SALARY | إجمالي الراتب قبل الخصم | E27: =IF($C$3="","",INDEX(Payslip_Lookup[Gross Salary Before Deductions],$C$3)) -> 0 | F27: TOTAL DEDUCTIONS | إجمالي الخصومات | I27: =IF($C$3="","",INDEX(Payslip_Lookup[Total Deductions],$C$3)) -> 300.09
B29: FINAL SALARY (PAYABLE) | صافي الراتب المستحق | F29: NEGATIVE BALANCE / AMOUNT DUE FROM RIDER | المبلغ المستحق على المندوب
B30: =IF($C$3="","",INDEX(Payslip_Lookup[Final Salary],$C$3)) -> 0 | F30: =IF($C$3="","",INDEX(Payslip_Lookup[Negative Balance / Amount Due from Rider],$C$3)) -> 16
B32: =IF($C$3="","","Salary before other deductions: SAR "&TEXT(INDEX(Payslip_Lookup[Salary Before Other Deductions],$C$3),"#,##0.00;-#,##0.00")) -> Salary before other deductions: SAR -16.00 | F32: =IF($C$3="","","Total amount due from rider (incl. deductions beyond salary): SAR "&TEXT(INDEX(Payslip_Lookup[Total Amount Due from Rider],$C$3),"#,##0.00")) -> Total amount due from rider (incl. deductions beyond salary): SAR 316.09
B34: HOW THIS WAS CALCULATED | طريقة الحساب
B35: =IF($C$3="","","① Rider target = monthly target "&TEXT(INDEX(Payslip_Lookup[Monthly Target Orders],$C$3),"0.##")&" ÷ "&INDEX(Payslip_Lookup[Calendar Days],$C$3)&" days × "&INDEX(Payslip_Lookup[Working Days],$C$3)&" working days = "&TEXT(INDEX(Payslip_Lookup[Rider Target Orders],$C$3),"0.00")&" orders") -> ① Rider target = monthly target 465 ÷ 31 days × 8 working days = 120.00 orders
B36: =IF($C$3="","","② Earned salary = "&TEXT(INDEX(Payslip_Lookup[Orders Counted at Base Rate],$C$3),"0.00")&" orders × SAR "&TEXT(INDEX(Payslip_Lookup[Base Order Rate],$C$3),"0.00")&" = SAR "&TEXT(INDEX(Payslip_Lookup[Earned Salary],$C$3),"#,##0.00")) -> ② Earned salary = 72.00 orders × SAR 4.44 = SAR 320.00
B37: =IF($C$3="","","③ "&IF(INDEX(Payslip_Lookup[Missing Orders],$C$3)>0,"Shortfall: "&TEXT(INDEX(Payslip_Lookup[Missing Orders],$C$3),"0.##")&" missing orders × SAR "&Missing_Rate&" = SAR "&TEXT(INDEX(Payslip_Lookup[Missing-Order Deduction],$C$3),"#,##0.00")&" deducted",IF(INDEX(Payslip_Lookup[Extra Orders],$C$3)>0,"Bonus: "&TEXT(INDEX(Payslip_Lookup[Extra Orders],$C$3),"0.##")&" extra orders × SAR "&Extra_Rate&" = SAR "&TEXT(INDEX(Payslip_Lookup[Extra-Order Bonus],$C$3),"#,##0.00"),"Target met exactly – no shortfall or bonus"))) -> ③ Shortfall: 48 missing orders × SAR 7 = SAR 336.00 deducted
B39: NOTES | ملاحظات
B40: =IF($C$3="","",INDEX(Payslip_Lookup[Notes],$C$3)&IF(INDEX(Payslip_Lookup[Exception Reason],$C$3)<>""," ⚠ REVIEW REQUIRED: "&INDEX(Payslip_Lookup[Exception Reason],$C$3),""))
B44: Rider Signature | توقيع المندوب | E44: Payroll Officer | مسؤول الرواتب | H44: Approved by | اعتماد الإدارة
B45: Date / التاريخ: ____ / ____ / ________ | E45: Date / التاريخ: ____ / ____ / ________ | H45: Date / التاريخ: ____ / ____ / ________
B48: =Company_Name&" · System-generated payslip · Amounts in Saudi Riyals (SAR) · المبالغ بالريال السعودي" -> Elite Development · System-generated payslip · Amounts in Saudi Riyals (SAR) · المبالغ بالريال السعودي

Sheet Monthly_Import
B1: Monthly Import – new month in 5 minutes / الاستيراد الشهري
B3: 1. Save last month's file as a copy (e.g. Salary_2026-08.xlsx) – keep it as your archive, then reuse this file. | I3: Helper area – formulas only, do not edit
B4: 2. Settings → B13: type the new Salary Month (calendar days are calculated automatically).
B5: 3. Paste_FTR: select row 2 downward → Delete, then paste the new 'FTR Cost' export from cell A1 (header row included). | I5: # | J5: Rider ID | K5: Row in RLVL | L5: In Rider_Master? | M5: Orders FTR | N5: Orders RLVL | O5: Duplicate? | P5: Issue | Q5: Issue #
B6: 4. Paste_RLVL: same – delete old rows, paste the new RLVL export from A1. | I6: 1 | J6: =IFERROR(IF(INDEX(Rider_Input[Rider ID],I6)="","",INDEX(Rider_Input[Rider ID],I6)),"") -> 4849914 | K6: =IF(J6="","",IFERROR(MATCH(J6,INDEX(RLVL_Data,0,c_RLVL_ID),0),"")) -> 15 | L6: =IF(J6="","",IF(ISNUMBER(MATCH(J6,Rider_Master[Rider ID],0)),1,0)) -> 1 | M6: =IF(J6="","",INDEX(Rider_Input[Completed Orders],I6)) -> 72 | N6: =IF(OR(J6="",K6=""),"",IFERROR(INDEX(RLVL_Data,K6,c_RLVL_Orders),"")) -> 72 | O6: =IF(J6="","",IF(COUNTIF($J$6:$J$505,J6)>1,1,0)) -> 0 | P6: =IF(J6="","",IF(K6="","Not found in Paste_RLVL – deductions set to 0; ","")&IF(L6=0,"New rider (not in Rider_Master) – OK, shown as Rider <ID>; ","")&IF(AND(N6<>"",N6<>M6),"Orders differ: FTR "&M6&" vs RLVL "&N6&"; ","")&IF(O6=1,"Duplicate Rider ID; ","")) | Q6: =IF(P6="","",COUNTIF(P$6:P6,"?*"))
B7: 5. Adjustments (optional): clear last month's rows, add this month's Other Deductions (car, TGA, advances…). | I7: 2 | J7: =IFERROR(IF(INDEX(Rider_Input[Rider ID],I7)="","",INDEX(Rider_Input[Rider ID],I7)),"") -> 4849909 | K7: =IF(J7="","",IFERROR(MATCH(J7,INDEX(RLVL_Data,0,c_RLVL_ID),0),"")) -> 14 | L7: =IF(J7="","",IF(ISNUMBER(MATCH(J7,Rider_Master[Rider ID],0)),1,0)) -> 1 | M7: =IF(J7="","",INDEX(Rider_Input[Completed Orders],I7)) -> 101 | N7: =IF(OR(J7="",K7=""),"",IFERROR(INDEX(RLVL_Data,K7,c_RLVL_Orders),"")) -> 101 | O7: =IF(J7="","",IF(COUNTIF($J$6:$J$505,J7)>1,1,0)) -> 0 | P7: =IF(J7="","",IF(K7="","Not found in Paste_RLVL – deductions set to 0; ","")&IF(L7=0,"New rider (not in Rider_Master) – OK, shown as Rider <ID>; ","")&IF(AND(N7<>"",N7<>M7),"Orders differ: FTR "&M7&" vs RLVL "&N7&"; ","")&IF(O7=1,"Duplicate Rider ID; ","")) | Q7: =IF(P7="","",COUNTIF(P$6:P7,"?*"))
B8: 6. Come back here: banner must say READY. Fix anything under 'Items to review'. New riders appear automatically – no setup needed. | I8: 3 | J8: =IFERROR(IF(INDEX(Rider_Input[Rider ID],I8)="","",INDEX(Rider_Input[Rider ID],I8)),"") -> 4849222 | K8: =IF(J8="","",IFERROR(MATCH(J8,INDEX(RLVL_Data,0,c_RLVL_ID),0),"")) -> 13 | L8: =IF(J8="","",IF(ISNUMBER(MATCH(J8,Rider_Master[Rider ID],0)),1,0)) -> 1 | M8: =IF(J8="","",INDEX(Rider_Input[Completed Orders],I8)) -> 105 | N8: =IF(OR(J8="",K8=""),"",IFERROR(INDEX(RLVL_Data,K8,c_RLVL_Orders),"")) -> 105 | O8: =IF(J8="","",IF(COUNTIF($J$6:$J$505,J8)>1,1,0)) -> 0 | P8: =IF(J8="","",IF(K8="","Not found in Paste_RLVL – deductions set to 0; ","")&IF(L8=0,"New rider (not in Rider_Master) – OK, shown as Rider <ID>; ","")&IF(AND(N8<>"",N8<>M8),"Orders differ: FTR "&M8&" vs RLVL "&N8&"; ","")&IF(O8=1,"Duplicate Rider ID; ","")) | Q8: =IF(P8="","",COUNTIF(P$6:P8,"?*"))
B9: 7. Summary_Dashboard for totals, Payslip_Print for payslips (print or Save as PDF). | I9: 4 | J9: =IFERROR(IF(INDEX(Rider_Input[Rider ID],I9)="","",INDEX(Rider_Input[Rider ID],I9)),"") -> 4844480 | K9: =IF(J9="","",IFERROR(MATCH(J9,INDEX(RLVL_Data,0,c_RLVL_ID),0),"")) -> 12 | L9: =IF(J9="","",IF(ISNUMBER(MATCH(J9,Rider_Master[Rider ID],0)),1,0)) -> 1 | M9: =IF(J9="","",INDEX(Rider_Input[Completed Orders],I9)) -> 150 | N9: =IF(OR(J9="",K9=""),"",IFERROR(INDEX(RLVL_Data,K9,c_RLVL_Orders),"")) -> 150 | O9: =IF(J9="","",IF(COUNTIF($J$6:$J$505,J9)>1,1,0)) -> 0 | P9: =IF(J9="","",IF(K9="","Not found in Paste_RLVL – deductions set to 0; ","")&IF(L9=0,"New rider (not in Rider_Master) – OK, shown as Rider <ID>; ","")&IF(AND(N9<>"",N9<>M9),"Orders differ: FTR "&M9&" vs RLVL "&N9&"; ","")&IF(O9=1,"Duplicate Rider ID; ","")) | Q9: =IF(P9="","",COUNTIF(P$6:P9,"?*"))
I10: 5 | J10: =IFERROR(IF(INDEX(Rider_Input[Rider ID],I10)="","",INDEX(Rider_Input[Rider ID],I10)),"") -> 4838478 | K10: =IF(J10="","",IFERROR(MATCH(J10,INDEX(RLVL_Data,0,c_RLVL_ID),0),"")) -> 11 | L10: =IF(J10="","",IF(ISNUMBER(MATCH(J10,Rider_Master[Rider ID],0)),1,0)) -> 1 | M10: =IF(J10="","",INDEX(Rider_Input[Completed Orders],I10)) -> 171 | N10: =IF(OR(J10="",K10=""),"",IFERROR(INDEX(RLVL_Data,K10,c_RLVL_Orders),"")) -> 171 | O10: =IF(J10="","",IF(COUNTIF($J$6:$J$505,J10)>1,1,0)) -> 0 | P10: =IF(J10="","",IF(K10="","Not found in Paste_RLVL – deductions set to 0; ","")&IF(L10=0,"New rider (not in Rider_Master) – OK, shown as Rider <ID>; ","")&IF(AND(N10<>"",N10<>M10),"Orders differ: FTR "&M10&" vs RLVL "&N10&"; ","")&IF(O10=1,"Duplicate Rider ID; ","")) | Q10: =IF(P10="","",COUNTIF(P$6:P10,"?*"))
B11: =IF(COUNTIF(D14:D23,"CHECK")=0,"✔ READY – all checks passed ("&C15&" riders loaded for "&TEXT(Salary_Month,"mmmm yyyy")&")","⚠ CHECK – "&COUNTIF(D14:D23,"CHECK")&" item(s) marked CHECK below; review before paying") -> ✔ READY – all checks passed (15 riders loaded for August 2026) | I11: 6 | J11: =IFERROR(IF(INDEX(Rider_Input[Rider ID],I11)="","",INDEX(Rider_Input[Rider ID],I11)),"") -> 4838471 | K11: =IF(J11="","",IFERROR(MATCH(J11,INDEX(RLVL_Data,0,c_RLVL_ID),0),"")) -> 10 | L11: =IF(J11="","",IF(ISNUMBER(MATCH(J11,Rider_Master[Rider ID],0)),1,0)) -> 1 | M11: =IF(J11="","",INDEX(Rider_Input[Completed Orders],I11)) -> 146 | N11: =IF(OR(J11="",K11=""),"",IFERROR(INDEX(RLVL_Data,K11,c_RLVL_Orders),"")) -> 146 | O11: =IF(J11="","",IF(COUNTIF($J$6:$J$505,J11)>1,1,0)) -> 0 | P11: =IF(J11="","",IF(K11="","Not found in Paste_RLVL – deductions set to 0; ","")&IF(L11=0,"New rider (not in Rider_Master) – OK, shown as Rider <ID>; ","")&IF(AND(N11<>"",N11<>M11),"Orders differ: FTR "&M11&" vs RLVL "&N11&"; ","")&IF(O11=1,"Duplicate Rider ID; ","")) | Q11: =IF(P11="","",COUNTIF(P$6:P11,"?*"))
I12: 7 | J12: =IFERROR(IF(INDEX(Rider_Input[Rider ID],I12)="","",INDEX(Rider_Input[Rider ID],I12)),"") -> 4747290 | K12: =IF(J12="","",IFERROR(MATCH(J12,INDEX(RLVL_Data,0,c_RLVL_ID),0),"")) -> 9 | L12: =IF(J12="","",IF(ISNUMBER(MATCH(J12,Rider_Master[Rider ID],0)),1,0)) -> 1 | M12: =IF(J12="","",INDEX(Rider_Input[Completed Orders],I12)) -> 498 | N12: =IF(OR(J12="",K12=""),"",IFERROR(INDEX(RLVL_Data,K12,c_RLVL_Orders),"")) -> 498 | O12: =IF(J12="","",IF(COUNTIF($J$6:$J$505,J12)>1,1,0)) -> 0 | P12: =IF(J12="","",IF(K12="","Not found in Paste_RLVL – deductions set to 0; ","")&IF(L12=0,"New rider (not in Rider_Master) – OK, shown as Rider <ID>; ","")&IF(AND(N12<>"",N12<>M12),"Orders differ: FTR "&M12&" vs RLVL "&N12&"; ","")&IF(O12=1,"Duplicate Rider ID; ","")) | Q12: =IF(P12="","",COUNTIF(P$6:P12,"?*"))
B13: Import Health / فحص الاستيراد | I13: 8 | J13: =IFERROR(IF(INDEX(Rider_Input[Rider ID],I13)="","",INDEX(Rider_Input[Rider ID],I13)),"") -> 4652654 | K13: =IF(J13="","",IFERROR(MATCH(J13,INDEX(RLVL_Data,0,c_RLVL_ID),0),"")) -> 8 | L13: =IF(J13="","",IF(ISNUMBER(MATCH(J13,Rider_Master[Rider ID],0)),1,0)) -> 1 | M13: =IF(J13="","",INDEX(Rider_Input[Completed Orders],I13)) -> 433 | N13: =IF(OR(J13="",K13=""),"",IFERROR(INDEX(RLVL_Data,K13,c_RLVL_Orders),"")) -> 433 | O13: =IF(J13="","",IF(COUNTIF($J$6:$J$505,J13)>1,1,0)) -> 0 | P13: =IF(J13="","",IF(K13="","Not found in Paste_RLVL – deductions set to 0; ","")&IF(L13=0,"New rider (not in Rider_Master) – OK, shown as Rider <ID>; ","")&IF(AND(N13<>"",N13<>M13),"Orders differ: FTR "&M13&" vs RLVL "&N13&"; ","")&IF(O13=1,"Duplicate Rider ID; ","")) | Q13: =IF(P13="","",COUNTIF(P$6:P13,"?*"))
B14: Salary Month set | C14: =IF(ISNUMBER(Salary_Month),Salary_Month,"MISSING") -> 46235 | D14: =IF(ISNUMBER(C14),"OK","CHECK") -> OK | I14: 9 | J14: =IFERROR(IF(INDEX(Rider_Input[Rider ID],I14)="","",INDEX(Rider_Input[Rider ID],I14)),"") -> 4652587 | K14: =IF(J14="","",IFERROR(MATCH(J14,INDEX(RLVL_Data,0,c_RLVL_ID),0),"")) -> 7 | L14: =IF(J14="","",IF(ISNUMBER(MATCH(J14,Rider_Master[Rider ID],0)),1,0)) -> 1 | M14: =IF(J14="","",INDEX(Rider_Input[Completed Orders],I14)) -> 382 | N14: =IF(OR(J14="",K14=""),"",IFERROR(INDEX(RLVL_Data,K14,c_RLVL_Orders),"")) -> 382 | O14: =IF(J14="","",IF(COUNTIF($J$6:$J$505,J14)>1,1,0)) -> 0 | P14: =IF(J14="","",IF(K14="","Not found in Paste_RLVL – deductions set to 0; ","")&IF(L14=0,"New rider (not in Rider_Master) – OK, shown as Rider <ID>; ","")&IF(AND(N14<>"",N14<>M14),"Orders differ: FTR "&M14&" vs RLVL "&N14&"; ","")&IF(O14=1,"Duplicate Rider ID; ","")) | Q14: =IF(P14="","",COUNTIF(P$6:P14,"?*"))
B15: Riders found in Paste_FTR | C15: =IFERROR(COUNT(INDEX(FTR_Data,0,c_FTR_ID)),0) -> 15 | D15: =IF(C15>0,"OK","CHECK") -> OK | I15: 10 | J15: =IFERROR(IF(INDEX(Rider_Input[Rider ID],I15)="","",INDEX(Rider_Input[Rider ID],I15)),"") -> 4648709 | K15: =IF(J15="","",IFERROR(MATCH(J15,INDEX(RLVL_Data,0,c_RLVL_ID),0),"")) -> 6 | L15: =IF(J15="","",IF(ISNUMBER(MATCH(J15,Rider_Master[Rider ID],0)),1,0)) -> 1 | M15: =IF(J15="","",INDEX(Rider_Input[Completed Orders],I15)) -> 391 | N15: =IF(OR(J15="",K15=""),"",IFERROR(INDEX(RLVL_Data,K15,c_RLVL_Orders),"")) -> 391 | O15: =IF(J15="","",IF(COUNTIF($J$6:$J$505,J15)>1,1,0)) -> 0 | P15: =IF(J15="","",IF(K15="","Not found in Paste_RLVL – deductions set to 0; ","")&IF(L15=0,"New rider (not in Rider_Master) – OK, shown as Rider <ID>; ","")&IF(AND(N15<>"",N15<>M15),"Orders differ: FTR "&M15&" vs RLVL "&N15&"; ","")&IF(O15=1,"Duplicate Rider ID; ","")) | Q15: =IF(P15="","",COUNTIF(P$6:P15,"?*"))
B16: Riders found in Paste_RLVL | C16: =IFERROR(COUNT(INDEX(RLVL_Data,0,c_RLVL_ID)),0) -> 15 | D16: =IF(C16>0,"OK","CHECK") -> OK | I16: 11 | J16: =IFERROR(IF(INDEX(Rider_Input[Rider ID],I16)="","",INDEX(Rider_Input[Rider ID],I16)),"") -> 4648308 | K16: =IF(J16="","",IFERROR(MATCH(J16,INDEX(RLVL_Data,0,c_RLVL_ID),0),"")) -> 5 | L16: =IF(J16="","",IF(ISNUMBER(MATCH(J16,Rider_Master[Rider ID],0)),1,0)) -> 1 | M16: =IF(J16="","",INDEX(Rider_Input[Completed Orders],I16)) -> 551 | N16: =IF(OR(J16="",K16=""),"",IFERROR(INDEX(RLVL_Data,K16,c_RLVL_Orders),"")) -> 551 | O16: =IF(J16="","",IF(COUNTIF($J$6:$J$505,J16)>1,1,0)) -> 0 | P16: =IF(J16="","",IF(K16="","Not found in Paste_RLVL – deductions set to 0; ","")&IF(L16=0,"New rider (not in Rider_Master) – OK, shown as Rider <ID>; ","")&IF(AND(N16<>"",N16<>M16),"Orders differ: FTR "&M16&" vs RLVL "&N16&"; ","")&IF(O16=1,"Duplicate Rider ID; ","")) | Q16: =IF(P16="","",COUNTIF(P$6:P16,"?*"))
B17: Riders loaded into salary engine (capacity 500) | C17: =COUNTIF(Rider_Input[Rider ID],">0") -> 15 | D17: =IF(AND(C17=C15,C15<=500),"OK","CHECK") -> OK | I17: 12 | J17: =IFERROR(IF(INDEX(Rider_Input[Rider ID],I17)="","",INDEX(Rider_Input[Rider ID],I17)),"") -> 4644774 | K17: =IF(J17="","",IFERROR(MATCH(J17,INDEX(RLVL_Data,0,c_RLVL_ID),0),"")) -> 4 | L17: =IF(J17="","",IF(ISNUMBER(MATCH(J17,Rider_Master[Rider ID],0)),1,0)) -> 1 | M17: =IF(J17="","",INDEX(Rider_Input[Completed Orders],I17)) -> 367 | N17: =IF(OR(J17="",K17=""),"",IFERROR(INDEX(RLVL_Data,K17,c_RLVL_Orders),"")) -> 367 | O17: =IF(J17="","",IF(COUNTIF($J$6:$J$505,J17)>1,1,0)) -> 0 | P17: =IF(J17="","",IF(K17="","Not found in Paste_RLVL – deductions set to 0; ","")&IF(L17=0,"New rider (not in Rider_Master) – OK, shown as Rider <ID>; ","")&IF(AND(N17<>"",N17<>M17),"Orders differ: FTR "&M17&" vs RLVL "&N17&"; ","")&IF(O17=1,"Duplicate Rider ID; ","")) | Q17: =IF(P17="","",COUNTIF(P$6:P17,"?*"))
B18: FTR riders missing from RLVL | C18: =SUMPRODUCT(($J$6:$J$505<>"")*($K$6:$K$505="")) -> 0 | D18: =IF(C18=0,"OK","CHECK") -> OK | I18: 13 | J18: =IFERROR(IF(INDEX(Rider_Input[Rider ID],I18)="","",INDEX(Rider_Input[Rider ID],I18)),"") -> 4643856 | K18: =IF(J18="","",IFERROR(MATCH(J18,INDEX(RLVL_Data,0,c_RLVL_ID),0),"")) -> 3 | L18: =IF(J18="","",IF(ISNUMBER(MATCH(J18,Rider_Master[Rider ID],0)),1,0)) -> 1 | M18: =IF(J18="","",INDEX(Rider_Input[Completed Orders],I18)) -> 449 | N18: =IF(OR(J18="",K18=""),"",IFERROR(INDEX(RLVL_Data,K18,c_RLVL_Orders),"")) -> 449 | O18: =IF(J18="","",IF(COUNTIF($J$6:$J$505,J18)>1,1,0)) -> 0 | P18: =IF(J18="","",IF(K18="","Not found in Paste_RLVL – deductions set to 0; ","")&IF(L18=0,"New rider (not in Rider_Master) – OK, shown as Rider <ID>; ","")&IF(AND(N18<>"",N18<>M18),"Orders differ: FTR "&M18&" vs RLVL "&N18&"; ","")&IF(O18=1,"Duplicate Rider ID; ","")) | Q18: =IF(P18="","",COUNTIF(P$6:P18,"?*"))
B19: RLVL riders missing from FTR | C19: =IFERROR(SUMPRODUCT((INDEX(RLVL_Data,0,c_RLVL_ID)<>"")*(COUNTIF(INDEX(FTR_Data,0,c_FTR_ID),INDEX(RLVL_Data,0,c_RLVL_ID))=0)),0) -> 0 | D19: =IF(C19=0,"OK","CHECK") -> OK | I19: 14 | J19: =IFERROR(IF(INDEX(Rider_Input[Rider ID],I19)="","",INDEX(Rider_Input[Rider ID],I19)),"") -> 4642935 | K19: =IF(J19="","",IFERROR(MATCH(J19,INDEX(RLVL_Data,0,c_RLVL_ID),0),"")) -> 2 | L19: =IF(J19="","",IF(ISNUMBER(MATCH(J19,Rider_Master[Rider ID],0)),1,0)) -> 1 | M19: =IF(J19="","",INDEX(Rider_Input[Completed Orders],I19)) -> 442 | N19: =IF(OR(J19="",K19=""),"",IFERROR(INDEX(RLVL_Data,K19,c_RLVL_Orders),"")) -> 442 | O19: =IF(J19="","",IF(COUNTIF($J$6:$J$505,J19)>1,1,0)) -> 0 | P19: =IF(J19="","",IF(K19="","Not found in Paste_RLVL – deductions set to 0; ","")&IF(L19=0,"New rider (not in Rider_Master) – OK, shown as Rider <ID>; ","")&IF(AND(N19<>"",N19<>M19),"Orders differ: FTR "&M19&" vs RLVL "&N19&"; ","")&IF(O19=1,"Duplicate Rider ID; ","")) | Q19: =IF(P19="","",COUNTIF(P$6:P19,"?*"))
B20: Orders differ between FTR and RLVL | C20: =SUMPRODUCT(($N$6:$N$505<>"")*($N$6:$N$505<>$M$6:$M$505)) -> 0 | D20: =IF(C20=0,"OK","CHECK") -> OK | I20: 15 | J20: =IFERROR(IF(INDEX(Rider_Input[Rider ID],I20)="","",INDEX(Rider_Input[Rider ID],I20)),"") -> 4611383 | K20: =IF(J20="","",IFERROR(MATCH(J20,INDEX(RLVL_Data,0,c_RLVL_ID),0),"")) -> 1 | L20: =IF(J20="","",IF(ISNUMBER(MATCH(J20,Rider_Master[Rider ID],0)),1,0)) -> 1 | M20: =IF(J20="","",INDEX(Rider_Input[Completed Orders],I20)) -> 476 | N20: =IF(OR(J20="",K20=""),"",IFERROR(INDEX(RLVL_Data,K20,c_RLVL_Orders),"")) -> 476 | O20: =IF(J20="","",IF(COUNTIF($J$6:$J$505,J20)>1,1,0)) -> 0 | P20: =IF(J20="","",IF(K20="","Not found in Paste_RLVL – deductions set to 0; ","")&IF(L20=0,"New rider (not in Rider_Master) – OK, shown as Rider <ID>; ","")&IF(AND(N20<>"",N20<>M20),"Orders differ: FTR "&M20&" vs RLVL "&N20&"; ","")&IF(O20=1,"Duplicate Rider ID; ","")) | Q20: =IF(P20="","",COUNTIF(P$6:P20,"?*"))
B21: Duplicate Rider IDs | C21: =SUM($O$6:$O$505) -> 0 | D21: =IF(C21=0,"OK","CHECK") -> OK | I21: 16 | J21: =IFERROR(IF(INDEX(Rider_Input[Rider ID],I21)="","",INDEX(Rider_Input[Rider ID],I21)),"") | K21: =IF(J21="","",IFERROR(MATCH(J21,INDEX(RLVL_Data,0,c_RLVL_ID),0),"")) | L21: =IF(J21="","",IF(ISNUMBER(MATCH(J21,Rider_Master[Rider ID],0)),1,0)) | M21: =IF(J21="","",INDEX(Rider_Input[Completed Orders],I21)) | N21: =IF(OR(J21="",K21=""),"",IFERROR(INDEX(RLVL_Data,K21,c_RLVL_Orders),"")) | O21: =IF(J21="","",IF(COUNTIF($J$6:$J$505,J21)>1,1,0)) | P21: =IF(J21="","",IF(K21="","Not found in Paste_RLVL – deductions set to 0; ","")&IF(L21=0,"New rider (not in Rider_Master) – OK, shown as Rider <ID>; ","")&IF(AND(N21<>"",N21<>M21),"Orders differ: FTR "&M21&" vs RLVL "&N21&"; ","")&IF(O21=1,"Duplicate Rider ID; ","")) | Q21: =IF(P21="","",COUNTIF(P$6:P21,"?*"))
B22: Column mapping: columns not found | C22: =COUNTIF(F28:F35,"MISSING") -> 0 | D22: =IF(C22=0,"OK","CHECK") -> OK | I22: 17 | J22: =IFERROR(IF(INDEX(Rider_Input[Rider ID],I22)="","",INDEX(Rider_Input[Rider ID],I22)),"") | K22: =IF(J22="","",IFERROR(MATCH(J22,INDEX(RLVL_Data,0,c_RLVL_ID),0),"")) | L22: =IF(J22="","",IF(ISNUMBER(MATCH(J22,Rider_Master[Rider ID],0)),1,0)) | M22: =IF(J22="","",INDEX(Rider_Input[Completed Orders],I22)) | N22: =IF(OR(J22="",K22=""),"",IFERROR(INDEX(RLVL_Data,K22,c_RLVL_Orders),"")) | O22: =IF(J22="","",IF(COUNTIF($J$6:$J$505,J22)>1,1,0)) | P22: =IF(J22="","",IF(K22="","Not found in Paste_RLVL – deductions set to 0; ","")&IF(L22=0,"New rider (not in Rider_Master) – OK, shown as Rider <ID>; ","")&IF(AND(N22<>"",N22<>M22),"Orders differ: FTR "&M22&" vs RLVL "&N22&"; ","")&IF(O22=1,"Duplicate Rider ID; ","")) | Q22: =IF(P22="","",COUNTIF(P$6:P22,"?*"))
B23: Records flagged 'Review Required' in Salary_Calculation | C23: =COUNTIF(Salary_Calculation[Payment Status],"Review Required") -> 0 | D23: =IF(C23=0,"OK","CHECK") -> OK | I23: 18 | J23: =IFERROR(IF(INDEX(Rider_Input[Rider ID],I23)="","",INDEX(Rider_Input[Rider ID],I23)),"") | K23: =IF(J23="","",IFERROR(MATCH(J23,INDEX(RLVL_Data,0,c_RLVL_ID),0),"")) | L23: =IF(J23="","",IF(ISNUMBER(MATCH(J23,Rider_Master[Rider ID],0)),1,0)) | M23: =IF(J23="","",INDEX(Rider_Input[Completed Orders],I23)) | N23: =IF(OR(J23="",K23=""),"",IFERROR(INDEX(RLVL_Data,K23,c_RLVL_Orders),"")) | O23: =IF(J23="","",IF(COUNTIF($J$6:$J$505,J23)>1,1,0)) | P23: =IF(J23="","",IF(K23="","Not found in Paste_RLVL – deductions set to 0; ","")&IF(L23=0,"New rider (not in Rider_Master) – OK, shown as Rider <ID>; ","")&IF(AND(N23<>"",N23<>M23),"Orders differ: FTR "&M23&" vs RLVL "&N23&"; ","")&IF(O23=1,"Duplicate Rider ID; ","")) | Q23: =IF(P23="","",COUNTIF(P$6:P23,"?*"))
B24: New riders not in Rider_Master (information only) | C24: =SUMPRODUCT(($J$6:$J$505<>"")*($L$6:$L$505=0)) -> 0 | D24: =IF(C24=0,"OK","INFO") -> OK | I24: 19 | J24: =IFERROR(IF(INDEX(Rider_Input[Rider ID],I24)="","",INDEX(Rider_Input[Rider ID],I24)),"") | K24: =IF(J24="","",IFERROR(MATCH(J24,INDEX(RLVL_Data,0,c_RLVL_ID),0),"")) | L24: =IF(J24="","",IF(ISNUMBER(MATCH(J24,Rider_Master[Rider ID],0)),1,0)) | M24: =IF(J24="","",INDEX(Rider_Input[Completed Orders],I24)) | N24: =IF(OR(J24="",K24=""),"",IFERROR(INDEX(RLVL_Data,K24,c_RLVL_Orders),"")) | O24: =IF(J24="","",IF(COUNTIF($J$6:$J$505,J24)>1,1,0)) | P24: =IF(J24="","",IF(K24="","Not found in Paste_RLVL – deductions set to 0; ","")&IF(L24=0,"New rider (not in Rider_Master) – OK, shown as Rider <ID>; ","")&IF(AND(N24<>"",N24<>M24),"Orders differ: FTR "&M24&" vs RLVL "&N24&"; ","")&IF(O24=1,"Duplicate Rider ID; ","")) | Q24: =IF(P24="","",COUNTIF(P$6:P24,"?*"))
I25: 20 | J25: =IFERROR(IF(INDEX(Rider_Input[Rider ID],I25)="","",INDEX(Rider_Input[Rider ID],I25)),"") | K25: =IF(J25="","",IFERROR(MATCH(J25,INDEX(RLVL_Data,0,c_RLVL_ID),0),"")) | L25: =IF(J25="","",IF(ISNUMBER(MATCH(J25,Rider_Master[Rider ID],0)),1,0)) | M25: =IF(J25="","",INDEX(Rider_Input[Completed Orders],I25)) | N25: =IF(OR(J25="",K25=""),"",IFERROR(INDEX(RLVL_Data,K25,c_RLVL_Orders),"")) | O25: =IF(J25="","",IF(COUNTIF($J$6:$J$505,J25)>1,1,0)) | P25: =IF(J25="","",IF(K25="","Not found in Paste_RLVL – deductions set to 0; ","")&IF(L25=0,"New rider (not in Rider_Master) – OK, shown as Rider <ID>; ","")&IF(AND(N25<>"",N25<>M25),"Orders differ: FTR "&M25&" vs RLVL "&N25&"; ","")&IF(O25=1,"Duplicate Rider ID; ","")) | Q25: =IF(P25="","",COUNTIF(P$6:P25,"?*"))
B26: Column Mapping – finds each column by header text (use * as wildcard); edit only if the export headers change | I26: 21 | J26: =IFERROR(IF(INDEX(Rider_Input[Rider ID],I26)="","",INDEX(Rider_Input[Rider ID],I26)),"") | K26: =IF(J26="","",IFERROR(MATCH(J26,INDEX(RLVL_Data,0,c_RLVL_ID),0),"")) | L26: =IF(J26="","",IF(ISNUMBER(MATCH(J26,Rider_Master[Rider ID],0)),1,0)) | M26: =IF(J26="","",INDEX(Rider_Input[Completed Orders],I26)) | N26: =IF(OR(J26="",K26=""),"",IFERROR(INDEX(RLVL_Data,K26,c_RLVL_Orders),"")) | O26: =IF(J26="","",IF(COUNTIF($J$6:$J$505,J26)>1,1,0)) | P26: =IF(J26="","",IF(K26="","Not found in Paste_RLVL – deductions set to 0; ","")&IF(L26=0,"New rider (not in Rider_Master) – OK, shown as Rider <ID>; ","")&IF(AND(N26<>"",N26<>M26),"Orders differ: FTR "&M26&" vs RLVL "&N26&"; ","")&IF(O26=1,"Duplicate Rider ID; ","")) | Q26: =IF(P26="","",COUNTIF(P$6:P26,"?*"))
B27: Field | C27: Header contains / text | D27: Sheet | E27: Column # | F27: Found? | I27: 22 | J27: =IFERROR(IF(INDEX(Rider_Input[Rider ID],I27)="","",INDEX(Rider_Input[Rider ID],I27)),"") | K27: =IF(J27="","",IFERROR(MATCH(J27,INDEX(RLVL_Data,0,c_RLVL_ID),0),"")) | L27: =IF(J27="","",IF(ISNUMBER(MATCH(J27,Rider_Master[Rider ID],0)),1,0)) | M27: =IF(J27="","",INDEX(Rider_Input[Completed Orders],I27)) | N27: =IF(OR(J27="",K27=""),"",IFERROR(INDEX(RLVL_Data,K27,c_RLVL_Orders),"")) | O27: =IF(J27="","",IF(COUNTIF($J$6:$J$505,J27)>1,1,0)) | P27: =IF(J27="","",IF(K27="","Not found in Paste_RLVL – deductions set to 0; ","")&IF(L27=0,"New rider (not in Rider_Master) – OK, shown as Rider <ID>; ","")&IF(AND(N27<>"",N27<>M27),"Orders differ: FTR "&M27&" vs RLVL "&N27&"; ","")&IF(O27=1,"Duplicate Rider ID; ","")) | Q27: =IF(P27="","",COUNTIF(P$6:P27,"?*"))
B28: Rider ID (FTR) | C28: *rider_id | D28: Paste_FTR | E28: =IFERROR(MATCH($C28,Paste_FTR!$A$1:$BZ$1,0),"not found") -> 2 | F28: =IF(ISNUMBER(E28),"OK","MISSING") -> OK | I28: 23 | J28: =IFERROR(IF(INDEX(Rider_Input[Rider ID],I28)="","",INDEX(Rider_Input[Rider ID],I28)),"") | K28: =IF(J28="","",IFERROR(MATCH(J28,INDEX(RLVL_Data,0,c_RLVL_ID),0),"")) | L28: =IF(J28="","",IF(ISNUMBER(MATCH(J28,Rider_Master[Rider ID],0)),1,0)) | M28: =IF(J28="","",INDEX(Rider_Input[Completed Orders],I28)) | N28: =IF(OR(J28="",K28=""),"",IFERROR(INDEX(RLVL_Data,K28,c_RLVL_Orders),"")) | O28: =IF(J28="","",IF(COUNTIF($J$6:$J$505,J28)>1,1,0)) | P28: =IF(J28="","",IF(K28="","Not found in Paste_RLVL – deductions set to 0; ","")&IF(L28=0,"New rider (not in Rider_Master) – OK, shown as Rider <ID>; ","")&IF(AND(N28<>"",N28<>M28),"Orders differ: FTR "&M28&" vs RLVL "&N28&"; ","")&IF(O28=1,"Duplicate Rider ID; ","")) | Q28: =IF(P28="","",COUNTIF(P$6:P28,"?*"))
B29: Completed Orders (FTR) | C29: *completed_orders | D29: Paste_FTR | E29: =IFERROR(MATCH($C29,Paste_FTR!$A$1:$BZ$1,0),"not found") -> 8 | F29: =IF(ISNUMBER(E29),"OK","MISSING") -> OK | I29: 24 | J29: =IFERROR(IF(INDEX(Rider_Input[Rider ID],I29)="","",INDEX(Rider_Input[Rider ID],I29)),"") | K29: =IF(J29="","",IFERROR(MATCH(J29,INDEX(RLVL_Data,0,c_RLVL_ID),0),"")) | L29: =IF(J29="","",IF(ISNUMBER(MATCH(J29,Rider_Master[Rider ID],0)),1,0)) | M29: =IF(J29="","",INDEX(Rider_Input[Completed Orders],I29)) | N29: =IF(OR(J29="",K29=""),"",IFERROR(INDEX(RLVL_Data,K29,c_RLVL_Orders),"")) | O29: =IF(J29="","",IF(COUNTIF($J$6:$J$505,J29)>1,1,0)) | P29: =IF(J29="","",IF(K29="","Not found in Paste_RLVL – deductions set to 0; ","")&IF(L29=0,"New rider (not in Rider_Master) – OK, shown as Rider <ID>; ","")&IF(AND(N29<>"",N29<>M29),"Orders differ: FTR "&M29&" vs RLVL "&N29&"; ","")&IF(O29=1,"Duplicate Rider ID; ","")) | Q29: =IF(P29="","",COUNTIF(P$6:P29,"?*"))
B30: Working Days (FTR) | C30: working_days | D30: Paste_FTR | E30: =IFERROR(MATCH($C30,Paste_FTR!$A$1:$BZ$1,0),"not found") -> 12 | F30: =IF(ISNUMBER(E30),"OK","MISSING") -> OK | I30: 25 | J30: =IFERROR(IF(INDEX(Rider_Input[Rider ID],I30)="","",INDEX(Rider_Input[Rider ID],I30)),"") | K30: =IF(J30="","",IFERROR(MATCH(J30,INDEX(RLVL_Data,0,c_RLVL_ID),0),"")) | L30: =IF(J30="","",IF(ISNUMBER(MATCH(J30,Rider_Master[Rider ID],0)),1,0)) | M30: =IF(J30="","",INDEX(Rider_Input[Completed Orders],I30)) | N30: =IF(OR(J30="",K30=""),"",IFERROR(INDEX(RLVL_Data,K30,c_RLVL_Orders),"")) | O30: =IF(J30="","",IF(COUNTIF($J$6:$J$505,J30)>1,1,0)) | P30: =IF(J30="","",IF(K30="","Not found in Paste_RLVL – deductions set to 0; ","")&IF(L30=0,"New rider (not in Rider_Master) – OK, shown as Rider <ID>; ","")&IF(AND(N30<>"",N30<>M30),"Orders differ: FTR "&M30&" vs RLVL "&N30&"; ","")&IF(O30=1,"Duplicate Rider ID; ","")) | Q30: =IF(P30="","",COUNTIF(P$6:P30,"?*"))
B31: Rider ID (RLVL) | C31: *rider_id | D31: Paste_RLVL | E31: =IFERROR(MATCH($C31,Paste_RLVL!$A$1:$BZ$1,0),"not found") -> 1 | F31: =IF(ISNUMBER(E31),"OK","MISSING") -> OK | I31: 26 | J31: =IFERROR(IF(INDEX(Rider_Input[Rider ID],I31)="","",INDEX(Rider_Input[Rider ID],I31)),"") | K31: =IF(J31="","",IFERROR(MATCH(J31,INDEX(RLVL_Data,0,c_RLVL_ID),0),"")) | L31: =IF(J31="","",IF(ISNUMBER(MATCH(J31,Rider_Master[Rider ID],0)),1,0)) | M31: =IF(J31="","",INDEX(Rider_Input[Completed Orders],I31)) | N31: =IF(OR(J31="",K31=""),"",IFERROR(INDEX(RLVL_Data,K31,c_RLVL_Orders),"")) | O31: =IF(J31="","",IF(COUNTIF($J$6:$J$505,J31)>1,1,0)) | P31: =IF(J31="","",IF(K31="","Not found in Paste_RLVL – deductions set to 0; ","")&IF(L31=0,"New rider (not in Rider_Master) – OK, shown as Rider <ID>; ","")&IF(AND(N31<>"",N31<>M31),"Orders differ: FTR "&M31&" vs RLVL "&N31&"; ","")&IF(O31=1,"Duplicate Rider ID; ","")) | Q31: =IF(P31="","",COUNTIF(P$6:P31,"?*"))
B32: Completed Orders (RLVL, cross-check only) | C32: *completed_orders | D32: Paste_RLVL | E32: =IFERROR(MATCH($C32,Paste_RLVL!$A$1:$BZ$1,0),"not found") -> 3 | F32: =IF(ISNUMBER(E32),"OK","MISSING") -> OK | I32: 27 | J32: =IFERROR(IF(INDEX(Rider_Input[Rider ID],I32)="","",INDEX(Rider_Input[Rider ID],I32)),"") | K32: =IF(J32="","",IFERROR(MATCH(J32,INDEX(RLVL_Data,0,c_RLVL_ID),0),"")) | L32: =IF(J32="","",IF(ISNUMBER(MATCH(J32,Rider_Master[Rider ID],0)),1,0)) | M32: =IF(J32="","",INDEX(Rider_Input[Completed Orders],I32)) | N32: =IF(OR(J32="",K32=""),"",IFERROR(INDEX(RLVL_Data,K32,c_RLVL_Orders),"")) | O32: =IF(J32="","",IF(COUNTIF($J$6:$J$505,J32)>1,1,0)) | P32: =IF(J32="","",IF(K32="","Not found in Paste_RLVL – deductions set to 0; ","")&IF(L32=0,"New rider (not in Rider_Master) – OK, shown as Rider <ID>; ","")&IF(AND(N32<>"",N32<>M32),"Orders differ: FTR "&M32&" vs RLVL "&N32&"; ","")&IF(O32=1,"Duplicate Rider ID; ","")) | Q32: =IF(P32="","",COUNTIF(P$6:P32,"?*"))
B33: missed_days_penalty (RLVL) | C33: *missed_days_penalty | D33: Paste_RLVL | E33: =IFERROR(MATCH($C33,Paste_RLVL!$A$1:$BZ$1,0),"not found") -> 12 | F33: =IF(ISNUMBER(E33),"OK","MISSING") -> OK | I33: 28 | J33: =IFERROR(IF(INDEX(Rider_Input[Rider ID],I33)="","",INDEX(Rider_Input[Rider ID],I33)),"") | K33: =IF(J33="","",IFERROR(MATCH(J33,INDEX(RLVL_Data,0,c_RLVL_ID),0),"")) | L33: =IF(J33="","",IF(ISNUMBER(MATCH(J33,Rider_Master[Rider ID],0)),1,0)) | M33: =IF(J33="","",INDEX(Rider_Input[Completed Orders],I33)) | N33: =IF(OR(J33="",K33=""),"",IFERROR(INDEX(RLVL_Data,K33,c_RLVL_Orders),"")) | O33: =IF(J33="","",IF(COUNTIF($J$6:$J$505,J33)>1,1,0)) | P33: =IF(J33="","",IF(K33="","Not found in Paste_RLVL – deductions set to 0; ","")&IF(L33=0,"New rider (not in Rider_Master) – OK, shown as Rider <ID>; ","")&IF(AND(N33<>"",N33<>M33),"Orders differ: FTR "&M33&" vs RLVL "&N33&"; ","")&IF(O33=1,"Duplicate Rider ID; ","")) | Q33: =IF(P33="","",COUNTIF(P$6:P33,"?*"))
B34: Rider Balance (RLVL) | C34: *Rider Balance | D34: Paste_RLVL | E34: =IFERROR(MATCH($C34,Paste_RLVL!$A$1:$BZ$1,0),"not found") -> 16 | F34: =IF(ISNUMBER(E34),"OK","MISSING") -> OK | I34: 29 | J34: =IFERROR(IF(INDEX(Rider_Input[Rider ID],I34)="","",INDEX(Rider_Input[Rider ID],I34)),"") | K34: =IF(J34="","",IFERROR(MATCH(J34,INDEX(RLVL_Data,0,c_RLVL_ID),0),"")) | L34: =IF(J34="","",IF(ISNUMBER(MATCH(J34,Rider_Master[Rider ID],0)),1,0)) | M34: =IF(J34="","",INDEX(Rider_Input[Completed Orders],I34)) | N34: =IF(OR(J34="",K34=""),"",IFERROR(INDEX(RLVL_Data,K34,c_RLVL_Orders),"")) | O34: =IF(J34="","",IF(COUNTIF($J$6:$J$505,J34)>1,1,0)) | P34: =IF(J34="","",IF(K34="","Not found in Paste_RLVL – deductions set to 0; ","")&IF(L34=0,"New rider (not in Rider_Master) – OK, shown as Rider <ID>; ","")&IF(AND(N34<>"",N34<>M34),"Orders differ: FTR "&M34&" vs RLVL "&N34&"; ","")&IF(O34=1,"Duplicate Rider ID; ","")) | Q34: =IF(P34="","",COUNTIF(P$6:P34,"?*"))
B35: stacking_deduction (RLVL) | C35: *stacking_deduction | D35: Paste_RLVL | E35: =IFERROR(MATCH($C35,Paste_RLVL!$A$1:$BZ$1,0),"not found") -> 5 | F35: =IF(ISNUMBER(E35),"OK","MISSING") -> OK | I35: 30 | J35: =IFERROR(IF(INDEX(Rider_Input[Rider ID],I35)="","",INDEX(Rider_Input[Rider ID],I35)),"") | K35: =IF(J35="","",IFERROR(MATCH(J35,INDEX(RLVL_Data,0,c_RLVL_ID),0),"")) | L35: =IF(J35="","",IF(ISNUMBER(MATCH(J35,Rider_Master[Rider ID],0)),1,0)) | M35: =IF(J35="","",INDEX(Rider_Input[Completed Orders],I35)) | N35: =IF(OR(J35="",K35=""),"",IFERROR(INDEX(RLVL_Data,K35,c_RLVL_Orders),"")) | O35: =IF(J35="","",IF(COUNTIF($J$6:$J$505,J35)>1,1,0)) | P35: =IF(J35="","",IF(K35="","Not found in Paste_RLVL – deductions set to 0; ","")&IF(L35=0,"New rider (not in Rider_Master) – OK, shown as Rider <ID>; ","")&IF(AND(N35<>"",N35<>M35),"Orders differ: FTR "&M35&" vs RLVL "&N35&"; ","")&IF(O35=1,"Duplicate Rider ID; ","")) | Q35: =IF(P35="","",COUNTIF(P$6:P35,"?*"))
I36: 31 | J36: =IFERROR(IF(INDEX(Rider_Input[Rider ID],I36)="","",INDEX(Rider_Input[Rider ID],I36)),"") | K36: =IF(J36="","",IFERROR(MATCH(J36,INDEX(RLVL_Data,0,c_RLVL_ID),0),"")) | L36: =IF(J36="","",IF(ISNUMBER(MATCH(J36,Rider_Master[Rider ID],0)),1,0)) | M36: =IF(J36="","",INDEX(Rider_Input[Completed Orders],I36)) | N36: =IF(OR(J36="",K36=""),"",IFERROR(INDEX(RLVL_Data,K36,c_RLVL_Orders),"")) | O36: =IF(J36="","",IF(COUNTIF($J$6:$J$505,J36)>1,1,0)) | P36: =IF(J36="","",IF(K36="","Not found in Paste_RLVL – deductions set to 0; ","")&IF(L36=0,"New rider (not in Rider_Master) – OK, shown as Rider <ID>; ","")&IF(AND(N36<>"",N36<>M36),"Orders differ: FTR "&M36&" vs RLVL "&N36&"; ","")&IF(O36=1,"Duplicate Rider ID; ","")) | Q36: =IF(P36="","",COUNTIF(P$6:P36,"?*"))
I37: 32 | J37: =IFERROR(IF(INDEX(Rider_Input[Rider ID],I37)="","",INDEX(Rider_Input[Rider ID],I37)),"") | K37: =IF(J37="","",IFERROR(MATCH(J37,INDEX(RLVL_Data,0,c_RLVL_ID),0),"")) | L37: =IF(J37="","",IF(ISNUMBER(MATCH(J37,Rider_Master[Rider ID],0)),1,0)) | M37: =IF(J37="","",INDEX(Rider_Input[Completed Orders],I37)) | N37: =IF(OR(J37="",K37=""),"",IFERROR(INDEX(RLVL_Data,K37,c_RLVL_Orders),"")) | O37: =IF(J37="","",IF(COUNTIF($J$6:$J$505,J37)>1,1,0)) | P37: =IF(J37="","",IF(K37="","Not found in Paste_RLVL – deductions set to 0; ","")&IF(L37=0,"New rider (not in Rider_Master) – OK, shown as Rider <ID>; ","")&IF(AND(N37<>"",N37<>M37),"Orders differ: FTR "&M37&" vs RLVL "&N37&"; ","")&IF(O37=1,"Duplicate Rider ID; ","")) | Q37: =IF(P37="","",COUNTIF(P$6:P37,"?*"))
B38: Items to review – first 25 (all riders, full list in helper column P) | I38: 33 | J38: =IFERROR(IF(INDEX(Rider_Input[Rider ID],I38)="","",INDEX(Rider_Input[Rider ID],I38)),"") | K38: =IF(J38="","",IFERROR(MATCH(J38,INDEX(RLVL_Data,0,c_RLVL_ID),0),"")) | L38: =IF(J38="","",IF(ISNUMBER(MATCH(J38,Rider_Master[Rider ID],0)),1,0)) | M38: =IF(J38="","",INDEX(Rider_Input[Completed Orders],I38)) | N38: =IF(OR(J38="",K38=""),"",IFERROR(INDEX(RLVL_Data,K38,c_RLVL_Orders),"")) | O38: =IF(J38="","",IF(COUNTIF($J$6:$J$505,J38)>1,1,0)) | P38: =IF(J38="","",IF(K38="","Not found in Paste_RLVL – deductions set to 0; ","")&IF(L38=0,"New rider (not in Rider_Master) – OK, shown as Rider <ID>; ","")&IF(AND(N38<>"",N38<>M38),"Orders differ: FTR "&M38&" vs RLVL "&N38&"; ","")&IF(O38=1,"Duplicate Rider ID; ","")) | Q38: =IF(P38="","",COUNTIF(P$6:P38,"?*"))
B39: Rider ID | C39: Issue | I39: 34 | J39: =IFERROR(IF(INDEX(Rider_Input[Rider ID],I39)="","",INDEX(Rider_Input[Rider ID],I39)),"") | K39: =IF(J39="","",IFERROR(MATCH(J39,INDEX(RLVL_Data,0,c_RLVL_ID),0),"")) | L39: =IF(J39="","",IF(ISNUMBER(MATCH(J39,Rider_Master[Rider ID],0)),1,0)) | M39: =IF(J39="","",INDEX(Rider_Input[Completed Orders],I39)) | N39: =IF(OR(J39="",K39=""),"",IFERROR(INDEX(RLVL_Data,K39,c_RLVL_Orders),"")) | O39: =IF(J39="","",IF(COUNTIF($J$6:$J$505,J39)>1,1,0)) | P39: =IF(J39="","",IF(K39="","Not found in Paste_RLVL – deductions set to 0; ","")&IF(L39=0,"New rider (not in Rider_Master) – OK, shown as Rider <ID>; ","")&IF(AND(N39<>"",N39<>M39),"Orders differ: FTR "&M39&" vs RLVL "&N39&"; ","")&IF(O39=1,"Duplicate Rider ID; ","")) | Q39: =IF(P39="","",COUNTIF(P$6:P39,"?*"))
B40: =IFERROR(INDEX($J$6:$J$505,MATCH(1,$Q$6:$Q$505,0)),"") | C40: =IFERROR(INDEX($P$6:$P$505,MATCH(1,$Q$6:$Q$505,0)),"") | I40: 35 | J40: =IFERROR(IF(INDEX(Rider_Input[Rider ID],I40)="","",INDEX(Rider_Input[Rider ID],I40)),"") | K40: =IF(J40="","",IFERROR(MATCH(J40,INDEX(RLVL_Data,0,c_RLVL_ID),0),"")) | L40: =IF(J40="","",IF(ISNUMBER(MATCH(J40,Rider_Master[Rider ID],0)),1,0)) | M40: =IF(J40="","",INDEX(Rider_Input[Completed Orders],I40)) | N40: =IF(OR(J40="",K40=""),"",IFERROR(INDEX(RLVL_Data,K40,c_RLVL_Orders),"")) | O40: =IF(J40="","",IF(COUNTIF($J$6:$J$505,J40)>1,1,0)) | P40: =IF(J40="","",IF(K40="","Not found in Paste_RLVL – deductions set to 0; ","")&IF(L40=0,"New rider (not in Rider_Master) – OK, shown as Rider <ID>; ","")&IF(AND(N40<>"",N40<>M40),"Orders differ: FTR "&M40&" vs RLVL "&N40&"; ","")&IF(O40=1,"Duplicate Rider ID; ","")) | Q40: =IF(P40="","",COUNTIF(P$6:P40,"?*"))
B41: =IFERROR(INDEX($J$6:$J$505,MATCH(2,$Q$6:$Q$505,0)),"") | C41: =IFERROR(INDEX($P$6:$P$505,MATCH(2,$Q$6:$Q$505,0)),"") | I41: 36 | J41: =IFERROR(IF(INDEX(Rider_Input[Rider ID],I41)="","",INDEX(Rider_Input[Rider ID],I41)),"") | K41: =IF(J41="","",IFERROR(MATCH(J41,INDEX(RLVL_Data,0,c_RLVL_ID),0),"")) | L41: =IF(J41="","",IF(ISNUMBER(MATCH(J41,Rider_Master[Rider ID],0)),1,0)) | M41: =IF(J41="","",INDEX(Rider_Input[Completed Orders],I41)) | N41: =IF(OR(J41="",K41=""),"",IFERROR(INDEX(RLVL_Data,K41,c_RLVL_Orders),"")) | O41: =IF(J41="","",IF(COUNTIF($J$6:$J$505,J41)>1,1,0)) | P41: =IF(J41="","",IF(K41="","Not found in Paste_RLVL – deductions set to 0; ","")&IF(L41=0,"New rider (not in Rider_Master) – OK, shown as Rider <ID>; ","")&IF(AND(N41<>"",N41<>M41),"Orders differ: FTR "&M41&" vs RLVL "&N41&"; ","")&IF(O41=1,"Duplicate Rider ID; ","")) | Q41: =IF(P41="","",COUNTIF(P$6:P41,"?*"))
B42: =IFERROR(INDEX($J$6:$J$505,MATCH(3,$Q$6:$Q$505,0)),"") | C42: =IFERROR(INDEX($P$6:$P$505,MATCH(3,$Q$6:$Q$505,0)),"") | I42: 37 | J42: =IFERROR(IF(INDEX(Rider_Input[Rider ID],I42)="","",INDEX(Rider_Input[Rider ID],I42)),"") | K42: =IF(J42="","",IFERROR(MATCH(J42,INDEX(RLVL_Data,0,c_RLVL_ID),0),"")) | L42: =IF(J42="","",IF(ISNUMBER(MATCH(J42,Rider_Master[Rider ID],0)),1,0)) | M42: =IF(J42="","",INDEX(Rider_Input[Completed Orders],I42)) | N42: =IF(OR(J42="",K42=""),"",IFERROR(INDEX(RLVL_Data,K42,c_RLVL_Orders),"")) | O42: =IF(J42="","",IF(COUNTIF($J$6:$J$505,J42)>1,1,0)) | P42: =IF(J42="","",IF(K42="","Not found in Paste_RLVL – deductions set to 0; ","")&IF(L42=0,"New rider (not in Rider_Master) – OK, shown as Rider <ID>; ","")&IF(AND(N42<>"",N42<>M42),"Orders differ: FTR "&M42&" vs RLVL "&N42&"; ","")&IF(O42=1,"Duplicate Rider ID; ","")) | Q42: =IF(P42="","",COUNTIF(P$6:P42,"?*"))
B43: =IFERROR(INDEX($J$6:$J$505,MATCH(4,$Q$6:$Q$505,0)),"") | C43: =IFERROR(INDEX($P$6:$P$505,MATCH(4,$Q$6:$Q$505,0)),"") | I43: 38 | J43: =IFERROR(IF(INDEX(Rider_Input[Rider ID],I43)="","",INDEX(Rider_Input[Rider ID],I43)),"") | K43: =IF(J43="","",IFERROR(MATCH(J43,INDEX(RLVL_Data,0,c_RLVL_ID),0),"")) | L43: =IF(J43="","",IF(ISNUMBER(MATCH(J43,Rider_Master[Rider ID],0)),1,0)) | M43: =IF(J43="","",INDEX(Rider_Input[Completed Orders],I43)) | N43: =IF(OR(J43="",K43=""),"",IFERROR(INDEX(RLVL_Data,K43,c_RLVL_Orders),"")) | O43: =IF(J43="","",IF(COUNTIF($J$6:$J$505,J43)>1,1,0)) | P43: =IF(J43="","",IF(K43="","Not found in Paste_RLVL – deductions set to 0; ","")&IF(L43=0,"New rider (not in Rider_Master) – OK, shown as Rider <ID>; ","")&IF(AND(N43<>"",N43<>M43),"Orders differ: FTR "&M43&" vs RLVL "&N43&"; ","")&IF(O43=1,"Duplicate Rider ID; ","")) | Q43: =IF(P43="","",COUNTIF(P$6:P43,"?*"))
B44: =IFERROR(INDEX($J$6:$J$505,MATCH(5,$Q$6:$Q$505,0)),"") | C44: =IFERROR(INDEX($P$6:$P$505,MATCH(5,$Q$6:$Q$505,0)),"") | I44: 39 | J44: =IFERROR(IF(INDEX(Rider_Input[Rider ID],I44)="","",INDEX(Rider_Input[Rider ID],I44)),"") | K44: =IF(J44="","",IFERROR(MATCH(J44,INDEX(RLVL_Data,0,c_RLVL_ID),0),"")) | L44: =IF(J44="","",IF(ISNUMBER(MATCH(J44,Rider_Master[Rider ID],0)),1,0)) | M44: =IF(J44="","",INDEX(Rider_Input[Completed Orders],I44)) | N44: =IF(OR(J44="",K44=""),"",IFERROR(INDEX(RLVL_Data,K44,c_RLVL_Orders),"")) | O44: =IF(J44="","",IF(COUNTIF($J$6:$J$505,J44)>1,1,0)) | P44: =IF(J44="","",IF(K44="","Not found in Paste_RLVL – deductions set to 0; ","")&IF(L44=0,"New rider (not in Rider_Master) – OK, shown as Rider <ID>; ","")&IF(AND(N44<>"",N44<>M44),"Orders differ: FTR "&M44&" vs RLVL "&N44&"; ","")&IF(O44=1,"Duplicate Rider ID; ","")) | Q44: =IF(P44="","",COUNTIF(P$6:P44,"?*"))
B45: =IFERROR(INDEX($J$6:$J$505,MATCH(6,$Q$6:$Q$505,0)),"") | C45: =IFERROR(INDEX($P$6:$P$505,MATCH(6,$Q$6:$Q$505,0)),"") | I45: 40 | J45: =IFERROR(IF(INDEX(Rider_Input[Rider ID],I45)="","",INDEX(Rider_Input[Rider ID],I45)),"") | K45: =IF(J45="","",IFERROR(MATCH(J45,INDEX(RLVL_Data,0,c_RLVL_ID),0),"")) | L45: =IF(J45="","",IF(ISNUMBER(MATCH(J45,Rider_Master[Rider ID],0)),1,0)) | M45: =IF(J45="","",INDEX(Rider_Input[Completed Orders],I45)) | N45: =IF(OR(J45="",K45=""),"",IFERROR(INDEX(RLVL_Data,K45,c_RLVL_Orders),"")) | O45: =IF(J45="","",IF(COUNTIF($J$6:$J$505,J45)>1,1,0)) | P45: =IF(J45="","",IF(K45="","Not found in Paste_RLVL – deductions set to 0; ","")&IF(L45=0,"New rider (not in Rider_Master) – OK, shown as Rider <ID>; ","")&IF(AND(N45<>"",N45<>M45),"Orders differ: FTR "&M45&" vs RLVL "&N45&"; ","")&IF(O45=1,"Duplicate Rider ID; ","")) | Q45: =IF(P45="","",COUNTIF(P$6:P45,"?*"))
B46: =IFERROR(INDEX($J$6:$J$505,MATCH(7,$Q$6:$Q$505,0)),"") | C46: =IFERROR(INDEX($P$6:$P$505,MATCH(7,$Q$6:$Q$505,0)),"") | I46: 41 | J46: =IFERROR(IF(INDEX(Rider_Input[Rider ID],I46)="","",INDEX(Rider_Input[Rider ID],I46)),"") | K46: =IF(J46="","",IFERROR(MATCH(J46,INDEX(RLVL_Data,0,c_RLVL_ID),0),"")) | L46: =IF(J46="","",IF(ISNUMBER(MATCH(J46,Rider_Master[Rider ID],0)),1,0)) | M46: =IF(J46="","",INDEX(Rider_Input[Completed Orders],I46)) | N46: =IF(OR(J46="",K46=""),"",IFERROR(INDEX(RLVL_Data,K46,c_RLVL_Orders),"")) | O46: =IF(J46="","",IF(COUNTIF($J$6:$J$505,J46)>1,1,0)) | P46: =IF(J46="","",IF(K46="","Not found in Paste_RLVL – deductions set to 0; ","")&IF(L46=0,"New rider (not in Rider_Master) – OK, shown as Rider <ID>; ","")&IF(AND(N46<>"",N46<>M46),"Orders differ: FTR "&M46&" vs RLVL "&N46&"; ","")&IF(O46=1,"Duplicate Rider ID; ","")) | Q46: =IF(P46="","",COUNTIF(P$6:P46,"?*"))
B47: =IFERROR(INDEX($J$6:$J$505,MATCH(8,$Q$6:$Q$505,0)),"") | C47: =IFERROR(INDEX($P$6:$P$505,MATCH(8,$Q$6:$Q$505,0)),"") | I47: 42 | J47: =IFERROR(IF(INDEX(Rider_Input[Rider ID],I47)="","",INDEX(Rider_Input[Rider ID],I47)),"") | K47: =IF(J47="","",IFERROR(MATCH(J47,INDEX(RLVL_Data,0,c_RLVL_ID),0),"")) | L47: =IF(J47="","",IF(ISNUMBER(MATCH(J47,Rider_Master[Rider ID],0)),1,0)) | M47: =IF(J47="","",INDEX(Rider_Input[Completed Orders],I47)) | N47: =IF(OR(J47="",K47=""),"",IFERROR(INDEX(RLVL_Data,K47,c_RLVL_Orders),"")) | O47: =IF(J47="","",IF(COUNTIF($J$6:$J$505,J47)>1,1,0)) | P47: =IF(J47="","",IF(K47="","Not found in Paste_RLVL – deductions set to 0; ","")&IF(L47=0,"New rider (not in Rider_Master) – OK, shown as Rider <ID>; ","")&IF(AND(N47<>"",N47<>M47),"Orders differ: FTR "&M47&" vs RLVL "&N47&"; ","")&IF(O47=1,"Duplicate Rider ID; ","")) | Q47: =IF(P47="","",COUNTIF(P$6:P47,"?*"))
B48: =IFERROR(INDEX($J$6:$J$505,MATCH(9,$Q$6:$Q$505,0)),"") | C48: =IFERROR(INDEX($P$6:$P$505,MATCH(9,$Q$6:$Q$505,0)),"") | I48: 43 | J48: =IFERROR(IF(INDEX(Rider_Input[Rider ID],I48)="","",INDEX(Rider_Input[Rider ID],I48)),"") | K48: =IF(J48="","",IFERROR(MATCH(J48,INDEX(RLVL_Data,0,c_RLVL_ID),0),"")) | L48: =IF(J48="","",IF(ISNUMBER(MATCH(J48,Rider_Master[Rider ID],0)),1,0)) | M48: =IF(J48="","",INDEX(Rider_Input[Completed Orders],I48)) | N48: =IF(OR(J48="",K48=""),"",IFERROR(INDEX(RLVL_Data,K48,c_RLVL_Orders),"")) | O48: =IF(J48="","",IF(COUNTIF($J$6:$J$505,J48)>1,1,0)) | P48: =IF(J48="","",IF(K48="","Not found in Paste_RLVL – deductions set to 0; ","")&IF(L48=0,"New rider (not in Rider_Master) – OK, shown as Rider <ID>; ","")&IF(AND(N48<>"",N48<>M48),"Orders differ: FTR "&M48&" vs RLVL "&N48&"; ","")&IF(O48=1,"Duplicate Rider ID; ","")) | Q48: =IF(P48="","",COUNTIF(P$6:P48,"?*"))
B49: =IFERROR(INDEX($J$6:$J$505,MATCH(10,$Q$6:$Q$505,0)),"") | C49: =IFERROR(INDEX($P$6:$P$505,MATCH(10,$Q$6:$Q$505,0)),"") | I49: 44 | J49: =IFERROR(IF(INDEX(Rider_Input[Rider ID],I49)="","",INDEX(Rider_Input[Rider ID],I49)),"") | K49: =IF(J49="","",IFERROR(MATCH(J49,INDEX(RLVL_Data,0,c_RLVL_ID),0),"")) | L49: =IF(J49="","",IF(ISNUMBER(MATCH(J49,Rider_Master[Rider ID],0)),1,0)) | M49: =IF(J49="","",INDEX(Rider_Input[Completed Orders],I49)) | N49: =IF(OR(J49="",K49=""),"",IFERROR(INDEX(RLVL_Data,K49,c_RLVL_Orders),"")) | O49: =IF(J49="","",IF(COUNTIF($J$6:$J$505,J49)>1,1,0)) | P49: =IF(J49="","",IF(K49="","Not found in Paste_RLVL – deductions set to 0; ","")&IF(L49=0,"New rider (not in Rider_Master) – OK, shown as Rider <ID>; ","")&IF(AND(N49<>"",N49<>M49),"Orders differ: FTR "&M49&" vs RLVL "&N49&"; ","")&IF(O49=1,"Duplicate Rider ID; ","")) | Q49: =IF(P49="","",COUNTIF(P$6:P49,"?*"))
B50: =IFERROR(INDEX($J$6:$J$505,MATCH(11,$Q$6:$Q$505,0)),"") | C50: =IFERROR(INDEX($P$6:$P$505,MATCH(11,$Q$6:$Q$505,0)),"") | I50: 45 | J50: =IFERROR(IF(INDEX(Rider_Input[Rider ID],I50)="","",INDEX(Rider_Input[Rider ID],I50)),"") | K50: =IF(J50="","",IFERROR(MATCH(J50,INDEX(RLVL_Data,0,c_RLVL_ID),0),"")) | L50: =IF(J50="","",IF(ISNUMBER(MATCH(J50,Rider_Master[Rider ID],0)),1,0)) | M50: =IF(J50="","",INDEX(Rider_Input[Completed Orders],I50)) | N50: =IF(OR(J50="",K50=""),"",IFERROR(INDEX(RLVL_Data,K50,c_RLVL_Orders),"")) | O50: =IF(J50="","",IF(COUNTIF($J$6:$J$505,J50)>1,1,0)) | P50: =IF(J50="","",IF(K50="","Not found in Paste_RLVL – deductions set to 0; ","")&IF(L50=0,"New rider (not in Rider_Master) – OK, shown as Rider <ID>; ","")&IF(AND(N50<>"",N50<>M50),"Orders differ: FTR "&M50&" vs RLVL "&N50&"; ","")&IF(O50=1,"Duplicate Rider ID; ","")) | Q50: =IF(P50="","",COUNTIF(P$6:P50,"?*"))
B51: =IFERROR(INDEX($J$6:$J$505,MATCH(12,$Q$6:$Q$505,0)),"") | C51: =IFERROR(INDEX($P$6:$P$505,MATCH(12,$Q$6:$Q$505,0)),"") | I51: 46 | J51: =IFERROR(IF(INDEX(Rider_Input[Rider ID],I51)="","",INDEX(Rider_Input[Rider ID],I51)),"") | K51: =IF(J51="","",IFERROR(MATCH(J51,INDEX(RLVL_Data,0,c_RLVL_ID),0),"")) | L51: =IF(J51="","",IF(ISNUMBER(MATCH(J51,Rider_Master[Rider ID],0)),1,0)) | M51: =IF(J51="","",INDEX(Rider_Input[Completed Orders],I51)) | N51: =IF(OR(J51="",K51=""),"",IFERROR(INDEX(RLVL_Data,K51,c_RLVL_Orders),"")) | O51: =IF(J51="","",IF(COUNTIF($J$6:$J$505,J51)>1,1,0)) | P51: =IF(J51="","",IF(K51="","Not found in Paste_RLVL – deductions set to 0; ","")&IF(L51=0,"New rider (not in Rider_Master) – OK, shown as Rider <ID>; ","")&IF(AND(N51<>"",N51<>M51),"Orders differ: FTR "&M51&" vs RLVL "&N51&"; ","")&IF(O51=1,"Duplicate Rider ID; ","")) | Q51: =IF(P51="","",COUNTIF(P$6:P51,"?*"))
B52: =IFERROR(INDEX($J$6:$J$505,MATCH(13,$Q$6:$Q$505,0)),"") | C52: =IFERROR(INDEX($P$6:$P$505,MATCH(13,$Q$6:$Q$505,0)),"") | I52: 47 | J52: =IFERROR(IF(INDEX(Rider_Input[Rider ID],I52)="","",INDEX(Rider_Input[Rider ID],I52)),"") | K52: =IF(J52="","",IFERROR(MATCH(J52,INDEX(RLVL_Data,0,c_RLVL_ID),0),"")) | L52: =IF(J52="","",IF(ISNUMBER(MATCH(J52,Rider_Master[Rider ID],0)),1,0)) | M52: =IF(J52="","",INDEX(Rider_Input[Completed Orders],I52)) | N52: =IF(OR(J52="",K52=""),"",IFERROR(INDEX(RLVL_Data,K52,c_RLVL_Orders),"")) | O52: =IF(J52="","",IF(COUNTIF($J$6:$J$505,J52)>1,1,0)) | P52: =IF(J52="","",IF(K52="","Not found in Paste_RLVL – deductions set to 0; ","")&IF(L52=0,"New rider (not in Rider_Master) – OK, shown as Rider <ID>; ","")&IF(AND(N52<>"",N52<>M52),"Orders differ: FTR "&M52&" vs RLVL "&N52&"; ","")&IF(O52=1,"Duplicate Rider ID; ","")) | Q52: =IF(P52="","",COUNTIF(P$6:P52,"?*"))
B53: =IFERROR(INDEX($J$6:$J$505,MATCH(14,$Q$6:$Q$505,0)),"") | C53: =IFERROR(INDEX($P$6:$P$505,MATCH(14,$Q$6:$Q$505,0)),"") | I53: 48 | J53: =IFERROR(IF(INDEX(Rider_Input[Rider ID],I53)="","",INDEX(Rider_Input[Rider ID],I53)),"") | K53: =IF(J53="","",IFERROR(MATCH(J53,INDEX(RLVL_Data,0,c_RLVL_ID),0),"")) | L53: =IF(J53="","",IF(ISNUMBER(MATCH(J53,Rider_Master[Rider ID],0)),1,0)) | M53: =IF(J53="","",INDEX(Rider_Input[Completed Orders],I53)) | N53: =IF(OR(J53="",K53=""),"",IFERROR(INDEX(RLVL_Data,K53,c_RLVL_Orders),"")) | O53: =IF(J53="","",IF(COUNTIF($J$6:$J$505,J53)>1,1,0)) | P53: =IF(J53="","",IF(K53="","Not found in Paste_RLVL – deductions set to 0; ","")&IF(L53=0,"New rider (not in Rider_Master) – OK, shown as Rider <ID>; ","")&IF(AND(N53<>"",N53<>M53),"Orders differ: FTR "&M53&" vs RLVL "&N53&"; ","")&IF(O53=1,"Duplicate Rider ID; ","")) | Q53: =IF(P53="","",COUNTIF(P$6:P53,"?*"))
B54: =IFERROR(INDEX($J$6:$J$505,MATCH(15,$Q$6:$Q$505,0)),"") | C54: =IFERROR(INDEX($P$6:$P$505,MATCH(15,$Q$6:$Q$505,0)),"") | I54: 49 | J54: =IFERROR(IF(INDEX(Rider_Input[Rider ID],I54)="","",INDEX(Rider_Input[Rider ID],I54)),"") | K54: =IF(J54="","",IFERROR(MATCH(J54,INDEX(RLVL_Data,0,c_RLVL_ID),0),"")) | L54: =IF(J54="","",IF(ISNUMBER(MATCH(J54,Rider_Master[Rider ID],0)),1,0)) | M54: =IF(J54="","",INDEX(Rider_Input[Completed Orders],I54)) | N54: =IF(OR(J54="",K54=""),"",IFERROR(INDEX(RLVL_Data,K54,c_RLVL_Orders),"")) | O54: =IF(J54="","",IF(COUNTIF($J$6:$J$505,J54)>1,1,0)) | P54: =IF(J54="","",IF(K54="","Not found in Paste_RLVL – deductions set to 0; ","")&IF(L54=0,"New rider (not in Rider_Master) – OK, shown as Rider <ID>; ","")&IF(AND(N54<>"",N54<>M54),"Orders differ: FTR "&M54&" vs RLVL "&N54&"; ","")&IF(O54=1,"Duplicate Rider ID; ","")) | Q54: =IF(P54="","",COUNTIF(P$6:P54,"?*"))
B55: =IFERROR(INDEX($J$6:$J$505,MATCH(16,$Q$6:$Q$505,0)),"") | C55: =IFERROR(INDEX($P$6:$P$505,MATCH(16,$Q$6:$Q$505,0)),"") | I55: 50 | J55: =IFERROR(IF(INDEX(Rider_Input[Rider ID],I55)="","",INDEX(Rider_Input[Rider ID],I55)),"") | K55: =IF(J55="","",IFERROR(MATCH(J55,INDEX(RLVL_Data,0,c_RLVL_ID),0),"")) | L55: =IF(J55="","",IF(ISNUMBER(MATCH(J55,Rider_Master[Rider ID],0)),1,0)) | M55: =IF(J55="","",INDEX(Rider_Input[Completed Orders],I55)) | N55: =IF(OR(J55="",K55=""),"",IFERROR(INDEX(RLVL_Data,K55,c_RLVL_Orders),"")) | O55: =IF(J55="","",IF(COUNTIF($J$6:$J$505,J55)>1,1,0)) | P55: =IF(J55="","",IF(K55="","Not found in Paste_RLVL – deductions set to 0; ","")&IF(L55=0,"New rider (not in Rider_Master) – OK, shown as Rider <ID>; ","")&IF(AND(N55<>"",N55<>M55),"Orders differ: FTR "&M55&" vs RLVL "&N55&"; ","")&IF(O55=1,"Duplicate Rider ID; ","")) | Q55: =IF(P55="","",COUNTIF(P$6:P55,"?*"))
B56: =IFERROR(INDEX($J$6:$J$505,MATCH(17,$Q$6:$Q$505,0)),"") | C56: =IFERROR(INDEX($P$6:$P$505,MATCH(17,$Q$6:$Q$505,0)),"") | I56: 51 | J56: =IFERROR(IF(INDEX(Rider_Input[Rider ID],I56)="","",INDEX(Rider_Input[Rider ID],I56)),"") | K56: =IF(J56="","",IFERROR(MATCH(J56,INDEX(RLVL_Data,0,c_RLVL_ID),0),"")) | L56: =IF(J56="","",IF(ISNUMBER(MATCH(J56,Rider_Master[Rider ID],0)),1,0)) | M56: =IF(J56="","",INDEX(Rider_Input[Completed Orders],I56)) | N56: =IF(OR(J56="",K56=""),"",IFERROR(INDEX(RLVL_Data,K56,c_RLVL_Orders),"")) | O56: =IF(J56="","",IF(COUNTIF($J$6:$J$505,J56)>1,1,0)) | P56: =IF(J56="","",IF(K56="","Not found in Paste_RLVL – deductions set to 0; ","")&IF(L56=0,"New rider (not in Rider_Master) – OK, shown as Rider <ID>; ","")&IF(AND(N56<>"",N56<>M56),"Orders differ: FTR "&M56&" vs RLVL "&N56&"; ","")&IF(O56=1,"Duplicate Rider ID; ","")) | Q56: =IF(P56="","",COUNTIF(P$6:P56,"?*"))
B57: =IFERROR(INDEX($J$6:$J$505,MATCH(18,$Q$6:$Q$505,0)),"") | C57: =IFERROR(INDEX($P$6:$P$505,MATCH(18,$Q$6:$Q$505,0)),"") | I57: 52 | J57: =IFERROR(IF(INDEX(Rider_Input[Rider ID],I57)="","",INDEX(Rider_Input[Rider ID],I57)),"") | K57: =IF(J57="","",IFERROR(MATCH(J57,INDEX(RLVL_Data,0,c_RLVL_ID),0),"")) | L57: =IF(J57="","",IF(ISNUMBER(MATCH(J57,Rider_Master[Rider ID],0)),1,0)) | M57: =IF(J57="","",INDEX(Rider_Input[Completed Orders],I57)) | N57: =IF(OR(J57="",K57=""),"",IFERROR(INDEX(RLVL_Data,K57,c_RLVL_Orders),"")) | O57: =IF(J57="","",IF(COUNTIF($J$6:$J$505,J57)>1,1,0)) | P57: =IF(J57="","",IF(K57="","Not found in Paste_RLVL – deductions set to 0; ","")&IF(L57=0,"New rider (not in Rider_Master) – OK, shown as Rider <ID>; ","")&IF(AND(N57<>"",N57<>M57),"Orders differ: FTR "&M57&" vs RLVL "&N57&"; ","")&IF(O57=1,"Duplicate Rider ID; ","")) | Q57: =IF(P57="","",COUNTIF(P$6:P57,"?*"))
B58: =IFERROR(INDEX($J$6:$J$505,MATCH(19,$Q$6:$Q$505,0)),"") | C58: =IFERROR(INDEX($P$6:$P$505,MATCH(19,$Q$6:$Q$505,0)),"") | I58: 53 | J58: =IFERROR(IF(INDEX(Rider_Input[Rider ID],I58)="","",INDEX(Rider_Input[Rider ID],I58)),"") | K58: =IF(J58="","",IFERROR(MATCH(J58,INDEX(RLVL_Data,0,c_RLVL_ID),0),"")) | L58: =IF(J58="","",IF(ISNUMBER(MATCH(J58,Rider_Master[Rider ID],0)),1,0)) | M58: =IF(J58="","",INDEX(Rider_Input[Completed Orders],I58)) | N58: =IF(OR(J58="",K58=""),"",IFERROR(INDEX(RLVL_Data,K58,c_RLVL_Orders),"")) | O58: =IF(J58="","",IF(COUNTIF($J$6:$J$505,J58)>1,1,0)) | P58: =IF(J58="","",IF(K58="","Not found in Paste_RLVL – deductions set to 0; ","")&IF(L58=0,"New rider (not in Rider_Master) – OK, shown as Rider <ID>; ","")&IF(AND(N58<>"",N58<>M58),"Orders differ: FTR "&M58&" vs RLVL "&N58&"; ","")&IF(O58=1,"Duplicate Rider ID; ","")) | Q58: =IF(P58="","",COUNTIF(P$6:P58,"?*"))
B59: =IFERROR(INDEX($J$6:$J$505,MATCH(20,$Q$6:$Q$505,0)),"") | C59: =IFERROR(INDEX($P$6:$P$505,MATCH(20,$Q$6:$Q$505,0)),"") | I59: 54 | J59: =IFERROR(IF(INDEX(Rider_Input[Rider ID],I59)="","",INDEX(Rider_Input[Rider ID],I59)),"") | K59: =IF(J59="","",IFERROR(MATCH(J59,INDEX(RLVL_Data,0,c_RLVL_ID),0),"")) | L59: =IF(J59="","",IF(ISNUMBER(MATCH(J59,Rider_Master[Rider ID],0)),1,0)) | M59: =IF(J59="","",INDEX(Rider_Input[Completed Orders],I59)) | N59: =IF(OR(J59="",K59=""),"",IFERROR(INDEX(RLVL_Data,K59,c_RLVL_Orders),"")) | O59: =IF(J59="","",IF(COUNTIF($J$6:$J$505,J59)>1,1,0)) | P59: =IF(J59="","",IF(K59="","Not found in Paste_RLVL – deductions set to 0; ","")&IF(L59=0,"New rider (not in Rider_Master) – OK, shown as Rider <ID>; ","")&IF(AND(N59<>"",N59<>M59),"Orders differ: FTR "&M59&" vs RLVL "&N59&"; ","")&IF(O59=1,"Duplicate Rider ID; ","")) | Q59: =IF(P59="","",COUNTIF(P$6:P59,"?*"))
B60: =IFERROR(INDEX($J$6:$J$505,MATCH(21,$Q$6:$Q$505,0)),"") | C60: =IFERROR(INDEX($P$6:$P$505,MATCH(21,$Q$6:$Q$505,0)),"") | I60: 55 | J60: =IFERROR(IF(INDEX(Rider_Input[Rider ID],I60)="","",INDEX(Rider_Input[Rider ID],I60)),"") | K60: =IF(J60="","",IFERROR(MATCH(J60,INDEX(RLVL_Data,0,c_RLVL_ID),0),"")) | L60: =IF(J60="","",IF(ISNUMBER(MATCH(J60,Rider_Master[Rider ID],0)),1,0)) | M60: =IF(J60="","",INDEX(Rider_Input[Completed Orders],I60)) | N60: =IF(OR(J60="",K60=""),"",IFERROR(INDEX(RLVL_Data,K60,c_RLVL_Orders),"")) | O60: =IF(J60="","",IF(COUNTIF($J$6:$J$505,J60)>1,1,0)) | P60: =IF(J60="","",IF(K60="","Not found in Paste_RLVL – deductions set to 0; ","")&IF(L60=0,"New rider (not in Rider_Master) – OK, shown as Rider <ID>; ","")&IF(AND(N60<>"",N60<>M60),"Orders differ: FTR "&M60&" vs RLVL "&N60&"; ","")&IF(O60=1,"Duplicate Rider ID; ","")) | Q60: =IF(P60="","",COUNTIF(P$6:P60,"?*"))
B61: =IFERROR(INDEX($J$6:$J$505,MATCH(22,$Q$6:$Q$505,0)),"") | C61: =IFERROR(INDEX($P$6:$P$505,MATCH(22,$Q$6:$Q$505,0)),"") | I61: 56 | J61: =IFERROR(IF(INDEX(Rider_Input[Rider ID],I61)="","",INDEX(Rider_Input[Rider ID],I61)),"") | K61: =IF(J61="","",IFERROR(MATCH(J61,INDEX(RLVL_Data,0,c_RLVL_ID),0),"")) | L61: =IF(J61="","",IF(ISNUMBER(MATCH(J61,Rider_Master[Rider ID],0)),1,0)) | M61: =IF(J61="","",INDEX(Rider_Input[Completed Orders],I61)) | N61: =IF(OR(J61="",K61=""),"",IFERROR(INDEX(RLVL_Data,K61,c_RLVL_Orders),"")) | O61: =IF(J61="","",IF(COUNTIF($J$6:$J$505,J61)>1,1,0)) | P61: =IF(J61="","",IF(K61="","Not found in Paste_RLVL – deductions set to 0; ","")&IF(L61=0,"New rider (not in Rider_Master) – OK, shown as Rider <ID>; ","")&IF(AND(N61<>"",N61<>M61),"Orders differ: FTR "&M61&" vs RLVL "&N61&"; ","")&IF(O61=1,"Duplicate Rider ID; ","")) | Q61: =IF(P61="","",COUNTIF(P$6:P61,"?*"))
B62: =IFERROR(INDEX($J$6:$J$505,MATCH(23,$Q$6:$Q$505,0)),"") | C62: =IFERROR(INDEX($P$6:$P$505,MATCH(23,$Q$6:$Q$505,0)),"") | I62: 57 | J62: =IFERROR(IF(INDEX(Rider_Input[Rider ID],I62)="","",INDEX(Rider_Input[Rider ID],I62)),"") | K62: =IF(J62="","",IFERROR(MATCH(J62,INDEX(RLVL_Data,0,c_RLVL_ID),0),"")) | L62: =IF(J62="","",IF(ISNUMBER(MATCH(J62,Rider_Master[Rider ID],0)),1,0)) | M62: =IF(J62="","",INDEX(Rider_Input[Completed Orders],I62)) | N62: =IF(OR(J62="",K62=""),"",IFERROR(INDEX(RLVL_Data,K62,c_RLVL_Orders),"")) | O62: =IF(J62="","",IF(COUNTIF($J$6:$J$505,J62)>1,1,0)) | P62: =IF(J62="","",IF(K62="","Not found in Paste_RLVL – deductions set to 0; ","")&IF(L62=0,"New rider (not in Rider_Master) – OK, shown as Rider <ID>; ","")&IF(AND(N62<>"",N62<>M62),"Orders differ: FTR "&M62&" vs RLVL "&N62&"; ","")&IF(O62=1,"Duplicate Rider ID; ","")) | Q62: =IF(P62="","",COUNTIF(P$6:P62,"?*"))
B63: =IFERROR(INDEX($J$6:$J$505,MATCH(24,$Q$6:$Q$505,0)),"") | C63: =IFERROR(INDEX($P$6:$P$505,MATCH(24,$Q$6:$Q$505,0)),"") | I63: 58 | J63: =IFERROR(IF(INDEX(Rider_Input[Rider ID],I63)="","",INDEX(Rider_Input[Rider ID],I63)),"") | K63: =IF(J63="","",IFERROR(MATCH(J63,INDEX(RLVL_Data,0,c_RLVL_ID),0),"")) | L63: =IF(J63="","",IF(ISNUMBER(MATCH(J63,Rider_Master[Rider ID],0)),1,0)) | M63: =IF(J63="","",INDEX(Rider_Input[Completed Orders],I63)) | N63: =IF(OR(J63="",K63=""),"",IFERROR(INDEX(RLVL_Data,K63,c_RLVL_Orders),"")) | O63: =IF(J63="","",IF(COUNTIF($J$6:$J$505,J63)>1,1,0)) | P63: =IF(J63="","",IF(K63="","Not found in Paste_RLVL – deductions set to 0; ","")&IF(L63=0,"New rider (not in Rider_Master) – OK, shown as Rider <ID>; ","")&IF(AND(N63<>"",N63<>M63),"Orders differ: FTR "&M63&" vs RLVL "&N63&"; ","")&IF(O63=1,"Duplicate Rider ID; ","")) | Q63: =IF(P63="","",COUNTIF(P$6:P63,"?*"))
B64: =IFERROR(INDEX($J$6:$J$505,MATCH(25,$Q$6:$Q$505,0)),"") | C64: =IFERROR(INDEX($P$6:$P$505,MATCH(25,$Q$6:$Q$505,0)),"") | I64: 59 | J64: =IFERROR(IF(INDEX(Rider_Input[Rider ID],I64)="","",INDEX(Rider_Input[Rider ID],I64)),"") | K64: =IF(J64="","",IFERROR(MATCH(J64,INDEX(RLVL_Data,0,c_RLVL_ID),0),"")) | L64: =IF(J64="","",IF(ISNUMBER(MATCH(J64,Rider_Master[Rider ID],0)),1,0)) | M64: =IF(J64="","",INDEX(Rider_Input[Completed Orders],I64)) | N64: =IF(OR(J64="",K64=""),"",IFERROR(INDEX(RLVL_Data,K64,c_RLVL_Orders),"")) | O64: =IF(J64="","",IF(COUNTIF($J$6:$J$505,J64)>1,1,0)) | P64: =IF(J64="","",IF(K64="","Not found in Paste_RLVL – deductions set to 0; ","")&IF(L64=0,"New rider (not in Rider_Master) – OK, shown as Rider <ID>; ","")&IF(AND(N64<>"",N64<>M64),"Orders differ: FTR "&M64&" vs RLVL "&N64&"; ","")&IF(O64=1,"Duplicate Rider ID; ","")) | Q64: =IF(P64="","",COUNTIF(P$6:P64,"?*"))
I65: 60 | J65: =IFERROR(IF(INDEX(Rider_Input[Rider ID],I65)="","",INDEX(Rider_Input[Rider ID],I65)),"") | K65: =IF(J65="","",IFERROR(MATCH(J65,INDEX(RLVL_Data,0,c_RLVL_ID),0),"")) | L65: =IF(J65="","",IF(ISNUMBER(MATCH(J65,Rider_Master[Rider ID],0)),1,0)) | M65: =IF(J65="","",INDEX(Rider_Input[Completed Orders],I65)) | N65: =IF(OR(J65="",K65=""),"",IFERROR(INDEX(RLVL_Data,K65,c_RLVL_Orders),"")) | O65: =IF(J65="","",IF(COUNTIF($J$6:$J$505,J65)>1,1,0)) | P65: =IF(J65="","",IF(K65="","Not found in Paste_RLVL – deductions set to 0; ","")&IF(L65=0,"New rider (not in Rider_Master) – OK, shown as Rider <ID>; ","")&IF(AND(N65<>"",N65<>M65),"Orders differ: FTR "&M65&" vs RLVL "&N65&"; ","")&IF(O65=1,"Duplicate Rider ID; ","")) | Q65: =IF(P65="","",COUNTIF(P$6:P65,"?*"))
I66: 61 | J66: =IFERROR(IF(INDEX(Rider_Input[Rider ID],I66)="","",INDEX(Rider_Input[Rider ID],I66)),"") | K66: =IF(J66="","",IFERROR(MATCH(J66,INDEX(RLVL_Data,0,c_RLVL_ID),0),"")) | L66: =IF(J66="","",IF(ISNUMBER(MATCH(J66,Rider_Master[Rider ID],0)),1,0)) | M66: =IF(J66="","",INDEX(Rider_Input[Completed Orders],I66)) | N66: =IF(OR(J66="",K66=""),"",IFERROR(INDEX(RLVL_Data,K66,c_RLVL_Orders),"")) | O66: =IF(J66="","",IF(COUNTIF($J$6:$J$505,J66)>1,1,0)) | P66: =IF(J66="","",IF(K66="","Not found in Paste_RLVL – deductions set to 0; ","")&IF(L66=0,"New rider (not in Rider_Master) – OK, shown as Rider <ID>; ","")&IF(AND(N66<>"",N66<>M66),"Orders differ: FTR "&M66&" vs RLVL "&N66&"; ","")&IF(O66=1,"Duplicate Rider ID; ","")) | Q66: =IF(P66="","",COUNTIF(P$6:P66,"?*"))
I67: 62 | J67: =IFERROR(IF(INDEX(Rider_Input[Rider ID],I67)="","",INDEX(Rider_Input[Rider ID],I67)),"") | K67: =IF(J67="","",IFERROR(MATCH(J67,INDEX(RLVL_Data,0,c_RLVL_ID),0),"")) | L67: =IF(J67="","",IF(ISNUMBER(MATCH(J67,Rider_Master[Rider ID],0)),1,0)) | M67: =IF(J67="","",INDEX(Rider_Input[Completed Orders],I67)) | N67: =IF(OR(J67="",K67=""),"",IFERROR(INDEX(RLVL_Data,K67,c_RLVL_Orders),"")) | O67: =IF(J67="","",IF(COUNTIF($J$6:$J$505,J67)>1,1,0)) | P67: =IF(J67="","",IF(K67="","Not found in Paste_RLVL – deductions set to 0; ","")&IF(L67=0,"New rider (not in Rider_Master) – OK, shown as Rider <ID>; ","")&IF(AND(N67<>"",N67<>M67),"Orders differ: FTR "&M67&" vs RLVL "&N67&"; ","")&IF(O67=1,"Duplicate Rider ID; ","")) | Q67: =IF(P67="","",COUNTIF(P$6:P67,"?*"))
I68: 63 | J68: =IFERROR(IF(INDEX(Rider_Input[Rider ID],I68)="","",INDEX(Rider_Input[Rider ID],I68)),"") | K68: =IF(J68="","",IFERROR(MATCH(J68,INDEX(RLVL_Data,0,c_RLVL_ID),0),"")) | L68: =IF(J68="","",IF(ISNUMBER(MATCH(J68,Rider_Master[Rider ID],0)),1,0)) | M68: =IF(J68="","",INDEX(Rider_Input[Completed Orders],I68)) | N68: =IF(OR(J68="",K68=""),"",IFERROR(INDEX(RLVL_Data,K68,c_RLVL_Orders),"")) | O68: =IF(J68="","",IF(COUNTIF($J$6:$J$505,J68)>1,1,0)) | P68: =IF(J68="","",IF(K68="","Not found in Paste_RLVL – deductions set to 0; ","")&IF(L68=0,"New rider (not in Rider_Master) – OK, shown as Rider <ID>; ","")&IF(AND(N68<>"",N68<>M68),"Orders differ: FTR "&M68&" vs RLVL "&N68&"; ","")&IF(O68=1,"Duplicate Rider ID; ","")) | Q68: =IF(P68="","",COUNTIF(P$6:P68,"?*"))
I69: 64 | J69: =IFERROR(IF(INDEX(Rider_Input[Rider ID],I69)="","",INDEX(Rider_Input[Rider ID],I69)),"") | K69: =IF(J69="","",IFERROR(MATCH(J69,INDEX(RLVL_Data,0,c_RLVL_ID),0),"")) | L69: =IF(J69="","",IF(ISNUMBER(MATCH(J69,Rider_Master[Rider ID],0)),1,0)) | M69: =IF(J69="","",INDEX(Rider_Input[Completed Orders],I69)) | N69: =IF(OR(J69="",K69=""),"",IFERROR(INDEX(RLVL_Data,K69,c_RLVL_Orders),"")) | O69: =IF(J69="","",IF(COUNTIF($J$6:$J$505,J69)>1,1,0)) | P69: =IF(J69="","",IF(K69="","Not found in Paste_RLVL – deductions set to 0; ","")&IF(L69=0,"New rider (not in Rider_Master) – OK, shown as Rider <ID>; ","")&IF(AND(N69<>"",N69<>M69),"Orders differ: FTR "&M69&" vs RLVL "&N69&"; ","")&IF(O69=1,"Duplicate Rider ID; ","")) | Q69: =IF(P69="","",COUNTIF(P$6:P69,"?*"))
I70: 65 | J70: =IFERROR(IF(INDEX(Rider_Input[Rider ID],I70)="","",INDEX(Rider_Input[Rider ID],I70)),"") | K70: =IF(J70="","",IFERROR(MATCH(J70,INDEX(RLVL_Data,0,c_RLVL_ID),0),"")) | L70: =IF(J70="","",IF(ISNUMBER(MATCH(J70,Rider_Master[Rider ID],0)),1,0)) | M70: =IF(J70="","",INDEX(Rider_Input[Completed Orders],I70)) | N70: =IF(OR(J70="",K70=""),"",IFERROR(INDEX(RLVL_Data,K70,c_RLVL_Orders),"")) | O70: =IF(J70="","",IF(COUNTIF($J$6:$J$505,J70)>1,1,0)) | P70: =IF(J70="","",IF(K70="","Not found in Paste_RLVL – deductions set to 0; ","")&IF(L70=0,"New rider (not in Rider_Master) – OK, shown as Rider <ID>; ","")&IF(AND(N70<>"",N70<>M70),"Orders differ: FTR "&M70&" vs RLVL "&N70&"; ","")&IF(O70=1,"Duplicate Rider ID; ","")) | Q70: =IF(P70="","",COUNTIF(P$6:P70,"?*"))
I71: 66 | J71: =IFERROR(IF(INDEX(Rider_Input[Rider ID],I71)="","",INDEX(Rider_Input[Rider ID],I71)),"") | K71: =IF(J71="","",IFERROR(MATCH(J71,INDEX(RLVL_Data,0,c_RLVL_ID),0),"")) | L71: =IF(J71="","",IF(ISNUMBER(MATCH(J71,Rider_Master[Rider ID],0)),1,0)) | M71: =IF(J71="","",INDEX(Rider_Input[Completed Orders],I71)) | N71: =IF(OR(J71="",K71=""),"",IFERROR(INDEX(RLVL_Data,K71,c_RLVL_Orders),"")) | O71: =IF(J71="","",IF(COUNTIF($J$6:$J$505,J71)>1,1,0)) | P71: =IF(J71="","",IF(K71="","Not found in Paste_RLVL – deductions set to 0; ","")&IF(L71=0,"New rider (not in Rider_Master) – OK, shown as Rider <ID>; ","")&IF(AND(N71<>"",N71<>M71),"Orders differ: FTR "&M71&" vs RLVL "&N71&"; ","")&IF(O71=1,"Duplicate Rider ID; ","")) | Q71: =IF(P71="","",COUNTIF(P$6:P71,"?*"))
I72: 67 | J72: =IFERROR(IF(INDEX(Rider_Input[Rider ID],I72)="","",INDEX(Rider_Input[Rider ID],I72)),"") | K72: =IF(J72="","",IFERROR(MATCH(J72,INDEX(RLVL_Data,0,c_RLVL_ID),0),"")) | L72: =IF(J72="","",IF(ISNUMBER(MATCH(J72,Rider_Master[Rider ID],0)),1,0)) | M72: =IF(J72="","",INDEX(Rider_Input[Completed Orders],I72)) | N72: =IF(OR(J72="",K72=""),"",IFERROR(INDEX(RLVL_Data,K72,c_RLVL_Orders),"")) | O72: =IF(J72="","",IF(COUNTIF($J$6:$J$505,J72)>1,1,0)) | P72: =IF(J72="","",IF(K72="","Not found in Paste_RLVL – deductions set to 0; ","")&IF(L72=0,"New rider (not in Rider_Master) – OK, shown as Rider <ID>; ","")&IF(AND(N72<>"",N72<>M72),"Orders differ: FTR "&M72&" vs RLVL "&N72&"; ","")&IF(O72=1,"Duplicate Rider ID; ","")) | Q72: =IF(P72="","",COUNTIF(P$6:P72,"?*"))
I73: 68 | J73: =IFERROR(IF(INDEX(Rider_Input[Rider ID],I73)="","",INDEX(Rider_Input[Rider ID],I73)),"") | K73: =IF(J73="","",IFERROR(MATCH(J73,INDEX(RLVL_Data,0,c_RLVL_ID),0),"")) | L73: =IF(J73="","",IF(ISNUMBER(MATCH(J73,Rider_Master[Rider ID],0)),1,0)) | M73: =IF(J73="","",INDEX(Rider_Input[Completed Orders],I73)) | N73: =IF(OR(J73="",K73=""),"",IFERROR(INDEX(RLVL_Data,K73,c_RLVL_Orders),"")) | O73: =IF(J73="","",IF(COUNTIF($J$6:$J$505,J73)>1,1,0)) | P73: =IF(J73="","",IF(K73="","Not found in Paste_RLVL – deductions set to 0; ","")&IF(L73=0,"New rider (not in Rider_Master) – OK, shown as Rider <ID>; ","")&IF(AND(N73<>"",N73<>M73),"Orders differ: FTR "&M73&" vs RLVL "&N73&"; ","")&IF(O73=1,"Duplicate Rider ID; ","")) | Q73: =IF(P73="","",COUNTIF(P$6:P73,"?*"))
I74: 69 | J74: =IFERROR(IF(INDEX(Rider_Input[Rider ID],I74)="","",INDEX(Rider_Input[Rider ID],I74)),"") | K74: =IF(J74="","",IFERROR(MATCH(J74,INDEX(RLVL_Data,0,c_RLVL_ID),0),"")) | L74: =IF(J74="","",IF(ISNUMBER(MATCH(J74,Rider_Master[Rider ID],0)),1,0)) | M74: =IF(J74="","",INDEX(Rider_Input[Completed Orders],I74)) | N74: =IF(OR(J74="",K74=""),"",IFERROR(INDEX(RLVL_Data,K74,c_RLVL_Orders),"")) | O74: =IF(J74="","",IF(COUNTIF($J$6:$J$505,J74)>1,1,0)) | P74: =IF(J74="","",IF(K74="","Not found in Paste_RLVL – deductions set to 0; ","")&IF(L74=0,"New rider (not in Rider_Master) – OK, shown as Rider <ID>; ","")&IF(AND(N74<>"",N74<>M74),"Orders differ: FTR "&M74&" vs RLVL "&N74&"; ","")&IF(O74=1,"Duplicate Rider ID; ","")) | Q74: =IF(P74="","",COUNTIF(P$6:P74,"?*"))
I75: 70 | J75: =IFERROR(IF(INDEX(Rider_Input[Rider ID],I75)="","",INDEX(Rider_Input[Rider ID],I75)),"") | K75: =IF(J75="","",IFERROR(MATCH(J75,INDEX(RLVL_Data,0,c_RLVL_ID),0),"")) | L75: =IF(J75="","",IF(ISNUMBER(MATCH(J75,Rider_Master[Rider ID],0)),1,0)) | M75: =IF(J75="","",INDEX(Rider_Input[Completed Orders],I75)) | N75: =IF(OR(J75="",K75=""),"",IFERROR(INDEX(RLVL_Data,K75,c_RLVL_Orders),"")) | O75: =IF(J75="","",IF(COUNTIF($J$6:$J$505,J75)>1,1,0)) | P75: =IF(J75="","",IF(K75="","Not found in Paste_RLVL – deductions set to 0; ","")&IF(L75=0,"New rider (not in Rider_Master) – OK, shown as Rider <ID>; ","")&IF(AND(N75<>"",N75<>M75),"Orders differ: FTR "&M75&" vs RLVL "&N75&"; ","")&IF(O75=1,"Duplicate Rider ID; ","")) | Q75: =IF(P75="","",COUNTIF(P$6:P75,"?*"))
I76: 71 | J76: =IFERROR(IF(INDEX(Rider_Input[Rider ID],I76)="","",INDEX(Rider_Input[Rider ID],I76)),"") | K76: =IF(J76="","",IFERROR(MATCH(J76,INDEX(RLVL_Data,0,c_RLVL_ID),0),"")) | L76: =IF(J76="","",IF(ISNUMBER(MATCH(J76,Rider_Master[Rider ID],0)),1,0)) | M76: =IF(J76="","",INDEX(Rider_Input[Completed Orders],I76)) | N76: =IF(OR(J76="",K76=""),"",IFERROR(INDEX(RLVL_Data,K76,c_RLVL_Orders),"")) | O76: =IF(J76="","",IF(COUNTIF($J$6:$J$505,J76)>1,1,0)) | P76: =IF(J76="","",IF(K76="","Not found in Paste_RLVL – deductions set to 0; ","")&IF(L76=0,"New rider (not in Rider_Master) – OK, shown as Rider <ID>; ","")&IF(AND(N76<>"",N76<>M76),"Orders differ: FTR "&M76&" vs RLVL "&N76&"; ","")&IF(O76=1,"Duplicate Rider ID; ","")) | Q76: =IF(P76="","",COUNTIF(P$6:P76,"?*"))
... I505: 500 | J505: =IFERROR(IF(INDEX(Rider_Input[Rider ID],I505)="","",INDEX(Rider_Input[Rider ID],I505)),"") | K505: =IF(J505="","",IFERROR(MATCH(J505,INDEX(RLVL_Data,0,c_RLVL_ID),0),"")) | L505: =IF(J505="","",IF(ISNUMBER(MATCH(J505,Rider_Master[Rider ID],0)),1,0)) | M505: =IF(J505="","",INDEX(Rider_Input[Completed Orders],I505)) | N505: =IF(OR(J505="",K505=""),"",IFERROR(INDEX(RLVL_Data,K505,c_RLVL_Orders),"")) | O505: =IF(J505="","",IF(COUNTIF($J$6:$J$505,J505)>1,1,0)) | P505: =IF(J505="","",IF(K505="","Not found in Paste_RLVL – deductions set to 0; ","")&IF(L505=0,"New rider (not in Rider_Master) – OK, shown as Rider <ID>; ","")&IF(AND(N505<>"",N505<>M505),"Orders differ: FTR "&M505&" vs RLVL "&N505&"; ","")&IF(O505=1,"Duplicate Rider ID; ","")) | Q505: =IF(P505="","",COUNTIF(P$6:P505,"?*"))

Sheet Settings
B1: Settings / الإعدادات
A3: Setting / الإعداد | B3: Value / القيمة | C3: Description / الوصف
A4: Order Rate Method | B4: Exact rate | C4: Exact rate = Basic Payment / 450; Fixed rate = 4.44
A5: Default Basic Payment | B5: 2000 | C5: Default SAR basic payment for 450 standard monthly orders (type this into Rider_Input for new riders; used by Example 1 on the dashboard)
A6: Standard Monthly Orders | B6: 450 | C6: Standard monthly target orders for a 30-day month
A7: Standard Month Days | B7: 30 | C7: Denominator for calendar-day adjustment
A8: Fixed Order Rate | B8: 4.44 | C8: Used only when Order Rate Method = Fixed rate
A9: Missing-Order Deduction Rate | B9: 7 | C9: SAR per missing order
A10: Extra-Order Bonus Rate | B10: 10 | C10: SAR per extra order
A11: Company Name | B11: Elite Development | C11: Company name printed on payslips and footers
A12: Company Logo Placeholder | B12: Logo embedded (picture) | C12: The Elite Development logo is embedded as a picture on Payslip_Print, Summary_Dashboard, Instructions, Settings and Monthly_Import. To replace it: right-click the picture → Change Picture.
A13: Salary Month (any date in the month) | B13: 46235 | C13: CHANGE THIS EACH MONTH. Drives Salary Month and Calendar Days for every rider (days in month are calculated automatically).
A14: Status Labels | B14: Meaning
A15: Paid in Full | B15: Payable salary with no deductions reducing the gross salary
A16: Paid After Deductions | B16: Positive final salary after deductions
A17: No Salary – Amount Due from Rider | B17: No payable salary remains and an amount is due from the rider
A18: Review Required | B18: Input is incomplete or violates a validation rule
A19: No Orders | B19: Rider completed zero orders in the month

Sheet Paste_FTR
A1: Contract Name | B1: rider_id | C1: is_active | D1: city_name | E1: rider_vehicle_type | F1: contract_start_date_local | G1: contract_end_date_local | H1: completed_orders | I1: total_monthly_working_hours | J1: working_hours | K1: fully_working_days | L1: working_days | M1: city_monthly_flat_salary | N1: city_payment | O1: basic_rate | P1: declined_penalties_day_logic | Q1: inactive_reason | R1: excused_absence_days | S1: missed_weekends | T1: missed_eom | U1: total_missed_days | V1: missed_days_after_allowance | W1: missed_days_penalty | X1: missed_days_penalty_logic | Y1: segment | Z1: segment_rate | AA1: segment_payment | AB1: manhattan_distance_payable | AC1: distance_payment | BB1: ◀ PASTE AREA: keep the header in row 1, paste the new monthly export from A1. Clear old rows first (select row 2 downward → Delete). Up to 1,000 rows / columns A:BZ are read.
A2: nokhaba_tatweer_ftr | B2: 4849914 | C2: =TRUE() -> TRUE | D2: Qp | E2: car | F2: 46255 | G2: 49907 | H2: 72 | I2: 118.18 | J2: 86.18 | K2: 7 | L2: 8 | N2: 0 | O2: 6 | Q2: Active | R2: 0 | S2: 1 | T2: 1 | U2: 2 | V2: 1 | W2: 0 | X2: Adjusted in basic payment | Y2: E | Z2: 0.75 | AA2: 54 | AB2: 389.044 | AC2: 350.1396
A3: nokhaba_tatweer_ftr | B3: 4849909 | C3: =TRUE() -> TRUE | D3: Qp | E3: car | F3: 46255 | G3: 49907 | H3: 101 | I3: 139.71 | J3: 115.71 | K3: 9 | L3: 11 | N3: 0 | O3: 8 | Q3: Active | R3: 0 | S3: 0 | T3: 1 | U3: 1 | V3: 0 | W3: 0 | X3: No missed days | Y3: E | Z3: 0.75 | AA3: 75.75 | AB3: 572.282 | AC3: 658.1243
A4: nokhaba_tatweer_ftr | B4: 4849222 | C4: =TRUE() -> TRUE | D4: Qp | E4: car | F4: 46254 | G4: 49906 | H4: 105 | I4: 150.94 | J4: 126.94 | K4: 9 | L4: 11 | N4: 0 | O4: 8 | Q4: Active | R4: 0 | S4: 0 | T4: 1 | U4: 1 | V4: 0 | W4: 0 | X4: No missed days | Y4: D | Z4: 1.25 | AA4: 131.25 | AB4: 598.671 | AC4: 688.47165
A5: nokhaba_tatweer_ftr | B5: 4844480 | C5: =TRUE() -> TRUE | D5: Qp | E5: car | F5: 46253 | G5: 49905 | H5: 150 | I5: 167.95 | J5: 143.95 | K5: 11 | L5: 12 | N5: 0 | O5: 8 | Q5: Active | R5: 0 | S5: 0 | T5: 1 | U5: 1 | V5: 0 | W5: 0 | X5: No missed days | Y5: E | Z5: 0.75 | AA5: 112.5 | AB5: 766.915 | AC5: 881.95225
A6: nokhaba_tatweer_ftr | B6: 4838478 | C6: =TRUE() -> TRUE | D6: Qp | E6: car | F6: 46251 | G6: 49903 | H6: 171 | I6: 205.98 | J6: 181.98 | K6: 12 | L6: 14 | N6: 0 | O6: 8 | Q6: Active | R6: 0 | S6: 0 | T6: 1 | U6: 1 | V6: 0 | W6: 0 | X6: No missed days | Y6: E | Z6: 0.75 | AA6: 128.25 | AB6: 931.88 | AC6: 1071.662
A7: nokhaba_tatweer_ftr | B7: 4838471 | C7: =TRUE() -> TRUE | D7: Qp | E7: car | F7: 46251 | G7: 49903 | H7: 146 | I7: 187.15 | J7: 163.15 | K7: 11 | L7: 12 | N7: 0 | O7: 8 | Q7: Active | R7: 0 | S7: 1 | T7: 0 | U7: 1 | V7: 1 | W7: -500 | X7: 500 per day penalty | Y7: E | Z7: 0.75 | AA7: 109.5 | AB7: 845.35 | AC7: 972.1525
A8: nokhaba_tatweer_ftr | B8: 4747290 | C8: =TRUE() -> TRUE | D8: Qp | E8: car | F8: 46212 | G8: 49864 | H8: 498 | I8: 455.44 | J8: 455.44 | K8: 31 | L8: 31 | N8: 0 | O8: 8 | Q8: Active | R8: 0 | S8: 0 | T8: 0 | U8: 0 | V8: 0 | W8: 0 | X8: No missed days | Y8: D | Z8: 1.25 | AA8: 622.5 | AB8: 2847.412 | AC8: 3274.5238
A9: nokhaba_tatweer_ftr | B9: 4652654 | C9: =TRUE() -> TRUE | D9: Qp | E9: car | F9: 46165 | G9: 49817 | H9: 433 | I9: 420.49 | J9: 420.49 | K9: 31 | L9: 31 | N9: 0 | O9: 8 | Q9: Active | R9: 0 | S9: 0 | T9: 0 | U9: 0 | V9: 0 | W9: 0 | X9: No missed days | Y9: C | Z9: 1.75 | AA9: 757.75 | AB9: 2649.379 | AC9: 3046.7858
A10: nokhaba_tatweer_ftr | B10: 4652587 | C10: =TRUE() -> TRUE | D10: Qp | E10: car | F10: 46164 | G10: 49816 | H10: 382 | I10: 485.15 | J10: 485.15 | K10: 28 | L10: 30 | N10: 0 | O10: 8 | Q10: Active | R10: 0 | S10: 0 | T10: 2 | U10: 2 | V10: 1 | W10: -500 | X10: 500 per day penalty | Y10: E | Z10: 0.75 | AA10: 286.5 | AB10: 2401.539 | AC10: 2761.7698
A11: nokhaba_tatweer_ftr | B11: 4648709 | C11: =TRUE() -> TRUE | D11: Qp | E11: car | F11: 46163 | G11: 49815 | H11: 391 | I11: 412.55 | J11: 412.55 | K11: 30 | L11: 31 | N11: 0 | O11: 8 | Q11: Active | R11: 0 | S11: 0 | T11: 0 | U11: 0 | V11: 0 | W11: 0 | X11: No missed days | Y11: D | Z11: 1.25 | AA11: 488.75 | AB11: 1973.288 | AC11: 2269.2812
A12: nokhaba_tatweer_ftr | B12: 4648308 | C12: =TRUE() -> TRUE | D12: Qp | E12: car | F12: 46189 | G12: 49839 | H12: 551 | I12: 449.49 | J12: 449.49 | K12: 31 | L12: 31 | N12: 0 | O12: 8 | Q12: Active | R12: 0 | S12: 0 | T12: 0 | U12: 0 | V12: 0 | W12: 0 | X12: No missed days | Y12: C | Z12: 1.75 | AA12: 964.25 | AB12: 3104.681 | AC12: 3570.3831
A13: nokhaba_tatweer_ftr | B13: 4644774 | C13: =TRUE() -> TRUE | D13: Qp | E13: car | F13: 46161 | G13: 49813 | H13: 367 | I13: 423.45 | J13: 423.45 | K13: 30 | L13: 31 | N13: 0 | O13: 8 | Q13: Active | R13: 0 | S13: 0 | T13: 0 | U13: 0 | V13: 0 | W13: 0 | X13: No missed days | Y13: D | Z13: 1.25 | AA13: 458.75 | AB13: 2119.546 | AC13: 2437.4779
... A16: nokhaba_tatweer_ftr | B16: 4611383 | C16: =TRUE() -> TRUE | D16: Qp | E16: car | F16: 46145 | G16: 49797 | H16: 476 | I16: 417.5 | J16: 417.5 | K16: 31 | L16: 31 | N16: 0 | O16: 8 | Q16: Active | R16: 0 | S16: 0 | T16: 0 | U16: 0 | V16: 0 | W16: 0 | X16: No missed days | Y16: E | Z16: 0.75 | AA16: 357 | AB16: 2410.346 | AC16: 2771.8979

Sheet Paste_RLVL
A1: معرف المندوب - rider_id | B1: Contract Name | C1: الطلبات المكتملة - completed_orders | D1: الدفعة الأساسية - basic_payment | E1: خصم الطلبات المتعددة - stacking_deduction | F1: غرامة الرفض اليومية - declined_penalties_day_logic | G1: غرامة التأخير - late_penalty | H1: غرامة عدم الحضور - no_show_penalty | I1: غرامة عدم الحضور للمدن الخاصة - no_show_penalty_special_cities | J1: غرامة معدل القبول اليومية - daily_acceptance_rate_penalty | K1: بدل المسافة - distance_payment | L1: غرامة الأيام الفائتة - missed_days_penalty | M1: بدل الفئات - segment_payment | N1: الدفع الأساسي للمندوب - rider_basic | O1: تقييم المندوب - rider_scoring | P1: محفظة المندوب - Rider Balance | BB1: ◀ PASTE AREA: keep the header in row 1, paste the new monthly export from A1. Clear old rows first (select row 2 downward → Delete). Up to 1,000 rows / columns A:BZ are read.
A2: 4611383 | B2: nokhaba_tatweer_ftr | C2: 476 | D2: 3808 | E2: -88 | G2: 0 | H2: 0 | I2: 0 | K2: 2771.8979 | L2: 0 | M2: 357 | N2: 0 | O2: 0 | P2: 240.4
A3: 4642935 | B3: nokhaba_tatweer_ftr | C3: 442 | D3: 3536 | E3: -84 | G3: 0 | H3: 0 | I3: 0 | K3: 2961.1016 | L3: 0 | M3: 773.5 | N3: 0 | O3: 0 | P3: 116.95
A4: 4643856 | B4: nokhaba_tatweer_ftr | C4: 449 | D4: 3592 | E4: -80 | G4: 0 | H4: 0 | I4: 0 | K4: 3007.4846 | L4: 0 | M4: 561.25 | N4: 0 | O4: 0 | P4: 128.27
A5: 4644774 | B5: nokhaba_tatweer_ftr | C5: 367 | D5: 2936 | E5: -52 | G5: 0 | H5: 0 | I5: 0 | K5: 2437.4779 | L5: 0 | M5: 458.75 | N5: 0 | O5: 0 | P5: 275.31
A6: 4648308 | B6: nokhaba_tatweer_ftr | C6: 551 | D6: 4408 | E6: -112 | G6: 0 | H6: 0 | I6: 0 | K6: 3570.3831 | L6: 0 | M6: 964.25 | N6: 0 | O6: 0 | P6: 93.12
A7: 4648709 | B7: nokhaba_tatweer_ftr | C7: 391 | D7: 3128 | E7: -76 | G7: 0 | H7: 0 | I7: 0 | K7: 2269.2812 | L7: 0 | M7: 488.75 | N7: 0 | O7: 0 | P7: 266.18
A8: 4652587 | B8: nokhaba_tatweer_ftr | C8: 382 | D8: 3056 | E8: -44 | G8: 0 | H8: 0 | I8: 0 | K8: 2761.7698 | L8: -500 | M8: 286.5 | N8: 0 | O8: 0 | P8: 121.92
A9: 4652654 | B9: nokhaba_tatweer_ftr | C9: 433 | D9: 3464 | E9: -44 | G9: 0 | H9: 0 | I9: 0 | K9: 3046.7858 | L9: 0 | M9: 757.75 | N9: 0 | O9: 0 | P9: 201.65
A10: 4747290 | B10: nokhaba_tatweer_ftr | C10: 498 | D10: 3984 | E10: -52 | G10: 0 | H10: 0 | I10: 0 | K10: 3274.5238 | L10: 0 | M10: 622.5 | N10: 0 | O10: 0 | P10: 104.03
A11: 4838471 | B11: nokhaba_tatweer_ftr | C11: 146 | D11: 1168 | E11: -32 | G11: 0 | H11: 0 | I11: 0 | K11: 972.1525 | L11: -500 | M11: 109.5 | N11: 0 | O11: 0 | P11: 192.89
A12: 4838478 | B12: nokhaba_tatweer_ftr | C12: 171 | D12: 1368 | E12: -36 | G12: 0 | H12: -85.5 | I12: 0 | K12: 1071.662 | L12: 0 | M12: 128.25 | N12: 0 | O12: 0 | P12: 200.44
A13: 4844480 | B13: nokhaba_tatweer_ftr | C13: 150 | D13: 1200 | E13: -36 | G13: 0 | H13: -75 | I13: 0 | K13: 881.95225 | L13: 0 | M13: 112.5 | N13: 0 | O13: 0 | P13: 57.17
... A16: 4849914 | B16: nokhaba_tatweer_ftr | C16: 72 | D16: 432 | E16: -32 | G16: 0 | H16: -36 | I16: 0 | K16: 350.1396 | L16: 0 | M16: 54 | N16: 0 | O16: 0 | P16: 268.09

Sheet Rider_Master
A1: Rider ID | B1: Rider Name | C1: Basic Payment (blank = default) | D1: Notes | F1: OPTIONAL. The salary engine works without this sheet: unknown riders show as 'Rider <ID>' with the default basic payment. To add new riders: type under the last row (the table grows by itself) or copy the IDs listed in Monthly_Import → 'Items to review'. Fill Rider Name for payslips, and Basic Payment only for riders on a different contract.
A2: 4611383
A3: 4642935
A4: 4643856
A5: 4644774
A6: 4648308
A7: 4648709
A8: 4652587
A9: 4652654
A10: 4747290
A11: 4838471
A12: 4838478
A13: 4844480
... A16: 4849914

Sheet Adjustments
A1: Rider ID | B1: Other Deductions | C1: Note / Reason | E1: OPTIONAL monthly extras, one line per deduction. Type under the last row – the table grows by itself. Several lines for the same Rider ID are added together into 'Other Deductions' (car deduction, TGA fines, advances…) and the note appears on the payslip. Clear the rows at the start of each month (leave the header and one row).

Sheet Rider_Input
A1: Salary Month | B1: Rider ID | C1: Rider Name | D1: Basic Payment | E1: Calendar Days in Month | F1: Working Days | G1: Completed Orders | H1: missed_days_penalty | I1: Rider Balance / محفظة المندوب | J1: stacking_deduction / خصم الطلبات المتعددة | K1: Other Deductions | L1: Notes
A2: =IF(Rider_Input[[#This Row],[Rider ID]]="","",Salary_Month) -> 46235 | B2: =IFERROR(IF(INDEX(FTR_Data,ROW()-ROW(Rider_Input[#Headers]),c_FTR_ID)="","",INDEX(FTR_Data,ROW()-ROW(Rider_Input[#Headers]),c_FTR_ID)),"") -> 4849914 | C2: =IF(Rider_Input[[#This Row],[Rider ID]]="","",IFERROR(IF(INDEX(Rider_Master[Rider Name],MATCH(Rider_Input[[#This Row],[Rider ID]],Rider_Master[Rider ID],0))="","Rider "&Rider_Input[[#This Row],[Rider ID]],INDEX(Rider_Master[Rider Name],MATCH(Rider_Input[[#This Row],[Rider ID]],Rider_Master[Rider ID],0))),"Rider "&Rider_Input[[#This Row],[Rider ID]])) -> Rider 4849914 | D2: =IF(Rider_Input[[#This Row],[Rider ID]]="","",IFERROR(IF(INDEX(Rider_Master[Basic Payment (blank = default)],MATCH(Rider_Input[[#This Row],[Rider ID]],Rider_Master[Rider ID],0))="",Default_Basic,INDEX(Rider_Master[Basic Payment (blank = default)],MATCH(Rider_Input[[#This Row],[Rider ID]],Rider_Master[Rider ID],0))),Default_Basic)) -> 2000 | E2: =IF(Rider_Input[[#This Row],[Rider ID]]="","",DAY(EOMONTH(Salary_Month,0))) -> 31 | F2: =IF(Rider_Input[[#This Row],[Rider ID]]="","",IFERROR(IF(INDEX(FTR_Data,ROW()-ROW(Rider_Input[#Headers]),c_FTR_WD)="","",INDEX(FTR_Data,ROW()-ROW(Rider_Input[#Headers]),c_FTR_WD)),"")) -> 8 | G2: =IF(Rider_Input[[#This Row],[Rider ID]]="","",IFERROR(IF(INDEX(FTR_Data,ROW()-ROW(Rider_Input[#Headers]),c_FTR_Orders)="","",INDEX(FTR_Data,ROW()-ROW(Rider_Input[#Headers]),c_FTR_Orders)),"")) -> 72 | H2: =IF(Rider_Input[[#This Row],[Rider ID]]="","",IFERROR(ABS(INDEX(RLVL_Data,MATCH(Rider_Input[[#This Row],[Rider ID]],INDEX(RLVL_Data,0,c_RLVL_ID),0),c_RLVL_Missed)),0)) -> 0 | I2: =IF(Rider_Input[[#This Row],[Rider ID]]="","",IFERROR(ABS(INDEX(RLVL_Data,MATCH(Rider_Input[[#This Row],[Rider ID]],INDEX(RLVL_Data,0,c_RLVL_ID),0),c_RLVL_Bal)),0)) -> 268.09 | J2: =IF(Rider_Input[[#This Row],[Rider ID]]="","",IFERROR(ABS(INDEX(RLVL_Data,MATCH(Rider_Input[[#This Row],[Rider ID]],INDEX(RLVL_Data,0,c_RLVL_ID),0),c_RLVL_Stack)),0)) -> 32 | K2: =IF(Rider_Input[[#This Row],[Rider ID]]="","",SUMIFS(Adj_Input[Other Deductions],Adj_Input[Rider ID],Rider_Input[[#This Row],[Rider ID]])) -> 0 | L2: =IF(Rider_Input[[#This Row],[Rider ID]]="","",IFERROR(INDEX(Adj_Input[Note / Reason],MATCH(Rider_Input[[#This Row],[Rider ID]],Adj_Input[Rider ID],0))&"",""))
A3: =IF(Rider_Input[[#This Row],[Rider ID]]="","",Salary_Month) -> 46235 | B3: =IFERROR(IF(INDEX(FTR_Data,ROW()-ROW(Rider_Input[#Headers]),c_FTR_ID)="","",INDEX(FTR_Data,ROW()-ROW(Rider_Input[#Headers]),c_FTR_ID)),"") -> 4849909 | C3: =IF(Rider_Input[[#This Row],[Rider ID]]="","",IFERROR(IF(INDEX(Rider_Master[Rider Name],MATCH(Rider_Input[[#This Row],[Rider ID]],Rider_Master[Rider ID],0))="","Rider "&Rider_Input[[#This Row],[Rider ID]],INDEX(Rider_Master[Rider Name],MATCH(Rider_Input[[#This Row],[Rider ID]],Rider_Master[Rider ID],0))),"Rider "&Rider_Input[[#This Row],[Rider ID]])) -> Rider 4849909 | D3: =IF(Rider_Input[[#This Row],[Rider ID]]="","",IFERROR(IF(INDEX(Rider_Master[Basic Payment (blank = default)],MATCH(Rider_Input[[#This Row],[Rider ID]],Rider_Master[Rider ID],0))="",Default_Basic,INDEX(Rider_Master[Basic Payment (blank = default)],MATCH(Rider_Input[[#This Row],[Rider ID]],Rider_Master[Rider ID],0))),Default_Basic)) -> 2000 | E3: =IF(Rider_Input[[#This Row],[Rider ID]]="","",DAY(EOMONTH(Salary_Month,0))) -> 31 | F3: =IF(Rider_Input[[#This Row],[Rider ID]]="","",IFERROR(IF(INDEX(FTR_Data,ROW()-ROW(Rider_Input[#Headers]),c_FTR_WD)="","",INDEX(FTR_Data,ROW()-ROW(Rider_Input[#Headers]),c_FTR_WD)),"")) -> 11 | G3: =IF(Rider_Input[[#This Row],[Rider ID]]="","",IFERROR(IF(INDEX(FTR_Data,ROW()-ROW(Rider_Input[#Headers]),c_FTR_Orders)="","",INDEX(FTR_Data,ROW()-ROW(Rider_Input[#Headers]),c_FTR_Orders)),"")) -> 101 | H3: =IF(Rider_Input[[#This Row],[Rider ID]]="","",IFERROR(ABS(INDEX(RLVL_Data,MATCH(Rider_Input[[#This Row],[Rider ID]],INDEX(RLVL_Data,0,c_RLVL_ID),0),c_RLVL_Missed)),0)) -> 0 | I3: =IF(Rider_Input[[#This Row],[Rider ID]]="","",IFERROR(ABS(INDEX(RLVL_Data,MATCH(Rider_Input[[#This Row],[Rider ID]],INDEX(RLVL_Data,0,c_RLVL_ID),0),c_RLVL_Bal)),0)) -> 213.56 | J3: =IF(Rider_Input[[#This Row],[Rider ID]]="","",IFERROR(ABS(INDEX(RLVL_Data,MATCH(Rider_Input[[#This Row],[Rider ID]],INDEX(RLVL_Data,0,c_RLVL_ID),0),c_RLVL_Stack)),0)) -> 20 | K3: =IF(Rider_Input[[#This Row],[Rider ID]]="","",SUMIFS(Adj_Input[Other Deductions],Adj_Input[Rider ID],Rider_Input[[#This Row],[Rider ID]])) -> 0 | L3: =IF(Rider_Input[[#This Row],[Rider ID]]="","",IFERROR(INDEX(Adj_Input[Note / Reason],MATCH(Rider_Input[[#This Row],[Rider ID]],Adj_Input[Rider ID],0))&"",""))
A4: =IF(Rider_Input[[#This Row],[Rider ID]]="","",Salary_Month) -> 46235 | B4: =IFERROR(IF(INDEX(FTR_Data,ROW()-ROW(Rider_Input[#Headers]),c_FTR_ID)="","",INDEX(FTR_Data,ROW()-ROW(Rider_Input[#Headers]),c_FTR_ID)),"") -> 4849222 | C4: =IF(Rider_Input[[#This Row],[Rider ID]]="","",IFERROR(IF(INDEX(Rider_Master[Rider Name],MATCH(Rider_Input[[#This Row],[Rider ID]],Rider_Master[Rider ID],0))="","Rider "&Rider_Input[[#This Row],[Rider ID]],INDEX(Rider_Master[Rider Name],MATCH(Rider_Input[[#This Row],[Rider ID]],Rider_Master[Rider ID],0))),"Rider "&Rider_Input[[#This Row],[Rider ID]])) -> Rider 4849222 | D4: =IF(Rider_Input[[#This Row],[Rider ID]]="","",IFERROR(IF(INDEX(Rider_Master[Basic Payment (blank = default)],MATCH(Rider_Input[[#This Row],[Rider ID]],Rider_Master[Rider ID],0))="",Default_Basic,INDEX(Rider_Master[Basic Payment (blank = default)],MATCH(Rider_Input[[#This Row],[Rider ID]],Rider_Master[Rider ID],0))),Default_Basic)) -> 2000 | E4: =IF(Rider_Input[[#This Row],[Rider ID]]="","",DAY(EOMONTH(Salary_Month,0))) -> 31 | F4: =IF(Rider_Input[[#This Row],[Rider ID]]="","",IFERROR(IF(INDEX(FTR_Data,ROW()-ROW(Rider_Input[#Headers]),c_FTR_WD)="","",INDEX(FTR_Data,ROW()-ROW(Rider_Input[#Headers]),c_FTR_WD)),"")) -> 11 | G4: =IF(Rider_Input[[#This Row],[Rider ID]]="","",IFERROR(IF(INDEX(FTR_Data,ROW()-ROW(Rider_Input[#Headers]),c_FTR_Orders)="","",INDEX(FTR_Data,ROW()-ROW(Rider_Input[#Headers]),c_FTR_Orders)),"")) -> 105 | H4: =IF(Rider_Input[[#This Row],[Rider ID]]="","",IFERROR(ABS(INDEX(RLVL_Data,MATCH(Rider_Input[[#This Row],[Rider ID]],INDEX(RLVL_Data,0,c_RLVL_ID),0),c_RLVL_Missed)),0)) -> 0 | I4: =IF(Rider_Input[[#This Row],[Rider ID]]="","",IFERROR(ABS(INDEX(RLVL_Data,MATCH(Rider_Input[[#This Row],[Rider ID]],INDEX(RLVL_Data,0,c_RLVL_ID),0),c_RLVL_Bal)),0)) -> 190.77 | J4: =IF(Rider_Input[[#This Row],[Rider ID]]="","",IFERROR(ABS(INDEX(RLVL_Data,MATCH(Rider_Input[[#This Row],[Rider ID]],INDEX(RLVL_Data,0,c_RLVL_ID),0),c_RLVL_Stack)),0)) -> 20 | K4: =IF(Rider_Input[[#This Row],[Rider ID]]="","",SUMIFS(Adj_Input[Other Deductions],Adj_Input[Rider ID],Rider_Input[[#This Row],[Rider ID]])) -> 0 | L4: =IF(Rider_Input[[#This Row],[Rider ID]]="","",IFERROR(INDEX(Adj_Input[Note / Reason],MATCH(Rider_Input[[#This Row],[Rider ID]],Adj_Input[Rider ID],0))&"",""))
A5: =IF(Rider_Input[[#This Row],[Rider ID]]="","",Salary_Month) -> 46235 | B5: =IFERROR(IF(INDEX(FTR_Data,ROW()-ROW(Rider_Input[#Headers]),c_FTR_ID)="","",INDEX(FTR_Data,ROW()-ROW(Rider_Input[#Headers]),c_FTR_ID)),"") -> 4844480 | C5: =IF(Rider_Input[[#This Row],[Rider ID]]="","",IFERROR(IF(INDEX(Rider_Master[Rider Name],MATCH(Rider_Input[[#This Row],[Rider ID]],Rider_Master[Rider ID],0))="","Rider "&Rider_Input[[#This Row],[Rider ID]],INDEX(Rider_Master[Rider Name],MATCH(Rider_Input[[#This Row],[Rider ID]],Rider_Master[Rider ID],0))),"Rider "&Rider_Input[[#This Row],[Rider ID]])) -> Rider 4844480 | D5: =IF(Rider_Input[[#This Row],[Rider ID]]="","",IFERROR(IF(INDEX(Rider_Master[Basic Payment (blank = default)],MATCH(Rider_Input[[#This Row],[Rider ID]],Rider_Master[Rider ID],0))="",Default_Basic,INDEX(Rider_Master[Basic Payment (blank = default)],MATCH(Rider_Input[[#This Row],[Rider ID]],Rider_Master[Rider ID],0))),Default_Basic)) -> 2000 | E5: =IF(Rider_Input[[#This Row],[Rider ID]]="","",DAY(EOMONTH(Salary_Month,0))) -> 31 | F5: =IF(Rider_Input[[#This Row],[Rider ID]]="","",IFERROR(IF(INDEX(FTR_Data,ROW()-ROW(Rider_Input[#Headers]),c_FTR_WD)="","",INDEX(FTR_Data,ROW()-ROW(Rider_Input[#Headers]),c_FTR_WD)),"")) -> 12 | G5: =IF(Rider_Input[[#This Row],[Rider ID]]="","",IFERROR(IF(INDEX(FTR_Data,ROW()-ROW(Rider_Input[#Headers]),c_FTR_Orders)="","",INDEX(FTR_Data,ROW()-ROW(Rider_Input[#Headers]),c_FTR_Orders)),"")) -> 150 | H5: =IF(Rider_Input[[#This Row],[Rider ID]]="","",IFERROR(ABS(INDEX(RLVL_Data,MATCH(Rider_Input[[#This Row],[Rider ID]],INDEX(RLVL_Data,0,c_RLVL_ID),0),c_RLVL_Missed)),0)) -> 0 | I5: =IF(Rider_Input[[#This Row],[Rider ID]]="","",IFERROR(ABS(INDEX(RLVL_Data,MATCH(Rider_Input[[#This Row],[Rider ID]],INDEX(RLVL_Data,0,c_RLVL_ID),0),c_RLVL_Bal)),0)) -> 57.17 | J5: =IF(Rider_Input[[#This Row],[Rider ID]]="","",IFERROR(ABS(INDEX(RLVL_Data,MATCH(Rider_Input[[#This Row],[Rider ID]],INDEX(RLVL_Data,0,c_RLVL_ID),0),c_RLVL_Stack)),0)) -> 36 | K5: =IF(Rider_Input[[#This Row],[Rider ID]]="","",SUMIFS(Adj_Input[Other Deductions],Adj_Input[Rider ID],Rider_Input[[#This Row],[Rider ID]])) -> 0 | L5: =IF(Rider_Input[[#This Row],[Rider ID]]="","",IFERROR(INDEX(Adj_Input[Note / Reason],MATCH(Rider_Input[[#This Row],[Rider ID]],Adj_Input[Rider ID],0))&"",""))
A6: =IF(Rider_Input[[#This Row],[Rider ID]]="","",Salary_Month) -> 46235 | B6: =IFERROR(IF(INDEX(FTR_Data,ROW()-ROW(Rider_Input[#Headers]),c_FTR_ID)="","",INDEX(FTR_Data,ROW()-ROW(Rider_Input[#Headers]),c_FTR_ID)),"") -> 4838478 | C6: =IF(Rider_Input[[#This Row],[Rider ID]]="","",IFERROR(IF(INDEX(Rider_Master[Rider Name],MATCH(Rider_Input[[#This Row],[Rider ID]],Rider_Master[Rider ID],0))="","Rider "&Rider_Input[[#This Row],[Rider ID]],INDEX(Rider_Master[Rider Name],MATCH(Rider_Input[[#This Row],[Rider ID]],Rider_Master[Rider ID],0))),"Rider "&Rider_Input[[#This Row],[Rider ID]])) -> Rider 4838478 | D6: =IF(Rider_Input[[#This Row],[Rider ID]]="","",IFERROR(IF(INDEX(Rider_Master[Basic Payment (blank = default)],MATCH(Rider_Input[[#This Row],[Rider ID]],Rider_Master[Rider ID],0))="",Default_Basic,INDEX(Rider_Master[Basic Payment (blank = default)],MATCH(Rider_Input[[#This Row],[Rider ID]],Rider_Master[Rider ID],0))),Default_Basic)) -> 2000 | E6: =IF(Rider_Input[[#This Row],[Rider ID]]="","",DAY(EOMONTH(Salary_Month,0))) -> 31 | F6: =IF(Rider_Input[[#This Row],[Rider ID]]="","",IFERROR(IF(INDEX(FTR_Data,ROW()-ROW(Rider_Input[#Headers]),c_FTR_WD)="","",INDEX(FTR_Data,ROW()-ROW(Rider_Input[#Headers]),c_FTR_WD)),"")) -> 14 | G6: =IF(Rider_Input[[#This Row],[Rider ID]]="","",IFERROR(IF(INDEX(FTR_Data,ROW()-ROW(Rider_Input[#Headers]),c_FTR_Orders)="","",INDEX(FTR_Data,ROW()-ROW(Rider_Input[#Headers]),c_FTR_Orders)),"")) -> 171 | H6: =IF(Rider_Input[[#This Row],[Rider ID]]="","",IFERROR(ABS(INDEX(RLVL_Data,MATCH(Rider_Input[[#This Row],[Rider ID]],INDEX(RLVL_Data,0,c_RLVL_ID),0),c_RLVL_Missed)),0)) -> 0 | I6: =IF(Rider_Input[[#This Row],[Rider ID]]="","",IFERROR(ABS(INDEX(RLVL_Data,MATCH(Rider_Input[[#This Row],[Rider ID]],INDEX(RLVL_Data,0,c_RLVL_ID),0),c_RLVL_Bal)),0)) -> 200.44 | J6: =IF(Rider_Input[[#This Row],[Rider ID]]="","",IFERROR(ABS(INDEX(RLVL_Data,MATCH(Rider_Input[[#This Row],[Rider ID]],INDEX(RLVL_Data,0,c_RLVL_ID),0),c_RLVL_Stack)),0)) -> 36 | K6: =IF(Rider_Input[[#This Row],[Rider ID]]="","",SUMIFS(Adj_Input[Other Deductions],Adj_Input[Rider ID],Rider_Input[[#This Row],[Rider ID]])) -> 0 | L6: =IF(Rider_Input[[#This Row],[Rider ID]]="","",IFERROR(INDEX(Adj_Input[Note / Reason],MATCH(Rider_Input[[#This Row],[Rider ID]],Adj_Input[Rider ID],0))&"",""))
A7: =IF(Rider_Input[[#This Row],[Rider ID]]="","",Salary_Month) -> 46235 | B7: =IFERROR(IF(INDEX(FTR_Data,ROW()-ROW(Rider_Input[#Headers]),c_FTR_ID)="","",INDEX(FTR_Data,ROW()-ROW(Rider_Input[#Headers]),c_FTR_ID)),"") -> 4838471 | C7: =IF(Rider_Input[[#This Row],[Rider ID]]="","",IFERROR(IF(INDEX(Rider_Master[Rider Name],MATCH(Rider_Input[[#This Row],[Rider ID]],Rider_Master[Rider ID],0))="","Rider "&Rider_Input[[#This Row],[Rider ID]],INDEX(Rider_Master[Rider Name],MATCH(Rider_Input[[#This Row],[Rider ID]],Rider_Master[Rider ID],0))),"Rider "&Rider_Input[[#This Row],[Rider ID]])) -> Rider 4838471 | D7: =IF(Rider_Input[[#This Row],[Rider ID]]="","",IFERROR(IF(INDEX(Rider_Master[Basic Payment (blank = default)],MATCH(Rider_Input[[#This Row],[Rider ID]],Rider_Master[Rider ID],0))="",Default_Basic,INDEX(Rider_Master[Basic Payment (blank = default)],MATCH(Rider_Input[[#This Row],[Rider ID]],Rider_Master[Rider ID],0))),Default_Basic)) -> 2000 | E7: =IF(Rider_Input[[#This Row],[Rider ID]]="","",DAY(EOMONTH(Salary_Month,0))) -> 31 | F7: =IF(Rider_Input[[#This Row],[Rider ID]]="","",IFERROR(IF(INDEX(FTR_Data,ROW()-ROW(Rider_Input[#Headers]),c_FTR_WD)="","",INDEX(FTR_Data,ROW()-ROW(Rider_Input[#Headers]),c_FTR_WD)),"")) -> 12 | G7: =IF(Rider_Input[[#This Row],[Rider ID]]="","",IFERROR(IF(INDEX(FTR_Data,ROW()-ROW(Rider_Input[#Headers]),c_FTR_Orders)="","",INDEX(FTR_Data,ROW()-ROW(Rider_Input[#Headers]),c_FTR_Orders)),"")) -> 146 | H7: =IF(Rider_Input[[#This Row],[Rider ID]]="","",IFERROR(ABS(INDEX(RLVL_Data,MATCH(Rider_Input[[#This Row],[Rider ID]],INDEX(RLVL_Data,0,c_RLVL_ID),0),c_RLVL_Missed)),0)) -> 500 | I7: =IF(Rider_Input[[#This Row],[Rider ID]]="","",IFERROR(ABS(INDEX(RLVL_Data,MATCH(Rider_Input[[#This Row],[Rider ID]],INDEX(RLVL_Data,0,c_RLVL_ID),0),c_RLVL_Bal)),0)) -> 192.89 | J7: =IF(Rider_Input[[#This Row],[Rider ID]]="","",IFERROR(ABS(INDEX(RLVL_Data,MATCH(Rider_Input[[#This Row],[Rider ID]],INDEX(RLVL_Data,0,c_RLVL_ID),0),c_RLVL_Stack)),0)) -> 32 | K7: =IF(Rider_Input[[#This Row],[Rider ID]]="","",SUMIFS(Adj_Input[Other Deductions],Adj_Input[Rider ID],Rider_Input[[#This Row],[Rider ID]])) -> 0 | L7: =IF(Rider_Input[[#This Row],[Rider ID]]="","",IFERROR(INDEX(Adj_Input[Note / Reason],MATCH(Rider_Input[[#This Row],[Rider ID]],Adj_Input[Rider ID],0))&"",""))
A8: =IF(Rider_Input[[#This Row],[Rider ID]]="","",Salary_Month) -> 46235 | B8: =IFERROR(IF(INDEX(FTR_Data,ROW()-ROW(Rider_Input[#Headers]),c_FTR_ID)="","",INDEX(FTR_Data,ROW()-ROW(Rider_Input[#Headers]),c_FTR_ID)),"") -> 4747290 | C8: =IF(Rider_Input[[#This Row],[Rider ID]]="","",IFERROR(IF(INDEX(Rider_Master[Rider Name],MATCH(Rider_Input[[#This Row],[Rider ID]],Rider_Master[Rider ID],0))="","Rider "&Rider_Input[[#This Row],[Rider ID]],INDEX(Rider_Master[Rider Name],MATCH(Rider_Input[[#This Row],[Rider ID]],Rider_Master[Rider ID],0))),"Rider "&Rider_Input[[#This Row],[Rider ID]])) -> Rider 4747290 | D8: =IF(Rider_Input[[#This Row],[Rider ID]]="","",IFERROR(IF(INDEX(Rider_Master[Basic Payment (blank = default)],MATCH(Rider_Input[[#This Row],[Rider ID]],Rider_Master[Rider ID],0))="",Default_Basic,INDEX(Rider_Master[Basic Payment (blank = default)],MATCH(Rider_Input[[#This Row],[Rider ID]],Rider_Master[Rider ID],0))),Default_Basic)) -> 2000 | E8: =IF(Rider_Input[[#This Row],[Rider ID]]="","",DAY(EOMONTH(Salary_Month,0))) -> 31 | F8: =IF(Rider_Input[[#This Row],[Rider ID]]="","",IFERROR(IF(INDEX(FTR_Data,ROW()-ROW(Rider_Input[#Headers]),c_FTR_WD)="","",INDEX(FTR_Data,ROW()-ROW(Rider_Input[#Headers]),c_FTR_WD)),"")) -> 31 | G8: =IF(Rider_Input[[#This Row],[Rider ID]]="","",IFERROR(IF(INDEX(FTR_Data,ROW()-ROW(Rider_Input[#Headers]),c_FTR_Orders)="","",INDEX(FTR_Data,ROW()-ROW(Rider_Input[#Headers]),c_FTR_Orders)),"")) -> 498 | H8: =IF(Rider_Input[[#This Row],[Rider ID]]="","",IFERROR(ABS(INDEX(RLVL_Data,MATCH(Rider_Input[[#This Row],[Rider ID]],INDEX(RLVL_Data,0,c_RLVL_ID),0),c_RLVL_Missed)),0)) -> 0 | I8: =IF(Rider_Input[[#This Row],[Rider ID]]="","",IFERROR(ABS(INDEX(RLVL_Data,MATCH(Rider_Input[[#This Row],[Rider ID]],INDEX(RLVL_Data,0,c_RLVL_ID),0),c_RLVL_Bal)),0)) -> 104.03 | J8: =IF(Rider_Input[[#This Row],[Rider ID]]="","",IFERROR(ABS(INDEX(RLVL_Data,MATCH(Rider_Input[[#This Row],[Rider ID]],INDEX(RLVL_Data,0,c_RLVL_ID),0),c_RLVL_Stack)),0)) -> 52 | K8: =IF(Rider_Input[[#This Row],[Rider ID]]="","",SUMIFS(Adj_Input[Other Deductions],Adj_Input[Rider ID],Rider_Input[[#This Row],[Rider ID]])) -> 0 | L8: =IF(Rider_Input[[#This Row],[Rider ID]]="","",IFERROR(INDEX(Adj_Input[Note / Reason],MATCH(Rider_Input[[#This Row],[Rider ID]],Adj_Input[Rider ID],0))&"",""))
A9: =IF(Rider_Input[[#This Row],[Rider ID]]="","",Salary_Month) -> 46235 | B9: =IFERROR(IF(INDEX(FTR_Data,ROW()-ROW(Rider_Input[#Headers]),c_FTR_ID)="","",INDEX(FTR_Data,ROW()-ROW(Rider_Input[#Headers]),c_FTR_ID)),"") -> 4652654 | C9: =IF(Rider_Input[[#This Row],[Rider ID]]="","",IFERROR(IF(INDEX(Rider_Master[Rider Name],MATCH(Rider_Input[[#This Row],[Rider ID]],Rider_Master[Rider ID],0))="","Rider "&Rider_Input[[#This Row],[Rider ID]],INDEX(Rider_Master[Rider Name],MATCH(Rider_Input[[#This Row],[Rider ID]],Rider_Master[Rider ID],0))),"Rider "&Rider_Input[[#This Row],[Rider ID]])) -> Rider 4652654 | D9: =IF(Rider_Input[[#This Row],[Rider ID]]="","",IFERROR(IF(INDEX(Rider_Master[Basic Payment (blank = default)],MATCH(Rider_Input[[#This Row],[Rider ID]],Rider_Master[Rider ID],0))="",Default_Basic,INDEX(Rider_Master[Basic Payment (blank = default)],MATCH(Rider_Input[[#This Row],[Rider ID]],Rider_Master[Rider ID],0))),Default_Basic)) -> 2000 | E9: =IF(Rider_Input[[#This Row],[Rider ID]]="","",DAY(EOMONTH(Salary_Month,0))) -> 31 | F9: =IF(Rider_Input[[#This Row],[Rider ID]]="","",IFERROR(IF(INDEX(FTR_Data,ROW()-ROW(Rider_Input[#Headers]),c_FTR_WD)="","",INDEX(FTR_Data,ROW()-ROW(Rider_Input[#Headers]),c_FTR_WD)),"")) -> 31 | G9: =IF(Rider_Input[[#This Row],[Rider ID]]="","",IFERROR(IF(INDEX(FTR_Data,ROW()-ROW(Rider_Input[#Headers]),c_FTR_Orders)="","",INDEX(FTR_Data,ROW()-ROW(Rider_Input[#Headers]),c_FTR_Orders)),"")) -> 433 | H9: =IF(Rider_Input[[#This Row],[Rider ID]]="","",IFERROR(ABS(INDEX(RLVL_Data,MATCH(Rider_Input[[#This Row],[Rider ID]],INDEX(RLVL_Data,0,c_RLVL_ID),0),c_RLVL_Missed)),0)) -> 0 | I9: =IF(Rider_Input[[#This Row],[Rider ID]]="","",IFERROR(ABS(INDEX(RLVL_Data,MATCH(Rider_Input[[#This Row],[Rider ID]],INDEX(RLVL_Data,0,c_RLVL_ID),0),c_RLVL_Bal)),0)) -> 201.65 | J9: =IF(Rider_Input[[#This Row],[Rider ID]]="","",IFERROR(ABS(INDEX(RLVL_Data,MATCH(Rider_Input[[#This Row],[Rider ID]],INDEX(RLVL_Data,0,c_RLVL_ID),0),c_RLVL_Stack)),0)) -> 44 | K9: =IF(Rider_Input[[#This Row],[Rider ID]]="","",SUMIFS(Adj_Input[Other Deductions],Adj_Input[Rider ID],Rider_Input[[#This Row],[Rider ID]])) -> 0 | L9: =IF(Rider_Input[[#This Row],[Rider ID]]="","",IFERROR(INDEX(Adj_Input[Note / Reason],MATCH(Rider_Input[[#This Row],[Rider ID]],Adj_Input[Rider ID],0))&"",""))
A10: =IF(Rider_Input[[#This Row],[Rider ID]]="","",Salary_Month) -> 46235 | B10: =IFERROR(IF(INDEX(FTR_Data,ROW()-ROW(Rider_Input[#Headers]),c_FTR_ID)="","",INDEX(FTR_Data,ROW()-ROW(Rider_Input[#Headers]),c_FTR_ID)),"") -> 4652587 | C10: =IF(Rider_Input[[#This Row],[Rider ID]]="","",IFERROR(IF(INDEX(Rider_Master[Rider Name],MATCH(Rider_Input[[#This Row],[Rider ID]],Rider_Master[Rider ID],0))="","Rider "&Rider_Input[[#This Row],[Rider ID]],INDEX(Rider_Master[Rider Name],MATCH(Rider_Input[[#This Row],[Rider ID]],Rider_Master[Rider ID],0))),"Rider "&Rider_Input[[#This Row],[Rider ID]])) -> Rider 4652587 | D10: =IF(Rider_Input[[#This Row],[Rider ID]]="","",IFERROR(IF(INDEX(Rider_Master[Basic Payment (blank = default)],MATCH(Rider_Input[[#This Row],[Rider ID]],Rider_Master[Rider ID],0))="",Default_Basic,INDEX(Rider_Master[Basic Payment (blank = default)],MATCH(Rider_Input[[#This Row],[Rider ID]],Rider_Master[Rider ID],0))),Default_Basic)) -> 2000 | E10: =IF(Rider_Input[[#This Row],[Rider ID]]="","",DAY(EOMONTH(Salary_Month,0))) -> 31 | F10: =IF(Rider_Input[[#This Row],[Rider ID]]="","",IFERROR(IF(INDEX(FTR_Data,ROW()-ROW(Rider_Input[#Headers]),c_FTR_WD)="","",INDEX(FTR_Data,ROW()-ROW(Rider_Input[#Headers]),c_FTR_WD)),"")) -> 30 | G10: =IF(Rider_Input[[#This Row],[Rider ID]]="","",IFERROR(IF(INDEX(FTR_Data,ROW()-ROW(Rider_Input[#Headers]),c_FTR_Orders)="","",INDEX(FTR_Data,ROW()-ROW(Rider_Input[#Headers]),c_FTR_Orders)),"")) -> 382 | H10: =IF(Rider_Input[[#This Row],[Rider ID]]="","",IFERROR(ABS(INDEX(RLVL_Data,MATCH(Rider_Input[[#This Row],[Rider ID]],INDEX(RLVL_Data,0,c_RLVL_ID),0),c_RLVL_Missed)),0)) -> 500 | I10: =IF(Rider_Input[[#This Row],[Rider ID]]="","",IFERROR(ABS(INDEX(RLVL_Data,MATCH(Rider_Input[[#This Row],[Rider ID]],INDEX(RLVL_Data,0,c_RLVL_ID),0),c_RLVL_Bal)),0)) -> 121.92 | J10: =IF(Rider_Input[[#This Row],[Rider ID]]="","",IFERROR(ABS(INDEX(RLVL_Data,MATCH(Rider_Input[[#This Row],[Rider ID]],INDEX(RLVL_Data,0,c_RLVL_ID),0),c_RLVL_Stack)),0)) -> 44 | K10: =IF(Rider_Input[[#This Row],[Rider ID]]="","",SUMIFS(Adj_Input[Other Deductions],Adj_Input[Rider ID],Rider_Input[[#This Row],[Rider ID]])) -> 0 | L10: =IF(Rider_Input[[#This Row],[Rider ID]]="","",IFERROR(INDEX(Adj_Input[Note / Reason],MATCH(Rider_Input[[#This Row],[Rider ID]],Adj_Input[Rider ID],0))&"",""))
A11: =IF(Rider_Input[[#This Row],[Rider ID]]="","",Salary_Month) -> 46235 | B11: =IFERROR(IF(INDEX(FTR_Data,ROW()-ROW(Rider_Input[#Headers]),c_FTR_ID)="","",INDEX(FTR_Data,ROW()-ROW(Rider_Input[#Headers]),c_FTR_ID)),"") -> 4648709 | C11: =IF(Rider_Input[[#This Row],[Rider ID]]="","",IFERROR(IF(INDEX(Rider_Master[Rider Name],MATCH(Rider_Input[[#This Row],[Rider ID]],Rider_Master[Rider ID],0))="","Rider "&Rider_Input[[#This Row],[Rider ID]],INDEX(Rider_Master[Rider Name],MATCH(Rider_Input[[#This Row],[Rider ID]],Rider_Master[Rider ID],0))),"Rider "&Rider_Input[[#This Row],[Rider ID]])) -> Rider 4648709 | D11: =IF(Rider_Input[[#This Row],[Rider ID]]="","",IFERROR(IF(INDEX(Rider_Master[Basic Payment (blank = default)],MATCH(Rider_Input[[#This Row],[Rider ID]],Rider_Master[Rider ID],0))="",Default_Basic,INDEX(Rider_Master[Basic Payment (blank = default)],MATCH(Rider_Input[[#This Row],[Rider ID]],Rider_Master[Rider ID],0))),Default_Basic)) -> 2000 | E11: =IF(Rider_Input[[#This Row],[Rider ID]]="","",DAY(EOMONTH(Salary_Month,0))) -> 31 | F11: =IF(Rider_Input[[#This Row],[Rider ID]]="","",IFERROR(IF(INDEX(FTR_Data,ROW()-ROW(Rider_Input[#Headers]),c_FTR_WD)="","",INDEX(FTR_Data,ROW()-ROW(Rider_Input[#Headers]),c_FTR_WD)),"")) -> 31 | G11: =IF(Rider_Input[[#This Row],[Rider ID]]="","",IFERROR(IF(INDEX(FTR_Data,ROW()-ROW(Rider_Input[#Headers]),c_FTR_Orders)="","",INDEX(FTR_Data,ROW()-ROW(Rider_Input[#Headers]),c_FTR_Orders)),"")) -> 391 | H11: =IF(Rider_Input[[#This Row],[Rider ID]]="","",IFERROR(ABS(INDEX(RLVL_Data,MATCH(Rider_Input[[#This Row],[Rider ID]],INDEX(RLVL_Data,0,c_RLVL_ID),0),c_RLVL_Missed)),0)) -> 0 | I11: =IF(Rider_Input[[#This Row],[Rider ID]]="","",IFERROR(ABS(INDEX(RLVL_Data,MATCH(Rider_Input[[#This Row],[Rider ID]],INDEX(RLVL_Data,0,c_RLVL_ID),0),c_RLVL_Bal)),0)) -> 266.18 | J11: =IF(Rider_Input[[#This Row],[Rider ID]]="","",IFERROR(ABS(INDEX(RLVL_Data,MATCH(Rider_Input[[#This Row],[Rider ID]],INDEX(RLVL_Data,0,c_RLVL_ID),0),c_RLVL_Stack)),0)) -> 76 | K11: =IF(Rider_Input[[#This Row],[Rider ID]]="","",SUMIFS(Adj_Input[Other Deductions],Adj_Input[Rider ID],Rider_Input[[#This Row],[Rider ID]])) -> 0 | L11: =IF(Rider_Input[[#This Row],[Rider ID]]="","",IFERROR(INDEX(Adj_Input[Note / Reason],MATCH(Rider_Input[[#This Row],[Rider ID]],Adj_Input[Rider ID],0))&"",""))
A12: =IF(Rider_Input[[#This Row],[Rider ID]]="","",Salary_Month) -> 46235 | B12: =IFERROR(IF(INDEX(FTR_Data,ROW()-ROW(Rider_Input[#Headers]),c_FTR_ID)="","",INDEX(FTR_Data,ROW()-ROW(Rider_Input[#Headers]),c_FTR_ID)),"") -> 4648308 | C12: =IF(Rider_Input[[#This Row],[Rider ID]]="","",IFERROR(IF(INDEX(Rider_Master[Rider Name],MATCH(Rider_Input[[#This Row],[Rider ID]],Rider_Master[Rider ID],0))="","Rider "&Rider_Input[[#This Row],[Rider ID]],INDEX(Rider_Master[Rider Name],MATCH(Rider_Input[[#This Row],[Rider ID]],Rider_Master[Rider ID],0))),"Rider "&Rider_Input[[#This Row],[Rider ID]])) -> Rider 4648308 | D12: =IF(Rider_Input[[#This Row],[Rider ID]]="","",IFERROR(IF(INDEX(Rider_Master[Basic Payment (blank = default)],MATCH(Rider_Input[[#This Row],[Rider ID]],Rider_Master[Rider ID],0))="",Default_Basic,INDEX(Rider_Master[Basic Payment (blank = default)],MATCH(Rider_Input[[#This Row],[Rider ID]],Rider_Master[Rider ID],0))),Default_Basic)) -> 2000 | E12: =IF(Rider_Input[[#This Row],[Rider ID]]="","",DAY(EOMONTH(Salary_Month,0))) -> 31 | F12: =IF(Rider_Input[[#This Row],[Rider ID]]="","",IFERROR(IF(INDEX(FTR_Data,ROW()-ROW(Rider_Input[#Headers]),c_FTR_WD)="","",INDEX(FTR_Data,ROW()-ROW(Rider_Input[#Headers]),c_FTR_WD)),"")) -> 31 | G12: =IF(Rider_Input[[#This Row],[Rider ID]]="","",IFERROR(IF(INDEX(FTR_Data,ROW()-ROW(Rider_Input[#Headers]),c_FTR_Orders)="","",INDEX(FTR_Data,ROW()-ROW(Rider_Input[#Headers]),c_FTR_Orders)),"")) -> 551 | H12: =IF(Rider_Input[[#This Row],[Rider ID]]="","",IFERROR(ABS(INDEX(RLVL_Data,MATCH(Rider_Input[[#This Row],[Rider ID]],INDEX(RLVL_Data,0,c_RLVL_ID),0),c_RLVL_Missed)),0)) -> 0 | I12: =IF(Rider_Input[[#This Row],[Rider ID]]="","",IFERROR(ABS(INDEX(RLVL_Data,MATCH(Rider_Input[[#This Row],[Rider ID]],INDEX(RLVL_Data,0,c_RLVL_ID),0),c_RLVL_Bal)),0)) -> 93.12 | J12: =IF(Rider_Input[[#This Row],[Rider ID]]="","",IFERROR(ABS(INDEX(RLVL_Data,MATCH(Rider_Input[[#This Row],[Rider ID]],INDEX(RLVL_Data,0,c_RLVL_ID),0),c_RLVL_Stack)),0)) -> 112 | K12: =IF(Rider_Input[[#This Row],[Rider ID]]="","",SUMIFS(Adj_Input[Other Deductions],Adj_Input[Rider ID],Rider_Input[[#This Row],[Rider ID]])) -> 0 | L12: =IF(Rider_Input[[#This Row],[Rider ID]]="","",IFERROR(INDEX(Adj_Input[Note / Reason],MATCH(Rider_Input[[#This Row],[Rider ID]],Adj_Input[Rider ID],0))&"",""))
A13: =IF(Rider_Input[[#This Row],[Rider ID]]="","",Salary_Month) -> 46235 | B13: =IFERROR(IF(INDEX(FTR_Data,ROW()-ROW(Rider_Input[#Headers]),c_FTR_ID)="","",INDEX(FTR_Data,ROW()-ROW(Rider_Input[#Headers]),c_FTR_ID)),"") -> 4644774 | C13: =IF(Rider_Input[[#This Row],[Rider ID]]="","",IFERROR(IF(INDEX(Rider_Master[Rider Name],MATCH(Rider_Input[[#This Row],[Rider ID]],Rider_Master[Rider ID],0))="","Rider "&Rider_Input[[#This Row],[Rider ID]],INDEX(Rider_Master[Rider Name],MATCH(Rider_Input[[#This Row],[Rider ID]],Rider_Master[Rider ID],0))),"Rider "&Rider_Input[[#This Row],[Rider ID]])) -> Rider 4644774 | D13: =IF(Rider_Input[[#This Row],[Rider ID]]="","",IFERROR(IF(INDEX(Rider_Master[Basic Payment (blank = default)],MATCH(Rider_Input[[#This Row],[Rider ID]],Rider_Master[Rider ID],0))="",Default_Basic,INDEX(Rider_Master[Basic Payment (blank = default)],MATCH(Rider_Input[[#This Row],[Rider ID]],Rider_Master[Rider ID],0))),Default_Basic)) -> 2000 | E13: =IF(Rider_Input[[#This Row],[Rider ID]]="","",DAY(EOMONTH(Salary_Month,0))) -> 31 | F13: =IF(Rider_Input[[#This Row],[Rider ID]]="","",IFERROR(IF(INDEX(FTR_Data,ROW()-ROW(Rider_Input[#Headers]),c_FTR_WD)="","",INDEX(FTR_Data,ROW()-ROW(Rider_Input[#Headers]),c_FTR_WD)),"")) -> 31 | G13: =IF(Rider_Input[[#This Row],[Rider ID]]="","",IFERROR(IF(INDEX(FTR_Data,ROW()-ROW(Rider_Input[#Headers]),c_FTR_Orders)="","",INDEX(FTR_Data,ROW()-ROW(Rider_Input[#Headers]),c_FTR_Orders)),"")) -> 367 | H13: =IF(Rider_Input[[#This Row],[Rider ID]]="","",IFERROR(ABS(INDEX(RLVL_Data,MATCH(Rider_Input[[#This Row],[Rider ID]],INDEX(RLVL_Data,0,c_RLVL_ID),0),c_RLVL_Missed)),0)) -> 0 | I13: =IF(Rider_Input[[#This Row],[Rider ID]]="","",IFERROR(ABS(INDEX(RLVL_Data,MATCH(Rider_Input[[#This Row],[Rider ID]],INDEX(RLVL_Data,0,c_RLVL_ID),0),c_RLVL_Bal)),0)) -> 275.31 | J13: =IF(Rider_Input[[#This Row],[Rider ID]]="","",IFERROR(ABS(INDEX(RLVL_Data,MATCH(Rider_Input[[#This Row],[Rider ID]],INDEX(RLVL_Data,0,c_RLVL_ID),0),c_RLVL_Stack)),0)) -> 52 | K13: =IF(Rider_Input[[#This Row],[Rider ID]]="","",SUMIFS(Adj_Input[Other Deductions],Adj_Input[Rider ID],Rider_Input[[#This Row],[Rider ID]])) -> 0 | L13: =IF(Rider_Input[[#This Row],[Rider ID]]="","",IFERROR(INDEX(Adj_Input[Note / Reason],MATCH(Rider_Input[[#This Row],[Rider ID]],Adj_Input[Rider ID],0))&"",""))
... A501: =IF(Rider_Input[[#This Row],[Rider ID]]="","",Salary_Month) | B501: =IFERROR(IF(INDEX(FTR_Data,ROW()-ROW(Rider_Input[#Headers]),c_FTR_ID)="","",INDEX(FTR_Data,ROW()-ROW(Rider_Input[#Headers]),c_FTR_ID)),"") | C501: =IF(Rider_Input[[#This Row],[Rider ID]]="","",IFERROR(IF(INDEX(Rider_Master[Rider Name],MATCH(Rider_Input[[#This Row],[Rider ID]],Rider_Master[Rider ID],0))="","Rider "&Rider_Input[[#This Row],[Rider ID]],INDEX(Rider_Master[Rider Name],MATCH(Rider_Input[[#This Row],[Rider ID]],Rider_Master[Rider ID],0))),"Rider "&Rider_Input[[#This Row],[Rider ID]])) | D501: =IF(Rider_Input[[#This Row],[Rider ID]]="","",IFERROR(IF(INDEX(Rider_Master[Basic Payment (blank = default)],MATCH(Rider_Input[[#This Row],[Rider ID]],Rider_Master[Rider ID],0))="",Default_Basic,INDEX(Rider_Master[Basic Payment (blank = default)],MATCH(Rider_Input[[#This Row],[Rider ID]],Rider_Master[Rider ID],0))),Default_Basic)) | E501: =IF(Rider_Input[[#This Row],[Rider ID]]="","",DAY(EOMONTH(Salary_Month,0))) | F501: =IF(Rider_Input[[#This Row],[Rider ID]]="","",IFERROR(IF(INDEX(FTR_Data,ROW()-ROW(Rider_Input[#Headers]),c_FTR_WD)="","",INDEX(FTR_Data,ROW()-ROW(Rider_Input[#Headers]),c_FTR_WD)),"")) | G501: =IF(Rider_Input[[#This Row],[Rider ID]]="","",IFERROR(IF(INDEX(FTR_Data,ROW()-ROW(Rider_Input[#Headers]),c_FTR_Orders)="","",INDEX(FTR_Data,ROW()-ROW(Rider_Input[#Headers]),c_FTR_Orders)),"")) | H501: =IF(Rider_Input[[#This Row],[Rider ID]]="","",IFERROR(ABS(INDEX(RLVL_Data,MATCH(Rider_Input[[#This Row],[Rider ID]],INDEX(RLVL_Data,0,c_RLVL_ID),0),c_RLVL_Missed)),0)) | I501: =IF(Rider_Input[[#This Row],[Rider ID]]="","",IFERROR(ABS(INDEX(RLVL_Data,MATCH(Rider_Input[[#This Row],[Rider ID]],INDEX(RLVL_Data,0,c_RLVL_ID),0),c_RLVL_Bal)),0)) | J501: =IF(Rider_Input[[#This Row],[Rider ID]]="","",IFERROR(ABS(INDEX(RLVL_Data,MATCH(Rider_Input[[#This Row],[Rider ID]],INDEX(RLVL_Data,0,c_RLVL_ID),0),c_RLVL_Stack)),0)) | K501: =IF(Rider_Input[[#This Row],[Rider ID]]="","",SUMIFS(Adj_Input[Other Deductions],Adj_Input[Rider ID],Rider_Input[[#This Row],[Rider ID]])) | L501: =IF(Rider_Input[[#This Row],[Rider ID]]="","",IFERROR(INDEX(Adj_Input[Note / Reason],MATCH(Rider_Input[[#This Row],[Rider ID]],Adj_Input[Rider ID],0))&"",""))

Sheet Salary_Calculation
A1: Salary Month | B1: Rider ID | C1: Rider Name | D1: Basic Payment | E1: Calendar Days | F1: Working Days | G1: Monthly Target Orders | H1: Rider Target Orders | I1: Completed Orders | J1: Base Order Rate | K1: Orders Counted at Base Rate | L1: Earned Salary | M1: Missing Orders | N1: Missing-Order Deduction | O1: Extra Orders | P1: Extra-Order Bonus | Q1: Gross Salary Before Deductions | R1: missed_days_penalty | S1: Rider Balance | T1: stacking_deduction | U1: Other Deductions | V1: Total Deductions | W1: Final Salary | X1: Negative Balance / Amount Due from Rider | Y1: Payment Status | Z1: Notes | AA1: Salary Before Other Deductions | AB1: Total Amount Due from Rider | AC1: Exception Reason | AD1: Basic Salary for Target | AE1: Source Row
A2: =IF(Salary_Calculation[[#This Row],[Source Row]]="","",IF(INDEX(Rider_Input[Salary Month],Salary_Calculation[[#This Row],[Source Row]])="","",INDEX(Rider_Input[Salary Month],Salary_Calculation[[#This Row],[Source Row]]))) -> 46235 | B2: =IF(Salary_Calculation[[#This Row],[Source Row]]="","",IF(INDEX(Rider_Input[Rider ID],Salary_Calculation[[#This Row],[Source Row]])="","",INDEX(Rider_Input[Rider ID],Salary_Calculation[[#This Row],[Source Row]]))) -> 4849914 | C2: =IF(Salary_Calculation[[#This Row],[Source Row]]="","",IF(INDEX(Rider_Input[Rider Name],Salary_Calculation[[#This Row],[Source Row]])="","",INDEX(Rider_Input[Rider Name],Salary_Calculation[[#This Row],[Source Row]]))) -> Rider 4849914 | D2: =IF(Salary_Calculation[[#This Row],[Source Row]]="","",IF(INDEX(Rider_Input[Basic Payment],Salary_Calculation[[#This Row],[Source Row]])="","",INDEX(Rider_Input[Basic Payment],Salary_Calculation[[#This Row],[Source Row]]))) -> 2000 | E2: =IF(Salary_Calculation[[#This Row],[Source Row]]="","",IF(INDEX(Rider_Input[Calendar Days in Month],Salary_Calculation[[#This Row],[Source Row]])="","",INDEX(Rider_Input[Calendar Days in Month],Salary_Calculation[[#This Row],[Source Row]]))) -> 31 | F2: =IF(Salary_Calculation[[#This Row],[Source Row]]="","",IF(INDEX(Rider_Input[Working Days],Salary_Calculation[[#This Row],[Source Row]])="","",INDEX(Rider_Input[Working Days],Salary_Calculation[[#This Row],[Source Row]]))) -> 8 | G2: =IF(Salary_Calculation[[#This Row],[Source Row]]="","",Std_Orders/Std_Days*N(Salary_Calculation[[#This Row],[Calendar Days]])) -> 465 | H2: =IF(Salary_Calculation[[#This Row],[Source Row]]="","",IF(N(Salary_Calculation[[#This Row],[Calendar Days]])>0,Salary_Calculation[[#This Row],[Monthly Target Orders]]/N(Salary_Calculation[[#This Row],[Calendar Days]])*N(Salary_Calculation[[#This Row],[Working Days]]),0)) -> 120 | I2: =IF(Salary_Calculation[[#This Row],[Source Row]]="","",IF(INDEX(Rider_Input[Completed Orders],Salary_Calculation[[#This Row],[Source Row]])="","",INDEX(Rider_Input[Completed Orders],Salary_Calculation[[#This Row],[Source Row]]))) -> 72 | J2: =IF(Salary_Calculation[[#This Row],[Source Row]]="","",IF(Rate_Method="Fixed rate",Fixed_Rate,IF(N(Salary_Calculation[[#This Row],[Basic Payment]])>0,N(Salary_Calculation[[#This Row],[Basic Payment]])/Std_Orders,0))) -> 4.4444444 | K2: =IF(Salary_Calculation[[#This Row],[Source Row]]="","",MAX(MIN(N(Salary_Calculation[[#This Row],[Completed Orders]]),Salary_Calculation[[#This Row],[Rider Target Orders]]),0)) -> 72 | L2: =IF(Salary_Calculation[[#This Row],[Source Row]]="","",Salary_Calculation[[#This Row],[Orders Counted at Base Rate]]*Salary_Calculation[[#This Row],[Base Order Rate]]) -> 320 | M2: =IF(Salary_Calculation[[#This Row],[Source Row]]="","",MAX(Salary_Calculation[[#This Row],[Rider Target Orders]]-N(Salary_Calculation[[#This Row],[Completed Orders]]),0)) -> 48 | N2: =IF(Salary_Calculation[[#This Row],[Source Row]]="","",Salary_Calculation[[#This Row],[Missing Orders]]*Missing_Rate) -> 336 | O2: =IF(Salary_Calculation[[#This Row],[Source Row]]="","",MAX(N(Salary_Calculation[[#This Row],[Completed Orders]])-Salary_Calculation[[#This Row],[Rider Target Orders]],0)) -> 0 | P2: =IF(Salary_Calculation[[#This Row],[Source Row]]="","",Salary_Calculation[[#This Row],[Extra Orders]]*Extra_Rate) -> 0 | Q2: =IF(Salary_Calculation[[#This Row],[Source Row]]="","",MAX(Salary_Calculation[[#This Row],[Salary Before Other Deductions]],0)) -> 0 | R2: =IF(Salary_Calculation[[#This Row],[Source Row]]="","",N(INDEX(Rider_Input[missed_days_penalty],Salary_Calculation[[#This Row],[Source Row]]))) -> 0 | S2: =IF(Salary_Calculation[[#This Row],[Source Row]]="","",N(INDEX(Rider_Input[Rider Balance / محفظة المندوب],Salary_Calculation[[#This Row],[Source Row]]))) -> 268.09 | T2: =IF(Salary_Calculation[[#This Row],[Source Row]]="","",N(INDEX(Rider_Input[stacking_deduction / خصم الطلبات المتعددة],Salary_Calculation[[#This Row],[Source Row]]))) -> 32 | U2: =IF(Salary_Calculation[[#This Row],[Source Row]]="","",N(INDEX(Rider_Input[Other Deductions],Salary_Calculation[[#This Row],[Source Row]]))) -> 0 | V2: =IF(Salary_Calculation[[#This Row],[Source Row]]="","",N(Salary_Calculation[[#This Row],[missed_days_penalty]])+N(Salary_Calculation[[#This Row],[Rider Balance]])+N(Salary_Calculation[[#This Row],[stacking_deduction]])+N(Salary_Calculation[[#This Row],[Other Deductions]])) -> 300.09 | W2: =IF(Salary_Calculation[[#This Row],[Source Row]]="","",ROUND(MAX(Salary_Calculation[[#This Row],[Gross Salary Before Deductions]]-Salary_Calculation[[#This Row],[Total Deductions]],0),2)) -> 0 | X2: =IF(Salary_Calculation[[#This Row],[Source Row]]="","",ROUND(MAX(Salary_Calculation[[#This Row],[Missing-Order Deduction]]-Salary_Calculation[[#This Row],[Earned Salary]],0),2)) -> 16 | Y2: =IF(Salary_Calculation[[#This Row],[Source Row]]="","",IF(Salary_Calculation[[#This Row],[Exception Reason]]<>"","Review Required",IF(N(Salary_Calculation[[#This Row],[Completed Orders]])=0,"No Orders",IF(AND(Salary_Calculation[[#This Row],[Final Salary]]=0,Salary_Calculation[[#This Row],[Total Amount Due from Rider]]>0),"No Salary – Amount Due from Rider",IF(AND(Salary_Calculation[[#This Row],[Total Deductions]]=0,Salary_Calculation[[#This Row],[Missing-Order Deduction]]=0),"Paid in Full","Paid After Deductions"))))) -> No Salary – Amount Due from Rider | Z2: =IF(Salary_Calculation[[#This Row],[Source Row]]="","",IF(INDEX(Rider_Input[Notes],Salary_Calculation[[#This Row],[Source Row]])="","",INDEX(Rider_Input[Notes],Salary_Calculation[[#This Row],[Source Row]]))) | AA2: =IF(Salary_Calculation[[#This Row],[Source Row]]="","",Salary_Calculation[[#This Row],[Earned Salary]]-Salary_Calculation[[#This Row],[Missing-Order Deduction]]+Salary_Calculation[[#This Row],[Extra-Order Bonus]]) -> -16 | AB2: =IF(Salary_Calculation[[#This Row],[Source Row]]="","",ROUND(Salary_Calculation[[#This Row],[Negative Balance / Amount Due from Rider]]+MAX(Salary_Calculation[[#This Row],[Total Deductions]]-Salary_Calculation[[#This Row],[Gross Salary Before Deductions]],0),2)) -> 316.09 | AC2: =IF(Salary_Calculation[[#This Row],[Source Row]]="","",IF(NOT(ISNUMBER(Salary_Calculation[[#This Row],[Salary Month]])),"Salary month missing; ","")&IF(Salary_Calculation[[#This Row],[Rider ID]]="","Rider ID missing; ","")&IF(Salary_Calculation[[#This Row],[Rider Name]]="","Rider name missing; ","")&IF(NOT(ISNUMBER(Salary_Calculation[[#This Row],[Basic Payment]])),"Basic payment missing; ",IF(Salary_Calculation[[#This Row],[Basic Payment]]<=0,"Basic payment zero or negative; ",""))&IF(NOT(ISNUMBER(Salary_Calculation[[#This Row],[Calendar Days]])),"Calendar days missing; ",IF(OR(Salary_Calculation[[#This Row],[Calendar Days]]<28,Salary_Calculation[[#This Row],[Calendar Days]]>31,Salary_Calculation[[#This Row],[Calendar Days]]<>INT(Salary_Calculation[[#This Row],[Calendar Days]])),"Calendar days not 28/29/30/31; ",IF(ISNUMBER(Salary_Calculation[[#This Row],[Salary Month]]),IF(DAY(EOMONTH(Salary_Calculation[[#This Row],[Salary Month]],0))<>Salary_Calculation[[#This Row],[Calendar Days]],"Calendar days differ from actual days in month; ",""),"")))&IF(NOT(ISNUMBER(Salary_Calculation[[#This Row],[Working Days]])),"Working days missing; ",IF(Salary_Calculation[[#This Row],[Working Days]]<0,"Working days negative; ",IF(AND(ISNUMBER(Salary_Calculation[[#This Row],[Calendar Days]]),Salary_Calculation[[#This Row],[Working Days]]>Salary_Calculation[[#This Row],[Calendar Days]]),"Working days exceed calendar days; ","")))&IF(NOT(ISNUMBER(Salary_Calculation[[#This Row],[Completed Orders]])),"Completed orders missing; ",IF(Salary_Calculation[[#This Row],[Completed Orders]]<0,"Completed orders negative; ",""))&IF(MIN(Salary_Calculation[[#This Row],[missed_days_penalty]],Salary_Calculation[[#This Row],[Rider Balance]],Salary_Calculation[[#This Row],[stacking_deduction]],Salary_Calculation[[#This Row],[Other Deductions]])<0,"Negative deduction entered; ","")&IF(Salary_Calculation[[#This Row],[Rider ID]]="","",IF(COUNTIFS(Rider_Input[Rider ID],Salary_Calculation[[#This Row],[Rider ID]],Rider_Input[Salary Month],Salary_Calculation[[#This Row],[Salary Month]])>1,"Duplicate Rider ID and month; ",""))) | AD2: =IF(Salary_Calculation[[#This Row],[Source Row]]="","",Salary_Calculation[[#This Row],[Rider Target Orders]]*Salary_Calculation[[#This Row],[Base Order Rate]]) -> 533.33333 | AE2: =IF(SUMPRODUCT(--(LEN(INDEX(Rider_Input[#Data],ROW()-ROW(Salary_Calculation[#Headers]),0))>0))=0,"",ROW()-ROW(Salary_Calculation[#Headers])) -> 1
A3: =IF(Salary_Calculation[[#This Row],[Source Row]]="","",IF(INDEX(Rider_Input[Salary Month],Salary_Calculation[[#This Row],[Source Row]])="","",INDEX(Rider_Input[Salary Month],Salary_Calculation[[#This Row],[Source Row]]))) -> 46235 | B3: =IF(Salary_Calculation[[#This Row],[Source Row]]="","",IF(INDEX(Rider_Input[Rider ID],Salary_Calculation[[#This Row],[Source Row]])="","",INDEX(Rider_Input[Rider ID],Salary_Calculation[[#This Row],[Source Row]]))) -> 4849909 | C3: =IF(Salary_Calculation[[#This Row],[Source Row]]="","",IF(INDEX(Rider_Input[Rider Name],Salary_Calculation[[#This Row],[Source Row]])="","",INDEX(Rider_Input[Rider Name],Salary_Calculation[[#This Row],[Source Row]]))) -> Rider 4849909 | D3: =IF(Salary_Calculation[[#This Row],[Source Row]]="","",IF(INDEX(Rider_Input[Basic Payment],Salary_Calculation[[#This Row],[Source Row]])="","",INDEX(Rider_Input[Basic Payment],Salary_Calculation[[#This Row],[Source Row]]))) -> 2000 | E3: =IF(Salary_Calculation[[#This Row],[Source Row]]="","",IF(INDEX(Rider_Input[Calendar Days in Month],Salary_Calculation[[#This Row],[Source Row]])="","",INDEX(Rider_Input[Calendar Days in Month],Salary_Calculation[[#This Row],[Source Row]]))) -> 31 | F3: =IF(Salary_Calculation[[#This Row],[Source Row]]="","",IF(INDEX(Rider_Input[Working Days],Salary_Calculation[[#This Row],[Source Row]])="","",INDEX(Rider_Input[Working Days],Salary_Calculation[[#This Row],[Source Row]]))) -> 11 | G3: =IF(Salary_Calculation[[#This Row],[Source Row]]="","",Std_Orders/Std_Days*N(Salary_Calculation[[#This Row],[Calendar Days]])) -> 465 | H3: =IF(Salary_Calculation[[#This Row],[Source Row]]="","",IF(N(Salary_Calculation[[#This Row],[Calendar Days]])>0,Salary_Calculation[[#This Row],[Monthly Target Orders]]/N(Salary_Calculation[[#This Row],[Calendar Days]])*N(Salary_Calculation[[#This Row],[Working Days]]),0)) -> 165 | I3: =IF(Salary_Calculation[[#This Row],[Source Row]]="","",IF(INDEX(Rider_Input[Completed Orders],Salary_Calculation[[#This Row],[Source Row]])="","",INDEX(Rider_Input[Completed Orders],Salary_Calculation[[#This Row],[Source Row]]))) -> 101 | J3: =IF(Salary_Calculation[[#This Row],[Source Row]]="","",IF(Rate_Method="Fixed rate",Fixed_Rate,IF(N(Salary_Calculation[[#This Row],[Basic Payment]])>0,N(Salary_Calculation[[#This Row],[Basic Payment]])/Std_Orders,0))) -> 4.4444444 | K3: =IF(Salary_Calculation[[#This Row],[Source Row]]="","",MAX(MIN(N(Salary_Calculation[[#This Row],[Completed Orders]]),Salary_Calculation[[#This Row],[Rider Target Orders]]),0)) -> 101 | L3: =IF(Salary_Calculation[[#This Row],[Source Row]]="","",Salary_Calculation[[#This Row],[Orders Counted at Base Rate]]*Salary_Calculation[[#This Row],[Base Order Rate]]) -> 448.88889 | M3: =IF(Salary_Calculation[[#This Row],[Source Row]]="","",MAX(Salary_Calculation[[#This Row],[Rider Target Orders]]-N(Salary_Calculation[[#This Row],[Completed Orders]]),0)) -> 64 | N3: =IF(Salary_Calculation[[#This Row],[Source Row]]="","",Salary_Calculation[[#This Row],[Missing Orders]]*Missing_Rate) -> 448 | O3: =IF(Salary_Calculation[[#This Row],[Source Row]]="","",MAX(N(Salary_Calculation[[#This Row],[Completed Orders]])-Salary_Calculation[[#This Row],[Rider Target Orders]],0)) -> 0 | P3: =IF(Salary_Calculation[[#This Row],[Source Row]]="","",Salary_Calculation[[#This Row],[Extra Orders]]*Extra_Rate) -> 0 | Q3: =IF(Salary_Calculation[[#This Row],[Source Row]]="","",MAX(Salary_Calculation[[#This Row],[Salary Before Other Deductions]],0)) -> 0.88888889 | R3: =IF(Salary_Calculation[[#This Row],[Source Row]]="","",N(INDEX(Rider_Input[missed_days_penalty],Salary_Calculation[[#This Row],[Source Row]]))) -> 0 | S3: =IF(Salary_Calculation[[#This Row],[Source Row]]="","",N(INDEX(Rider_Input[Rider Balance / محفظة المندوب],Salary_Calculation[[#This Row],[Source Row]]))) -> 213.56 | T3: =IF(Salary_Calculation[[#This Row],[Source Row]]="","",N(INDEX(Rider_Input[stacking_deduction / خصم الطلبات المتعددة],Salary_Calculation[[#This Row],[Source Row]]))) -> 20 | U3: =IF(Salary_Calculation[[#This Row],[Source Row]]="","",N(INDEX(Rider_Input[Other Deductions],Salary_Calculation[[#This Row],[Source Row]]))) -> 0 | V3: =IF(Salary_Calculation[[#This Row],[Source Row]]="","",N(Salary_Calculation[[#This Row],[missed_days_penalty]])+N(Salary_Calculation[[#This Row],[Rider Balance]])+N(Salary_Calculation[[#This Row],[stacking_deduction]])+N(Salary_Calculation[[#This Row],[Other Deductions]])) -> 233.56 | W3: =IF(Salary_Calculation[[#This Row],[Source Row]]="","",ROUND(MAX(Salary_Calculation[[#This Row],[Gross Salary Before Deductions]]-Salary_Calculation[[#This Row],[Total Deductions]],0),2)) -> 0 | X3: =IF(Salary_Calculation[[#This Row],[Source Row]]="","",ROUND(MAX(Salary_Calculation[[#This Row],[Missing-Order Deduction]]-Salary_Calculation[[#This Row],[Earned Salary]],0),2)) -> 0 | Y3: =IF(Salary_Calculation[[#This Row],[Source Row]]="","",IF(Salary_Calculation[[#This Row],[Exception Reason]]<>"","Review Required",IF(N(Salary_Calculation[[#This Row],[Completed Orders]])=0,"No Orders",IF(AND(Salary_Calculation[[#This Row],[Final Salary]]=0,Salary_Calculation[[#This Row],[Total Amount Due from Rider]]>0),"No Salary – Amount Due from Rider",IF(AND(Salary_Calculation[[#This Row],[Total Deductions]]=0,Salary_Calculation[[#This Row],[Missing-Order Deduction]]=0),"Paid in Full","Paid After Deductions"))))) -> No Salary – Amount Due from Rider | Z3: =IF(Salary_Calculation[[#This Row],[Source Row]]="","",IF(INDEX(Rider_Input[Notes],Salary_Calculation[[#This Row],[Source Row]])="","",INDEX(Rider_Input[Notes],Salary_Calculation[[#This Row],[Source Row]]))) | AA3: =IF(Salary_Calculation[[#This Row],[Source Row]]="","",Salary_Calculation[[#This Row],[Earned Salary]]-Salary_Calculation[[#This Row],[Missing-Order Deduction]]+Salary_Calculation[[#This Row],[Extra-Order Bonus]]) -> 0.88888889 | AB3: =IF(Salary_Calculation[[#This Row],[Source Row]]="","",ROUND(Salary_Calculation[[#This Row],[Negative Balance / Amount Due from Rider]]+MAX(Salary_Calculation[[#This Row],[Total Deductions]]-Salary_Calculation[[#This Row],[Gross Salary Before Deductions]],0),2)) -> 232.67 | AC3: =IF(Salary_Calculation[[#This Row],[Source Row]]="","",IF(NOT(ISNUMBER(Salary_Calculation[[#This Row],[Salary Month]])),"Salary month missing; ","")&IF(Salary_Calculation[[#This Row],[Rider ID]]="","Rider ID missing; ","")&IF(Salary_Calculation[[#This Row],[Rider Name]]="","Rider name missing; ","")&IF(NOT(ISNUMBER(Salary_Calculation[[#This Row],[Basic Payment]])),"Basic payment missing; ",IF(Salary_Calculation[[#This Row],[Basic Payment]]<=0,"Basic payment zero or negative; ",""))&IF(NOT(ISNUMBER(Salary_Calculation[[#This Row],[Calendar Days]])),"Calendar days missing; ",IF(OR(Salary_Calculation[[#This Row],[Calendar Days]]<28,Salary_Calculation[[#This Row],[Calendar Days]]>31,Salary_Calculation[[#This Row],[Calendar Days]]<>INT(Salary_Calculation[[#This Row],[Calendar Days]])),"Calendar days not 28/29/30/31; ",IF(ISNUMBER(Salary_Calculation[[#This Row],[Salary Month]]),IF(DAY(EOMONTH(Salary_Calculation[[#This Row],[Salary Month]],0))<>Salary_Calculation[[#This Row],[Calendar Days]],"Calendar days differ from actual days in month; ",""),"")))&IF(NOT(ISNUMBER(Salary_Calculation[[#This Row],[Working Days]])),"Working days missing; ",IF(Salary_Calculation[[#This Row],[Working Days]]<0,"Working days negative; ",IF(AND(ISNUMBER(Salary_Calculation[[#This Row],[Calendar Days]]),Salary_Calculation[[#This Row],[Working Days]]>Salary_Calculation[[#This Row],[Calendar Days]]),"Working days exceed calendar days; ","")))&IF(NOT(ISNUMBER(Salary_Calculation[[#This Row],[Completed Orders]])),"Completed orders missing; ",IF(Salary_Calculation[[#This Row],[Completed Orders]]<0,"Completed orders negative; ",""))&IF(MIN(Salary_Calculation[[#This Row],[missed_days_penalty]],Salary_Calculation[[#This Row],[Rider Balance]],Salary_Calculation[[#This Row],[stacking_deduction]],Salary_Calculation[[#This Row],[Other Deductions]])<0,"Negative deduction entered; ","")&IF(Salary_Calculation[[#This Row],[Rider ID]]="","",IF(COUNTIFS(Rider_Input[Rider ID],Salary_Calculation[[#This Row],[Rider ID]],Rider_Input[Salary Month],Salary_Calculation[[#This Row],[Salary Month]])>1,"Duplicate Rider ID and month; ",""))) | AD3: =IF(Salary_Calculation[[#This Row],[Source Row]]="","",Salary_Calculation[[#This Row],[Rider Target Orders]]*Salary_Calculation[[#This Row],[Base Order Rate]]) -> 733.33333 | AE3: =IF(SUMPRODUCT(--(LEN(INDEX(Rider_Input[#Data],ROW()-ROW(Salary_Calculation[#Headers]),0))>0))=0,"",ROW()-ROW(Salary_Calculation[#Headers])) -> 2
A4: =IF(Salary_Calculation[[#This Row],[Source Row]]="","",IF(INDEX(Rider_Input[Salary Month],Salary_Calculation[[#This Row],[Source Row]])="","",INDEX(Rider_Input[Salary Month],Salary_Calculation[[#This Row],[Source Row]]))) -> 46235 | B4: =IF(Salary_Calculation[[#This Row],[Source Row]]="","",IF(INDEX(Rider_Input[Rider ID],Salary_Calculation[[#This Row],[Source Row]])="","",INDEX(Rider_Input[Rider ID],Salary_Calculation[[#This Row],[Source Row]]))) -> 4849222 | C4: =IF(Salary_Calculation[[#This Row],[Source Row]]="","",IF(INDEX(Rider_Input[Rider Name],Salary_Calculation[[#This Row],[Source Row]])="","",INDEX(Rider_Input[Rider Name],Salary_Calculation[[#This Row],[Source Row]]))) -> Rider 4849222 | D4: =IF(Salary_Calculation[[#This Row],[Source Row]]="","",IF(INDEX(Rider_Input[Basic Payment],Salary_Calculation[[#This Row],[Source Row]])="","",INDEX(Rider_Input[Basic Payment],Salary_Calculation[[#This Row],[Source Row]]))) -> 2000 | E4: =IF(Salary_Calculation[[#This Row],[Source Row]]="","",IF(INDEX(Rider_Input[Calendar Days in Month],Salary_Calculation[[#This Row],[Source Row]])="","",INDEX(Rider_Input[Calendar Days in Month],Salary_Calculation[[#This Row],[Source Row]]))) -> 31 | F4: =IF(Salary_Calculation[[#This Row],[Source Row]]="","",IF(INDEX(Rider_Input[Working Days],Salary_Calculation[[#This Row],[Source Row]])="","",INDEX(Rider_Input[Working Days],Salary_Calculation[[#This Row],[Source Row]]))) -> 11 | G4: =IF(Salary_Calculation[[#This Row],[Source Row]]="","",Std_Orders/Std_Days*N(Salary_Calculation[[#This Row],[Calendar Days]])) -> 465 | H4: =IF(Salary_Calculation[[#This Row],[Source Row]]="","",IF(N(Salary_Calculation[[#This Row],[Calendar Days]])>0,Salary_Calculation[[#This Row],[Monthly Target Orders]]/N(Salary_Calculation[[#This Row],[Calendar Days]])*N(Salary_Calculation[[#This Row],[Working Days]]),0)) -> 165 | I4: =IF(Salary_Calculation[[#This Row],[Source Row]]="","",IF(INDEX(Rider_Input[Completed Orders],Salary_Calculation[[#This Row],[Source Row]])="","",INDEX(Rider_Input[Completed Orders],Salary_Calculation[[#This Row],[Source Row]]))) -> 105 | J4: =IF(Salary_Calculation[[#This Row],[Source Row]]="","",IF(Rate_Method="Fixed rate",Fixed_Rate,IF(N(Salary_Calculation[[#This Row],[Basic Payment]])>0,N(Salary_Calculation[[#This Row],[Basic Payment]])/Std_Orders,0))) -> 4.4444444 | K4: =IF(Salary_Calculation[[#This Row],[Source Row]]="","",MAX(MIN(N(Salary_Calculation[[#This Row],[Completed Orders]]),Salary_Calculation[[#This Row],[Rider Target Orders]]),0)) -> 105 | L4: =IF(Salary_Calculation[[#This Row],[Source Row]]="","",Salary_Calculation[[#This Row],[Orders Counted at Base Rate]]*Salary_Calculation[[#This Row],[Base Order Rate]]) -> 466.66667 | M4: =IF(Salary_Calculation[[#This Row],[Source Row]]="","",MAX(Salary_Calculation[[#This Row],[Rider Target Orders]]-N(Salary_Calculation[[#This Row],[Completed Orders]]),0)) -> 60 | N4: =IF(Salary_Calculation[[#This Row],[Source Row]]="","",Salary_Calculation[[#This Row],[Missing Orders]]*Missing_Rate) -> 420 | O4: =IF(Salary_Calculation[[#This Row],[Source Row]]="","",MAX(N(Salary_Calculation[[#This Row],[Completed Orders]])-Salary_Calculation[[#This Row],[Rider Target Orders]],0)) -> 0 | P4: =IF(Salary_Calculation[[#This Row],[Source Row]]="","",Salary_Calculation[[#This Row],[Extra Orders]]*Extra_Rate) -> 0 | Q4: =IF(Salary_Calculation[[#This Row],[Source Row]]="","",MAX(Salary_Calculation[[#This Row],[Salary Before Other Deductions]],0)) -> 46.666667 | R4: =IF(Salary_Calculation[[#This Row],[Source Row]]="","",N(INDEX(Rider_Input[missed_days_penalty],Salary_Calculation[[#This Row],[Source Row]]))) -> 0 | S4: =IF(Salary_Calculation[[#This Row],[Source Row]]="","",N(INDEX(Rider_Input[Rider Balance / محفظة المندوب],Salary_Calculation[[#This Row],[Source Row]]))) -> 190.77 | T4: =IF(Salary_Calculation[[#This Row],[Source Row]]="","",N(INDEX(Rider_Input[stacking_deduction / خصم الطلبات المتعددة],Salary_Calculation[[#This Row],[Source Row]]))) -> 20 | U4: =IF(Salary_Calculation[[#This Row],[Source Row]]="","",N(INDEX(Rider_Input[Other Deductions],Salary_Calculation[[#This Row],[Source Row]]))) -> 0 | V4: =IF(Salary_Calculation[[#This Row],[Source Row]]="","",N(Salary_Calculation[[#This Row],[missed_days_penalty]])+N(Salary_Calculation[[#This Row],[Rider Balance]])+N(Salary_Calculation[[#This Row],[stacking_deduction]])+N(Salary_Calculation[[#This Row],[Other Deductions]])) -> 210.77 | W4: =IF(Salary_Calculation[[#This Row],[Source Row]]="","",ROUND(MAX(Salary_Calculation[[#This Row],[Gross Salary Before Deductions]]-Salary_Calculation[[#This Row],[Total Deductions]],0),2)) -> 0 | X4: =IF(Salary_Calculation[[#This Row],[Source Row]]="","",ROUND(MAX(Salary_Calculation[[#This Row],[Missing-Order Deduction]]-Salary_Calculation[[#This Row],[Earned Salary]],0),2)) -> 0 | Y4: =IF(Salary_Calculation[[#This Row],[Source Row]]="","",IF(Salary_Calculation[[#This Row],[Exception Reason]]<>"","Review Required",IF(N(Salary_Calculation[[#This Row],[Completed Orders]])=0,"No Orders",IF(AND(Salary_Calculation[[#This Row],[Final Salary]]=0,Salary_Calculation[[#This Row],[Total Amount Due from Rider]]>0),"No Salary – Amount Due from Rider",IF(AND(Salary_Calculation[[#This Row],[Total Deductions]]=0,Salary_Calculation[[#This Row],[Missing-Order Deduction]]=0),"Paid in Full","Paid After Deductions"))))) -> No Salary – Amount Due from Rider | Z4: =IF(Salary_Calculation[[#This Row],[Source Row]]="","",IF(INDEX(Rider_Input[Notes],Salary_Calculation[[#This Row],[Source Row]])="","",INDEX(Rider_Input[Notes],Salary_Calculation[[#This Row],[Source Row]]))) | AA4: =IF(Salary_Calculation[[#This Row],[Source Row]]="","",Salary_Calculation[[#This Row],[Earned Salary]]-Salary_Calculation[[#This Row],[Missing-Order Deduction]]+Salary_Calculation[[#This Row],[Extra-Order Bonus]]) -> 46.666667 | AB4: =IF(Salary_Calculation[[#This Row],[Source Row]]="","",ROUND(Salary_Calculation[[#This Row],[Negative Balance / Amount Due from Rider]]+MAX(Salary_Calculation[[#This Row],[Total Deductions]]-Salary_Calculation[[#This Row],[Gross Salary Before Deductions]],0),2)) -> 164.1 | AC4: =IF(Salary_Calculation[[#This Row],[Source Row]]="","",IF(NOT(ISNUMBER(Salary_Calculation[[#This Row],[Salary Month]])),"Salary month missing; ","")&IF(Salary_Calculation[[#This Row],[Rider ID]]="","Rider ID missing; ","")&IF(Salary_Calculation[[#This Row],[Rider Name]]="","Rider name missing; ","")&IF(NOT(ISNUMBER(Salary_Calculation[[#This Row],[Basic Payment]])),"Basic payment missing; ",IF(Salary_Calculation[[#This Row],[Basic Payment]]<=0,"Basic payment zero or negative; ",""))&IF(NOT(ISNUMBER(Salary_Calculation[[#This Row],[Calendar Days]])),"Calendar days missing; ",IF(OR(Salary_Calculation[[#This Row],[Calendar Days]]<28,Salary_Calculation[[#This Row],[Calendar Days]]>31,Salary_Calculation[[#This Row],[Calendar Days]]<>INT(Salary_Calculation[[#This Row],[Calendar Days]])),"Calendar days not 28/29/30/31; ",IF(ISNUMBER(Salary_Calculation[[#This Row],[Salary Month]]),IF(DAY(EOMONTH(Salary_Calculation[[#This Row],[Salary Month]],0))<>Salary_Calculation[[#This Row],[Calendar Days]],"Calendar days differ from actual days in month; ",""),"")))&IF(NOT(ISNUMBER(Salary_Calculation[[#This Row],[Working Days]])),"Working days missing; ",IF(Salary_Calculation[[#This Row],[Working Days]]<0,"Working days negative; ",IF(AND(ISNUMBER(Salary_Calculation[[#This Row],[Calendar Days]]),Salary_Calculation[[#This Row],[Working Days]]>Salary_Calculation[[#This Row],[Calendar Days]]),"Working days exceed calendar days; ","")))&IF(NOT(ISNUMBER(Salary_Calculation[[#This Row],[Completed Orders]])),"Completed orders missing; ",IF(Salary_Calculation[[#This Row],[Completed Orders]]<0,"Completed orders negative; ",""))&IF(MIN(Salary_Calculation[[#This Row],[missed_days_penalty]],Salary_Calculation[[#This Row],[Rider Balance]],Salary_Calculation[[#This Row],[stacking_deduction]],Salary_Calculation[[#This Row],[Other Deductions]])<0,"Negative deduction entered; ","")&IF(Salary_Calculation[[#This Row],[Rider ID]]="","",IF(COUNTIFS(Rider_Input[Rider ID],Salary_Calculation[[#This Row],[Rider ID]],Rider_Input[Salary Month],Salary_Calculation[[#This Row],[Salary Month]])>1,"Duplicate Rider ID and month; ",""))) | AD4: =IF(Salary_Calculation[[#This Row],[Source Row]]="","",Salary_Calculation[[#This Row],[Rider Target Orders]]*Salary_Calculation[[#This Row],[Base Order Rate]]) -> 733.33333 | AE4: =IF(SUMPRODUCT(--(LEN(INDEX(Rider_Input[#Data],ROW()-ROW(Salary_Calculation[#Headers]),0))>0))=0,"",ROW()-ROW(Salary_Calculation[#Headers])) -> 3
A5: =IF(Salary_Calculation[[#This Row],[Source Row]]="","",IF(INDEX(Rider_Input[Salary Month],Salary_Calculation[[#This Row],[Source Row]])="","",INDEX(Rider_Input[Salary Month],Salary_Calculation[[#This Row],[Source Row]]))) -> 46235 | B5: =IF(Salary_Calculation[[#This Row],[Source Row]]="","",IF(INDEX(Rider_Input[Rider ID],Salary_Calculation[[#This Row],[Source Row]])="","",INDEX(Rider_Input[Rider ID],Salary_Calculation[[#This Row],[Source Row]]))) -> 4844480 | C5: =IF(Salary_Calculation[[#This Row],[Source Row]]="","",IF(INDEX(Rider_Input[Rider Name],Salary_Calculation[[#This Row],[Source Row]])="","",INDEX(Rider_Input[Rider Name],Salary_Calculation[[#This Row],[Source Row]]))) -> Rider 4844480 | D5: =IF(Salary_Calculation[[#This Row],[Source Row]]="","",IF(INDEX(Rider_Input[Basic Payment],Salary_Calculation[[#This Row],[Source Row]])="","",INDEX(Rider_Input[Basic Payment],Salary_Calculation[[#This Row],[Source Row]]))) -> 2000 | E5: =IF(Salary_Calculation[[#This Row],[Source Row]]="","",IF(INDEX(Rider_Input[Calendar Days in Month],Salary_Calculation[[#This Row],[Source Row]])="","",INDEX(Rider_Input[Calendar Days in Month],Salary_Calculation[[#This Row],[Source Row]]))) -> 31 | F5: =IF(Salary_Calculation[[#This Row],[Source Row]]="","",IF(INDEX(Rider_Input[Working Days],Salary_Calculation[[#This Row],[Source Row]])="","",INDEX(Rider_Input[Working Days],Salary_Calculation[[#This Row],[Source Row]]))) -> 12 | G5: =IF(Salary_Calculation[[#This Row],[Source Row]]="","",Std_Orders/Std_Days*N(Salary_Calculation[[#This Row],[Calendar Days]])) -> 465 | H5: =IF(Salary_Calculation[[#This Row],[Source Row]]="","",IF(N(Salary_Calculation[[#This Row],[Calendar Days]])>0,Salary_Calculation[[#This Row],[Monthly Target Orders]]/N(Salary_Calculation[[#This Row],[Calendar Days]])*N(Salary_Calculation[[#This Row],[Working Days]]),0)) -> 180 | I5: =IF(Salary_Calculation[[#This Row],[Source Row]]="","",IF(INDEX(Rider_Input[Completed Orders],Salary_Calculation[[#This Row],[Source Row]])="","",INDEX(Rider_Input[Completed Orders],Salary_Calculation[[#This Row],[Source Row]]))) -> 150 | J5: =IF(Salary_Calculation[[#This Row],[Source Row]]="","",IF(Rate_Method="Fixed rate",Fixed_Rate,IF(N(Salary_Calculation[[#This Row],[Basic Payment]])>0,N(Salary_Calculation[[#This Row],[Basic Payment]])/Std_Orders,0))) -> 4.4444444 | K5: =IF(Salary_Calculation[[#This Row],[Source Row]]="","",MAX(MIN(N(Salary_Calculation[[#This Row],[Completed Orders]]),Salary_Calculation[[#This Row],[Rider Target Orders]]),0)) -> 150 | L5: =IF(Salary_Calculation[[#This Row],[Source Row]]="","",Salary_Calculation[[#This Row],[Orders Counted at Base Rate]]*Salary_Calculation[[#This Row],[Base Order Rate]]) -> 666.66667 | M5: =IF(Salary_Calculation[[#This Row],[Source Row]]="","",MAX(Salary_Calculation[[#This Row],[Rider Target Orders]]-N(Salary_Calculation[[#This Row],[Completed Orders]]),0)) -> 30 | N5: =IF(Salary_Calculation[[#This Row],[Source Row]]="","",Salary_Calculation[[#This Row],[Missing Orders]]*Missing_Rate) -> 210 | O5: =IF(Salary_Calculation[[#This Row],[Source Row]]="","",MAX(N(Salary_Calculation[[#This Row],[Completed Orders]])-Salary_Calculation[[#This Row],[Rider Target Orders]],0)) -> 0 | P5: =IF(Salary_Calculation[[#This Row],[Source Row]]="","",Salary_Calculation[[#This Row],[Extra Orders]]*Extra_Rate) -> 0 | Q5: =IF(Salary_Calculation[[#This Row],[Source Row]]="","",MAX(Salary_Calculation[[#This Row],[Salary Before Other Deductions]],0)) -> 456.66667 | R5: =IF(Salary_Calculation[[#This Row],[Source Row]]="","",N(INDEX(Rider_Input[missed_days_penalty],Salary_Calculation[[#This Row],[Source Row]]))) -> 0 | S5: =IF(Salary_Calculation[[#This Row],[Source Row]]="","",N(INDEX(Rider_Input[Rider Balance / محفظة المندوب],Salary_Calculation[[#This Row],[Source Row]]))) -> 57.17 | T5: =IF(Salary_Calculation[[#This Row],[Source Row]]="","",N(INDEX(Rider_Input[stacking_deduction / خصم الطلبات المتعددة],Salary_Calculation[[#This Row],[Source Row]]))) -> 36 | U5: =IF(Salary_Calculation[[#This Row],[Source Row]]="","",N(INDEX(Rider_Input[Other Deductions],Salary_Calculation[[#This Row],[Source Row]]))) -> 0 | V5: =IF(Salary_Calculation[[#This Row],[Source Row]]="","",N(Salary_Calculation[[#This Row],[missed_days_penalty]])+N(Salary_Calculation[[#This Row],[Rider Balance]])+N(Salary_Calculation[[#This Row],[stacking_deduction]])+N(Salary_Calculation[[#This Row],[Other Deductions]])) -> 93.17 | W5: =IF(Salary_Calculation[[#This Row],[Source Row]]="","",ROUND(MAX(Salary_Calculation[[#This Row],[Gross Salary Before Deductions]]-Salary_Calculation[[#This Row],[Total Deductions]],0),2)) -> 363.5 | X5: =IF(Salary_Calculation[[#This Row],[Source Row]]="","",ROUND(MAX(Salary_Calculation[[#This Row],[Missing-Order Deduction]]-Salary_Calculation[[#This Row],[Earned Salary]],0),2)) -> 0 | Y5: =IF(Salary_Calculation[[#This Row],[Source Row]]="","",IF(Salary_Calculation[[#This Row],[Exception Reason]]<>"","Review Required",IF(N(Salary_Calculation[[#This Row],[Completed Orders]])=0,"No Orders",IF(AND(Salary_Calculation[[#This Row],[Final Salary]]=0,Salary_Calculation[[#This Row],[Total Amount Due from Rider]]>0),"No Salary – Amount Due from Rider",IF(AND(Salary_Calculation[[#This Row],[Total Deductions]]=0,Salary_Calculation[[#This Row],[Missing-Order Deduction]]=0),"Paid in Full","Paid After Deductions"))))) -> Paid After Deductions | Z5: =IF(Salary_Calculation[[#This Row],[Source Row]]="","",IF(INDEX(Rider_Input[Notes],Salary_Calculation[[#This Row],[Source Row]])="","",INDEX(Rider_Input[Notes],Salary_Calculation[[#This Row],[Source Row]]))) | AA5: =IF(Salary_Calculation[[#This Row],[Source Row]]="","",Salary_Calculation[[#This Row],[Earned Salary]]-Salary_Calculation[[#This Row],[Missing-Order Deduction]]+Salary_Calculation[[#This Row],[Extra-Order Bonus]]) -> 456.66667 | AB5: =IF(Salary_Calculation[[#This Row],[Source Row]]="","",ROUND(Salary_Calculation[[#This Row],[Negative Balance / Amount Due from Rider]]+MAX(Salary_Calculation[[#This Row],[Total Deductions]]-Salary_Calculation[[#This Row],[Gross Salary Before Deductions]],0),2)) -> 0 | AC5: =IF(Salary_Calculation[[#This Row],[Source Row]]="","",IF(NOT(ISNUMBER(Salary_Calculation[[#This Row],[Salary Month]])),"Salary month missing; ","")&IF(Salary_Calculation[[#This Row],[Rider ID]]="","Rider ID missing; ","")&IF(Salary_Calculation[[#This Row],[Rider Name]]="","Rider name missing; ","")&IF(NOT(ISNUMBER(Salary_Calculation[[#This Row],[Basic Payment]])),"Basic payment missing; ",IF(Salary_Calculation[[#This Row],[Basic Payment]]<=0,"Basic payment zero or negative; ",""))&IF(NOT(ISNUMBER(Salary_Calculation[[#This Row],[Calendar Days]])),"Calendar days missing; ",IF(OR(Salary_Calculation[[#This Row],[Calendar Days]]<28,Salary_Calculation[[#This Row],[Calendar Days]]>31,Salary_Calculation[[#This Row],[Calendar Days]]<>INT(Salary_Calculation[[#This Row],[Calendar Days]])),"Calendar days not 28/29/30/31; ",IF(ISNUMBER(Salary_Calculation[[#This Row],[Salary Month]]),IF(DAY(EOMONTH(Salary_Calculation[[#This Row],[Salary Month]],0))<>Salary_Calculation[[#This Row],[Calendar Days]],"Calendar days differ from actual days in month; ",""),"")))&IF(NOT(ISNUMBER(Salary_Calculation[[#This Row],[Working Days]])),"Working days missing; ",IF(Salary_Calculation[[#This Row],[Working Days]]<0,"Working days negative; ",IF(AND(ISNUMBER(Salary_Calculation[[#This Row],[Calendar Days]]),Salary_Calculation[[#This Row],[Working Days]]>Salary_Calculation[[#This Row],[Calendar Days]]),"Working days exceed calendar days; ","")))&IF(NOT(ISNUMBER(Salary_Calculation[[#This Row],[Completed Orders]])),"Completed orders missing; ",IF(Salary_Calculation[[#This Row],[Completed Orders]]<0,"Completed orders negative; ",""))&IF(MIN(Salary_Calculation[[#This Row],[missed_days_penalty]],Salary_Calculation[[#This Row],[Rider Balance]],Salary_Calculation[[#This Row],[stacking_deduction]],Salary_Calculation[[#This Row],[Other Deductions]])<0,"Negative deduction entered; ","")&IF(Salary_Calculation[[#This Row],[Rider ID]]="","",IF(COUNTIFS(Rider_Input[Rider ID],Salary_Calculation[[#This Row],[Rider ID]],Rider_Input[Salary Month],Salary_Calculation[[#This Row],[Salary Month]])>1,"Duplicate Rider ID and month; ",""))) | AD5: =IF(Salary_Calculation[[#This Row],[Source Row]]="","",Salary_Calculation[[#This Row],[Rider Target Orders]]*Salary_Calculation[[#This Row],[Base Order Rate]]) -> 800 | AE5: =IF(SUMPRODUCT(--(LEN(INDEX(Rider_Input[#Data],ROW()-ROW(Salary_Calculation[#Headers]),0))>0))=0,"",ROW()-ROW(Salary_Calculation[#Headers])) -> 4
A6: =IF(Salary_Calculation[[#This Row],[Source Row]]="","",IF(INDEX(Rider_Input[Salary Month],Salary_Calculation[[#This Row],[Source Row]])="","",INDEX(Rider_Input[Salary Month],Salary_Calculation[[#This Row],[Source Row]]))) -> 46235 | B6: =IF(Salary_Calculation[[#This Row],[Source Row]]="","",IF(INDEX(Rider_Input[Rider ID],Salary_Calculation[[#This Row],[Source Row]])="","",INDEX(Rider_Input[Rider ID],Salary_Calculation[[#This Row],[Source Row]]))) -> 4838478 | C6: =IF(Salary_Calculation[[#This Row],[Source Row]]="","",IF(INDEX(Rider_Input[Rider Name],Salary_Calculation[[#This Row],[Source Row]])="","",INDEX(Rider_Input[Rider Name],Salary_Calculation[[#This Row],[Source Row]]))) -> Rider 4838478 | D6: =IF(Salary_Calculation[[#This Row],[Source Row]]="","",IF(INDEX(Rider_Input[Basic Payment],Salary_Calculation[[#This Row],[Source Row]])="","",INDEX(Rider_Input[Basic Payment],Salary_Calculation[[#This Row],[Source Row]]))) -> 2000 | E6: =IF(Salary_Calculation[[#This Row],[Source Row]]="","",IF(INDEX(Rider_Input[Calendar Days in Month],Salary_Calculation[[#This Row],[Source Row]])="","",INDEX(Rider_Input[Calendar Days in Month],Salary_Calculation[[#This Row],[Source Row]]))) -> 31 | F6: =IF(Salary_Calculation[[#This Row],[Source Row]]="","",IF(INDEX(Rider_Input[Working Days],Salary_Calculation[[#This Row],[Source Row]])="","",INDEX(Rider_Input[Working Days],Salary_Calculation[[#This Row],[Source Row]]))) -> 14 | G6: =IF(Salary_Calculation[[#This Row],[Source Row]]="","",Std_Orders/Std_Days*N(Salary_Calculation[[#This Row],[Calendar Days]])) -> 465 | H6: =IF(Salary_Calculation[[#This Row],[Source Row]]="","",IF(N(Salary_Calculation[[#This Row],[Calendar Days]])>0,Salary_Calculation[[#This Row],[Monthly Target Orders]]/N(Salary_Calculation[[#This Row],[Calendar Days]])*N(Salary_Calculation[[#This Row],[Working Days]]),0)) -> 210 | I6: =IF(Salary_Calculation[[#This Row],[Source Row]]="","",IF(INDEX(Rider_Input[Completed Orders],Salary_Calculation[[#This Row],[Source Row]])="","",INDEX(Rider_Input[Completed Orders],Salary_Calculation[[#This Row],[Source Row]]))) -> 171 | J6: =IF(Salary_Calculation[[#This Row],[Source Row]]="","",IF(Rate_Method="Fixed rate",Fixed_Rate,IF(N(Salary_Calculation[[#This Row],[Basic Payment]])>0,N(Salary_Calculation[[#This Row],[Basic Payment]])/Std_Orders,0))) -> 4.4444444 | K6: =IF(Salary_Calculation[[#This Row],[Source Row]]="","",MAX(MIN(N(Salary_Calculation[[#This Row],[Completed Orders]]),Salary_Calculation[[#This Row],[Rider Target Orders]]),0)) -> 171 | L6: =IF(Salary_Calculation[[#This Row],[Source Row]]="","",Salary_Calculation[[#This Row],[Orders Counted at Base Rate]]*Salary_Calculation[[#This Row],[Base Order Rate]]) -> 760 | M6: =IF(Salary_Calculation[[#This Row],[Source Row]]="","",MAX(Salary_Calculation[[#This Row],[Rider Target Orders]]-N(Salary_Calculation[[#This Row],[Completed Orders]]),0)) -> 39 | N6: =IF(Salary_Calculation[[#This Row],[Source Row]]="","",Salary_Calculation[[#This Row],[Missing Orders]]*Missing_Rate) -> 273 | O6: =IF(Salary_Calculation[[#This Row],[Source Row]]="","",MAX(N(Salary_Calculation[[#This Row],[Completed Orders]])-Salary_Calculation[[#This Row],[Rider Target Orders]],0)) -> 0 | P6: =IF(Salary_Calculation[[#This Row],[Source Row]]="","",Salary_Calculation[[#This Row],[Extra Orders]]*Extra_Rate) -> 0 | Q6: =IF(Salary_Calculation[[#This Row],[Source Row]]="","",MAX(Salary_Calculation[[#This Row],[Salary Before Other Deductions]],0)) -> 487 | R6: =IF(Salary_Calculation[[#This Row],[Source Row]]="","",N(INDEX(Rider_Input[missed_days_penalty],Salary_Calculation[[#This Row],[Source Row]]))) -> 0 | S6: =IF(Salary_Calculation[[#This Row],[Source Row]]="","",N(INDEX(Rider_Input[Rider Balance / محفظة المندوب],Salary_Calculation[[#This Row],[Source Row]]))) -> 200.44 | T6: =IF(Salary_Calculation[[#This Row],[Source Row]]="","",N(INDEX(Rider_Input[stacking_deduction / خصم الطلبات المتعددة],Salary_Calculation[[#This Row],[Source Row]]))) -> 36 | U6: =IF(Salary_Calculation[[#This Row],[Source Row]]="","",N(INDEX(Rider_Input[Other Deductions],Salary_Calculation[[#This Row],[Source Row]]))) -> 0 | V6: =IF(Salary_Calculation[[#This Row],[Source Row]]="","",N(Salary_Calculation[[#This Row],[missed_days_penalty]])+N(Salary_Calculation[[#This Row],[Rider Balance]])+N(Salary_Calculation[[#This Row],[stacking_deduction]])+N(Salary_Calculation[[#This Row],[Other Deductions]])) -> 236.44 | W6: =IF(Salary_Calculation[[#This Row],[Source Row]]="","",ROUND(MAX(Salary_Calculation[[#This Row],[Gross Salary Before Deductions]]-Salary_Calculation[[#This Row],[Total Deductions]],0),2)) -> 250.56 | X6: =IF(Salary_Calculation[[#This Row],[Source Row]]="","",ROUND(MAX(Salary_Calculation[[#This Row],[Missing-Order Deduction]]-Salary_Calculation[[#This Row],[Earned Salary]],0),2)) -> 0 | Y6: =IF(Salary_Calculation[[#This Row],[Source Row]]="","",IF(Salary_Calculation[[#This Row],[Exception Reason]]<>"","Review Required",IF(N(Salary_Calculation[[#This Row],[Completed Orders]])=0,"No Orders",IF(AND(Salary_Calculation[[#This Row],[Final Salary]]=0,Salary_Calculation[[#This Row],[Total Amount Due from Rider]]>0),"No Salary – Amount Due from Rider",IF(AND(Salary_Calculation[[#This Row],[Total Deductions]]=0,Salary_Calculation[[#This Row],[Missing-Order Deduction]]=0),"Paid in Full","Paid After Deductions"))))) -> Paid After Deductions | Z6: =IF(Salary_Calculation[[#This Row],[Source Row]]="","",IF(INDEX(Rider_Input[Notes],Salary_Calculation[[#This Row],[Source Row]])="","",INDEX(Rider_Input[Notes],Salary_Calculation[[#This Row],[Source Row]]))) | AA6: =IF(Salary_Calculation[[#This Row],[Source Row]]="","",Salary_Calculation[[#This Row],[Earned Salary]]-Salary_Calculation[[#This Row],[Missing-Order Deduction]]+Salary_Calculation[[#This Row],[Extra-Order Bonus]]) -> 487 | AB6: =IF(Salary_Calculation[[#This Row],[Source Row]]="","",ROUND(Salary_Calculation[[#This Row],[Negative Balance / Amount Due from Rider]]+MAX(Salary_Calculation[[#This Row],[Total Deductions]]-Salary_Calculation[[#This Row],[Gross Salary Before Deductions]],0),2)) -> 0 | AC6: =IF(Salary_Calculation[[#This Row],[Source Row]]="","",IF(NOT(ISNUMBER(Salary_Calculation[[#This Row],[Salary Month]])),"Salary month missing; ","")&IF(Salary_Calculation[[#This Row],[Rider ID]]="","Rider ID missing; ","")&IF(Salary_Calculation[[#This Row],[Rider Name]]="","Rider name missing; ","")&IF(NOT(ISNUMBER(Salary_Calculation[[#This Row],[Basic Payment]])),"Basic payment missing; ",IF(Salary_Calculation[[#This Row],[Basic Payment]]<=0,"Basic payment zero or negative; ",""))&IF(NOT(ISNUMBER(Salary_Calculation[[#This Row],[Calendar Days]])),"Calendar days missing; ",IF(OR(Salary_Calculation[[#This Row],[Calendar Days]]<28,Salary_Calculation[[#This Row],[Calendar Days]]>31,Salary_Calculation[[#This Row],[Calendar Days]]<>INT(Salary_Calculation[[#This Row],[Calendar Days]])),"Calendar days not 28/29/30/31; ",IF(ISNUMBER(Salary_Calculation[[#This Row],[Salary Month]]),IF(DAY(EOMONTH(Salary_Calculation[[#This Row],[Salary Month]],0))<>Salary_Calculation[[#This Row],[Calendar Days]],"Calendar days differ from actual days in month; ",""),"")))&IF(NOT(ISNUMBER(Salary_Calculation[[#This Row],[Working Days]])),"Working days missing; ",IF(Salary_Calculation[[#This Row],[Working Days]]<0,"Working days negative; ",IF(AND(ISNUMBER(Salary_Calculation[[#This Row],[Calendar Days]]),Salary_Calculation[[#This Row],[Working Days]]>Salary_Calculation[[#This Row],[Calendar Days]]),"Working days exceed calendar days; ","")))&IF(NOT(ISNUMBER(Salary_Calculation[[#This Row],[Completed Orders]])),"Completed orders missing; ",IF(Salary_Calculation[[#This Row],[Completed Orders]]<0,"Completed orders negative; ",""))&IF(MIN(Salary_Calculation[[#This Row],[missed_days_penalty]],Salary_Calculation[[#This Row],[Rider Balance]],Salary_Calculation[[#This Row],[stacking_deduction]],Salary_Calculation[[#This Row],[Other Deductions]])<0,"Negative deduction entered; ","")&IF(Salary_Calculation[[#This Row],[Rider ID]]="","",IF(COUNTIFS(Rider_Input[Rider ID],Salary_Calculation[[#This Row],[Rider ID]],Rider_Input[Salary Month],Salary_Calculation[[#This Row],[Salary Month]])>1,"Duplicate Rider ID and month; ",""))) | AD6: =IF(Salary_Calculation[[#This Row],[Source Row]]="","",Salary_Calculation[[#This Row],[Rider Target Orders]]*Salary_Calculation[[#This Row],[Base Order Rate]]) -> 933.33333 | AE6: =IF(SUMPRODUCT(--(LEN(INDEX(Rider_Input[#Data],ROW()-ROW(Salary_Calculation[#Headers]),0))>0))=0,"",ROW()-ROW(Salary_Calculation[#Headers])) -> 5
A7: =IF(Salary_Calculation[[#This Row],[Source Row]]="","",IF(INDEX(Rider_Input[Salary Month],Salary_Calculation[[#This Row],[Source Row]])="","",INDEX(Rider_Input[Salary Month],Salary_Calculation[[#This Row],[Source Row]]))) -> 46235 | B7: =IF(Salary_Calculation[[#This Row],[Source Row]]="","",IF(INDEX(Rider_Input[Rider ID],Salary_Calculation[[#This Row],[Source Row]])="","",INDEX(Rider_Input[Rider ID],Salary_Calculation[[#This Row],[Source Row]]))) -> 4838471 | C7: =IF(Salary_Calculation[[#This Row],[Source Row]]="","",IF(INDEX(Rider_Input[Rider Name],Salary_Calculation[[#This Row],[Source Row]])="","",INDEX(Rider_Input[Rider Name],Salary_Calculation[[#This Row],[Source Row]]))) -> Rider 4838471 | D7: =IF(Salary_Calculation[[#This Row],[Source Row]]="","",IF(INDEX(Rider_Input[Basic Payment],Salary_Calculation[[#This Row],[Source Row]])="","",INDEX(Rider_Input[Basic Payment],Salary_Calculation[[#This Row],[Source Row]]))) -> 2000 | E7: =IF(Salary_Calculation[[#This Row],[Source Row]]="","",IF(INDEX(Rider_Input[Calendar Days in Month],Salary_Calculation[[#This Row],[Source Row]])="","",INDEX(Rider_Input[Calendar Days in Month],Salary_Calculation[[#This Row],[Source Row]]))) -> 31 | F7: =IF(Salary_Calculation[[#This Row],[Source Row]]="","",IF(INDEX(Rider_Input[Working Days],Salary_Calculation[[#This Row],[Source Row]])="","",INDEX(Rider_Input[Working Days],Salary_Calculation[[#This Row],[Source Row]]))) -> 12 | G7: =IF(Salary_Calculation[[#This Row],[Source Row]]="","",Std_Orders/Std_Days*N(Salary_Calculation[[#This Row],[Calendar Days]])) -> 465 | H7: =IF(Salary_Calculation[[#This Row],[Source Row]]="","",IF(N(Salary_Calculation[[#This Row],[Calendar Days]])>0,Salary_Calculation[[#This Row],[Monthly Target Orders]]/N(Salary_Calculation[[#This Row],[Calendar Days]])*N(Salary_Calculation[[#This Row],[Working Days]]),0)) -> 180 | I7: =IF(Salary_Calculation[[#This Row],[Source Row]]="","",IF(INDEX(Rider_Input[Completed Orders],Salary_Calculation[[#This Row],[Source Row]])="","",INDEX(Rider_Input[Completed Orders],Salary_Calculation[[#This Row],[Source Row]]))) -> 146 | J7: =IF(Salary_Calculation[[#This Row],[Source Row]]="","",IF(Rate_Method="Fixed rate",Fixed_Rate,IF(N(Salary_Calculation[[#This Row],[Basic Payment]])>0,N(Salary_Calculation[[#This Row],[Basic Payment]])/Std_Orders,0))) -> 4.4444444 | K7: =IF(Salary_Calculation[[#This Row],[Source Row]]="","",MAX(MIN(N(Salary_Calculation[[#This Row],[Completed Orders]]),Salary_Calculation[[#This Row],[Rider Target Orders]]),0)) -> 146 | L7: =IF(Salary_Calculation[[#This Row],[Source Row]]="","",Salary_Calculation[[#This Row],[Orders Counted at Base Rate]]*Salary_Calculation[[#This Row],[Base Order Rate]]) -> 648.88889 | M7: =IF(Salary_Calculation[[#This Row],[Source Row]]="","",MAX(Salary_Calculation[[#This Row],[Rider Target Orders]]-N(Salary_Calculation[[#This Row],[Completed Orders]]),0)) -> 34 | N7: =IF(Salary_Calculation[[#This Row],[Source Row]]="","",Salary_Calculation[[#This Row],[Missing Orders]]*Missing_Rate) -> 238 | O7: =IF(Salary_Calculation[[#This Row],[Source Row]]="","",MAX(N(Salary_Calculation[[#This Row],[Completed Orders]])-Salary_Calculation[[#This Row],[Rider Target Orders]],0)) -> 0 | P7: =IF(Salary_Calculation[[#This Row],[Source Row]]="","",Salary_Calculation[[#This Row],[Extra Orders]]*Extra_Rate) -> 0 | Q7: =IF(Salary_Calculation[[#This Row],[Source Row]]="","",MAX(Salary_Calculation[[#This Row],[Salary Before Other Deductions]],0)) -> 410.88889 | R7: =IF(Salary_Calculation[[#This Row],[Source Row]]="","",N(INDEX(Rider_Input[missed_days_penalty],Salary_Calculation[[#This Row],[Source Row]]))) -> 500 | S7: =IF(Salary_Calculation[[#This Row],[Source Row]]="","",N(INDEX(Rider_Input[Rider Balance / محفظة المندوب],Salary_Calculation[[#This Row],[Source Row]]))) -> 192.89 | T7: =IF(Salary_Calculation[[#This Row],[Source Row]]="","",N(INDEX(Rider_Input[stacking_deduction / خصم الطلبات المتعددة],Salary_Calculation[[#This Row],[Source Row]]))) -> 32 | U7: =IF(Salary_Calculation[[#This Row],[Source Row]]="","",N(INDEX(Rider_Input[Other Deductions],Salary_Calculation[[#This Row],[Source Row]]))) -> 0 | V7: =IF(Salary_Calculation[[#This Row],[Source Row]]="","",N(Salary_Calculation[[#This Row],[missed_days_penalty]])+N(Salary_Calculation[[#This Row],[Rider Balance]])+N(Salary_Calculation[[#This Row],[stacking_deduction]])+N(Salary_Calculation[[#This Row],[Other Deductions]])) -> 724.89 | W7: =IF(Salary_Calculation[[#This Row],[Source Row]]="","",ROUND(MAX(Salary_Calculation[[#This Row],[Gross Salary Before Deductions]]-Salary_Calculation[[#This Row],[Total Deductions]],0),2)) -> 0 | X7: =IF(Salary_Calculation[[#This Row],[Source Row]]="","",ROUND(MAX(Salary_Calculation[[#This Row],[Missing-Order Deduction]]-Salary_Calculation[[#This Row],[Earned Salary]],0),2)) -> 0 | Y7: =IF(Salary_Calculation[[#This Row],[Source Row]]="","",IF(Salary_Calculation[[#This Row],[Exception Reason]]<>"","Review Required",IF(N(Salary_Calculation[[#This Row],[Completed Orders]])=0,"No Orders",IF(AND(Salary_Calculation[[#This Row],[Final Salary]]=0,Salary_Calculation[[#This Row],[Total Amount Due from Rider]]>0),"No Salary – Amount Due from Rider",IF(AND(Salary_Calculation[[#This Row],[Total Deductions]]=0,Salary_Calculation[[#This Row],[Missing-Order Deduction]]=0),"Paid in Full","Paid After Deductions"))))) -> No Salary – Amount Due from Rider | Z7: =IF(Salary_Calculation[[#This Row],[Source Row]]="","",IF(INDEX(Rider_Input[Notes],Salary_Calculation[[#This Row],[Source Row]])="","",INDEX(Rider_Input[Notes],Salary_Calculation[[#This Row],[Source Row]]))) | AA7: =IF(Salary_Calculation[[#This Row],[Source Row]]="","",Salary_Calculation[[#This Row],[Earned Salary]]-Salary_Calculation[[#This Row],[Missing-Order Deduction]]+Salary_Calculation[[#This Row],[Extra-Order Bonus]]) -> 410.88889 | AB7: =IF(Salary_Calculation[[#This Row],[Source Row]]="","",ROUND(Salary_Calculation[[#This Row],[Negative Balance / Amount Due from Rider]]+MAX(Salary_Calculation[[#This Row],[Total Deductions]]-Salary_Calculation[[#This Row],[Gross Salary Before Deductions]],0),2)) -> 314 | AC7: =IF(Salary_Calculation[[#This Row],[Source Row]]="","",IF(NOT(ISNUMBER(Salary_Calculation[[#This Row],[Salary Month]])),"Salary month missing; ","")&IF(Salary_Calculation[[#This Row],[Rider ID]]="","Rider ID missing; ","")&IF(Salary_Calculation[[#This Row],[Rider Name]]="","Rider name missing; ","")&IF(NOT(ISNUMBER(Salary_Calculation[[#This Row],[Basic Payment]])),"Basic payment missing; ",IF(Salary_Calculation[[#This Row],[Basic Payment]]<=0,"Basic payment zero or negative; ",""))&IF(NOT(ISNUMBER(Salary_Calculation[[#This Row],[Calendar Days]])),"Calendar days missing; ",IF(OR(Salary_Calculation[[#This Row],[Calendar Days]]<28,Salary_Calculation[[#This Row],[Calendar Days]]>31,Salary_Calculation[[#This Row],[Calendar Days]]<>INT(Salary_Calculation[[#This Row],[Calendar Days]])),"Calendar days not 28/29/30/31; ",IF(ISNUMBER(Salary_Calculation[[#This Row],[Salary Month]]),IF(DAY(EOMONTH(Salary_Calculation[[#This Row],[Salary Month]],0))<>Salary_Calculation[[#This Row],[Calendar Days]],"Calendar days differ from actual days in month; ",""),"")))&IF(NOT(ISNUMBER(Salary_Calculation[[#This Row],[Working Days]])),"Working days missing; ",IF(Salary_Calculation[[#This Row],[Working Days]]<0,"Working days negative; ",IF(AND(ISNUMBER(Salary_Calculation[[#This Row],[Calendar Days]]),Salary_Calculation[[#This Row],[Working Days]]>Salary_Calculation[[#This Row],[Calendar Days]]),"Working days exceed calendar days; ","")))&IF(NOT(ISNUMBER(Salary_Calculation[[#This Row],[Completed Orders]])),"Completed orders missing; ",IF(Salary_Calculation[[#This Row],[Completed Orders]]<0,"Completed orders negative; ",""))&IF(MIN(Salary_Calculation[[#This Row],[missed_days_penalty]],Salary_Calculation[[#This Row],[Rider Balance]],Salary_Calculation[[#This Row],[stacking_deduction]],Salary_Calculation[[#This Row],[Other Deductions]])<0,"Negative deduction entered; ","")&IF(Salary_Calculation[[#This Row],[Rider ID]]="","",IF(COUNTIFS(Rider_Input[Rider ID],Salary_Calculation[[#This Row],[Rider ID]],Rider_Input[Salary Month],Salary_Calculation[[#This Row],[Salary Month]])>1,"Duplicate Rider ID and month; ",""))) | AD7: =IF(Salary_Calculation[[#This Row],[Source Row]]="","",Salary_Calculation[[#This Row],[Rider Target Orders]]*Salary_Calculation[[#This Row],[Base Order Rate]]) -> 800 | AE7: =IF(SUMPRODUCT(--(LEN(INDEX(Rider_Input[#Data],ROW()-ROW(Salary_Calculation[#Headers]),0))>0))=0,"",ROW()-ROW(Salary_Calculation[#Headers])) -> 6
